Workbook
Name acct_early: 'Control & Parameters'!$C$52
Name acct_target: 'Control & Parameters'!$C$57
Name acq_month: 'Control & Parameters'!$C$91
Name acq_year1: 'Control & Parameters'!$C$67
Name acq_year2: 'Control & Parameters'!$C$68
Name acq_year3: 'Control & Parameters'!$C$69
Name admin_per_prop: 'Control & Parameters'!$C$60
Name avg_price: 'Control & Parameters'!$C$45
Name base_calendar_year: 'Control & Parameters'!$C$11
Name beq_baseline: 'Control & Parameters'!$C$37
Name beq_growth_mult: 'Control & Parameters'!$C$39
Name board_early: 'Control & Parameters'!$C$51
Name board_target: 'Control & Parameters'!$C$56
Name constrain_growth: 'Control & Parameters'!$C$89
Name conveyancing: 'Control & Parameters'!$C$47
Name cpi_general: 'Control & Parameters'!$C$8
Name cs_baseline_issue: 'Control & Parameters'!$C$32
Name cs_dividend_rate: 'Control & Parameters'!$C$28
Name cs_issue_cost_pct: 'Control & Parameters'!$C$31
Name cs_max_pct_capital: 'Control & Parameters'!$C$29
Name cs_takeup_mult: 'Control & Parameters'!$C$33
Name cs_withdrawal_rate: 'Control & Parameters'!$C$34
Name cs_withdrawal_years: 'Control & Parameters'!$C$30
Name ct_exempt_toggle: 'Control & Parameters'!$C$84
Name ct_rate: 'Control & Parameters'!$C$85
Name debt_pay_freq: 'Control & Parameters'!$C$92
Name div_month: 'Control & Parameters'!$C$93
Name fca_early: 'Control & Parameters'!$C$53
Name fca_target: 'Control & Parameters'!$C$58
Name founding_capital: 'Control & Parameters'!$C$38
Name gift_aid_rate: 'Control & Parameters'!$C$87
Name gift_aid_toggle: 'Control & Parameters'!$C$86
Name gift_baseline: 'Control & Parameters'!$C$36
Name gross_yield: 'Control & Parameters'!$C$41
Name hpi_premium: 'Control & Parameters'!$C$10
Name hpi_shock_pct: 'Control & Parameters'!$C$80
Name hpi_shock_year: 'Control & Parameters'!$C$79
Name ins_early: 'Control & Parameters'!$C$54
Name ins_target: 'Control & Parameters'!$C$59
Name lc_share: 'Control & Parameters'!$C$42
Name logistic_ceiling: 'Control & Parameters'!$C$72
Name logistic_dbl_yrs: 'Control & Parameters'!$C$73
Name logistic_floor: 'Control & Parameters'!$C$71
Name logistic_start_yr: 'Control & Parameters'!$C$70
Name maint_per_prop: 'Control & Parameters'!$C$76
Name min_cash_buffer: 'Control & Parameters'!$C$65
Name pf_coupon_spread: 'Control & Parameters'!$C$17
Name pf_fund_op_margin: 'Control & Parameters'!$C$15
Name pf_fund_reg_charge: 'Control & Parameters'!$C$16
Name pf_index_label: 'Control & Parameters'!$C$13
Name pf_invest_phase_yrs: 'Control & Parameters'!$C$19
Name pf_investor_rate: 'Control & Parameters'!$C$14
Name pf_ltv_limit: 'Control & Parameters'!$C$22
Name pf_max_raise: 'Control & Parameters'!$C$18
Name pf_refi_amort_yrs: 'Control & Parameters'!$C$26
Name pf_refi_rate: 'Control & Parameters'!$C$25
Name pf_refi_toggle: 'Control & Parameters'!$C$23
Name pf_refi_year: 'Control & Parameters'!$C$24
Name pf_release_rate: 'Control & Parameters'!$C$21
Name pf_release_start_yr: 'Control & Parameters'!$C$20

Sheet Control & Parameters
A1: STROUD LAND COMMONS — CONTROL & PARAMETERS
A2: Single source of truth. Blue = input. Green = scenario-selected live value referenced by every other sheet.
A3: Version 2.1 — closed-end Tontine annuity mechanics and independent-review remediation. Last updated 26 July 2026.
A4: SCENARIO (set on Dashboard) | C4: =Dashboard!$C$3 -> Base
A5: Scenario ID | C5: =MATCH($C$4,{"Base";"Optimistic";"Stress"},0) -> 1
A6: PARAMETER | B6: UNIT | C6: LIVE VALUE | E6: Base | F6: Optimistic | G6: Stress
A7: MACRO & INDEXATION
A8: General CPI inflation | B8: % p.a. | C8: =CHOOSE($C$5,E8,F8,G8) -> 0.025 | E8: 0.025 | F8: 0.02 | G8: 0.045
A9: Rent inflation | B9: % p.a. | C9: =CHOOSE($C$5,E9,F9,G9) -> 0.025 | E9: 0.025 | F9: 0.03 | G9: =$E9 -> 0.025
A10: HPI premium over CPI | B10: % p.a. | C10: =CHOOSE($C$5,E10,F10,G10) -> 0.01 | E10: 0.01 | F10: 0.02 | G10: =$E10 -> 0.01
A11: Base calendar year (Year 1) | B11: year | C11: =CHOOSE($C$5,E11,F11,G11) -> 2026 | E11: 2026 | F11: =$E11 -> 2026 | G11: =$E11 -> 2026
A12: TONTINE FUND — CLOSED-END LIFETIME ANNUITY MUTUAL
A13: Indexation basis (principal and coupon) | B13: text | C13: =CHOOSE($C$5,E13,F13,G13) -> CPI | E13: CPI | F13: =$E13 -> CPI | G13: =$E13 -> CPI
A14: Target investor annuity rate — spread over index | B14: % p.a. | C14: =CHOOSE($C$5,E14,F14,G14) -> 0.03 | E14: 0.03 | F14: 0.03 | G14: 0.03
A15: Fund operating cost margin | B15: % p.a. | C15: =CHOOSE($C$5,E15,F15,G15) -> 0.005 | E15: 0.005 | F15: =$E15 -> 0.005 | G15: =$E15 -> 0.005
A16: Fund regulatory capital charge | B16: % p.a. | C16: =CHOOSE($C$5,E16,F16,G16) -> 0.0025 | E16: 0.0025 | F16: =$E16 -> 0.0025 | G16: =$E16 -> 0.0025
A17: Implied SLC coupon — spread over index (derived) | B17: % p.a. | C17: =CHOOSE($C$5,E17,F17,G17) -> 0.0375 | E17: =SUM(E14:E16) -> 0.0375 | F17: =SUM(F14:F16) -> 0.0375 | G17: =SUM(G14:G16) -> 0.0375
A18: Tontine maximum raise | B18: £ | C18: =CHOOSE($C$5,E18,F18,G18) -> 50000000 | E18: 50000000 | F18: =$E18 -> 50000000 | G18: =$E18 -> 50000000
A19: Investment phase duration | B19: years | C19: =CHOOSE($C$5,E19,F19,G19) -> 10 | E19: 10 | F19: =$E19 -> 10 | G19: =$E19 -> 10
A20: Release phase start year | B20: model year | C20: =CHOOSE($C$5,E20,F20,G20) -> 25 | E20: 25 | F20: =$E20 -> 25 | G20: =$E20 -> 25
A21: Annual release rate | B21: % of outstanding balance p.a. | C21: =CHOOSE($C$5,E21,F21,G21) -> 0.06 | E21: 0.06 | F21: =$E21 -> 0.06 | G21: =$E21 -> 0.06
A22: LTV limit | B22: % of portfolio value | C22: =CHOOSE($C$5,E22,F22,G22) -> 0.7 | E22: 0.7 | F22: 0.75 | G22: =$E22 -> 0.7
A23: Refinance into commercial mortgage? (1 = Yes) | B23: 1 / 0 | C23: =CHOOSE($C$5,E23,F23,G23) -> 0 | E23: 0 | F23: =$E23 -> 0 | G23: =$E23 -> 0
A24: Refinancing year | B24: model year | C24: =CHOOSE($C$5,E24,F24,G24) -> 26 | E24: 26 | F24: =$E24 -> 26 | G24: =$E24 -> 26
A25: Commercial mortgage rate | B25: % p.a. | C25: =CHOOSE($C$5,E25,F25,G25) -> 0.055 | E25: 0.055 | F25: 0.045 | G25: =$E25 -> 0.055
A26: Commercial mortgage amortisation | B26: years | C26: =CHOOSE($C$5,E26,F26,G26) -> 25 | E26: 25 | F26: =$E26 -> 25 | G26: =$E26 -> 25
A27: COMMUNITY SHARES (JUNIOR DEBT)
A28: Default dividend rate (override per year on Capital & Debt) | B28: % p.a. | C28: =CHOOSE($C$5,E28,F28,G28) -> 0.03 | E28: 0.03 | F28: =$E28 -> 0.03 | G28: =$E28 -> 0.03
A29: Maximum issuance cap | B29: % of total capital | C29: =CHOOSE($C$5,E29,F29,G29) -> 0.2 | E29: 0.2 | F29: =$E29 -> 0.2 | G29: =$E29 -> 0.2
A30: Withdrawal restriction period | B30: years | C30: =CHOOSE($C$5,E30,F30,G30) -> 5 | E30: 5 | F30: =$E30 -> 5 | G30: =$E30 -> 5
A31: Issuance / marketing cost | B31: % of proceeds | C31: =CHOOSE($C$5,E31,F31,G31) -> 0.05 | E31: 0.05 | F31: 0.04 | G31: =$E31 -> 0.05
A32: Baseline annual issuance (real) | B32: £ p.a. | C32: =CHOOSE($C$5,E32,F32,G32) -> 250000 | E32: 250000 | F32: =$E32 -> 250000 | G32: =$E32 -> 250000
A33: Take-up multiplier | B33: x | C33: =CHOOSE($C$5,E33,F33,G33) -> 1 | E33: 1 | F33: 1.5 | G33: 0.5
A34: Annual withdrawal rate on eligible shares | B34: % p.a. | C34: =CHOOSE($C$5,E34,F34,G34) -> 0.02 | E34: 0.02 | F34: 0.01 | G34: =$E34 -> 0.02
A35: BEQUESTS & GIFTS
A36: Cash gifts from living donors (Gift Aid eligible) | B36: £ p.a. | C36: =CHOOSE($C$5,E36,F36,G36) -> 40000 | E36: 40000 | F36: 60000 | G36: =$E36 -> 40000
A37: Bequests from estates (not Gift Aid eligible) | B37: £ p.a. | C37: =CHOOSE($C$5,E37,F37,G37) -> 60000 | E37: 60000 | F37: 90000 | G37: =$E37 -> 60000
A38: Founding capital injection (Year 1 only) | B38: £ | C38: =CHOOSE($C$5,E38,F38,G38) -> 150000 | E38: 150000 | F38: =$E38 -> 150000 | G38: =$E38 -> 150000
A39: Real growth multiplier | B39: % p.a. | C39: =CHOOSE($C$5,E39,F39,G39) -> 0 | E39: 0 | F39: 0.02 | G39: =$E39 -> 0
A40: RENT & YIELD
A41: Gross rental yield | B41: % of purchase price | C41: =CHOOSE($C$5,E41,F41,G41) -> 0.05 | E41: 0.05 | F41: 0.055 | G41: =$E41 -> 0.05
A42: Land Commons share of gross rent | B42: % | C42: =CHOOSE($C$5,E42,F42,G42) -> 0.8 | E42: 0.8 | F42: 0.85 | G42: =$E42 -> 0.8
A43: Void rate | B43: % | C43: =CHOOSE($C$5,E43,F43,G43) -> 0.05 | E43: 0.05 | F43: 0.03 | G43: 0.15
A44: ACQUISITION
A45: Average property price (real, Year 1) | B45: £ | C45: =CHOOSE($C$5,E45,F45,G45) -> 280000 | E45: 280000 | F45: =$E45 -> 280000 | G45: =$E45 -> 280000
A46: SDLT rate (charitable relief) | B46: % of price | C46: =CHOOSE($C$5,E46,F46,G46) -> 0 | E46: 0 | F46: =$E46 -> 0 | G46: =$E46 -> 0
A47: Conveyancing per property (real) | B47: £ | C47: =CHOOSE($C$5,E47,F47,G47) -> 2500 | E47: 2500 | F47: =$E47 -> 2500 | G47: =$E47 -> 2500
A48: Survey per property (real) | B48: £ | C48: =CHOOSE($C$5,E48,F48,G48) -> 800 | E48: 800 | F48: =$E48 -> 800 | G48: =$E48 -> 800
A49: Initial retrofit per property (real) | B49: £ | C49: =CHOOSE($C$5,E49,F49,G49) -> 5000 | E49: 5000 | F49: =$E49 -> 5000 | G49: =$E49 -> 5000
A50: ADMIN COSTS — EARLY YEARS (real)
A51: Board remuneration | B51: £ p.a. | C51: =CHOOSE($C$5,E51,F51,G51) -> 0 | E51: 0 | F51: =$E51 -> 0 | G51: =$E51 -> 0
A52: Accounting & audit | B52: £ p.a. | C52: =CHOOSE($C$5,E52,F52,G52) -> 3000 | E52: 3000 | F52: =$E52 -> 3000 | G52: =$E52 -> 3000
A53: FCA & annual reporting | B53: £ p.a. | C53: =CHOOSE($C$5,E53,F53,G53) -> 1500 | E53: 1500 | F53: =$E53 -> 1500 | G53: =$E53 -> 1500
A54: Insurance | B54: £ p.a. | C54: =CHOOSE($C$5,E54,F54,G54) -> 1000 | E54: 1000 | F54: =$E54 -> 1000 | G54: =$E54 -> 1000
A55: ADMIN COSTS — TARGET (real)
A56: Board remuneration | B56: £ p.a. | C56: =CHOOSE($C$5,E56,F56,G56) -> 12000 | E56: 12000 | F56: =$E56 -> 12000 | G56: =$E56 -> 12000
A57: Accounting & audit | B57: £ p.a. | C57: =CHOOSE($C$5,E57,F57,G57) -> 8000 | E57: 8000 | F57: =$E57 -> 8000 | G57: =$E57 -> 8000
A58: FCA & annual reporting | B58: £ p.a. | C58: =CHOOSE($C$5,E58,F58,G58) -> 3000 | E58: 3000 | F58: =$E58 -> 3000 | G58: =$E58 -> 3000
A59: Insurance | B59: £ p.a. | C59: =CHOOSE($C$5,E59,F59,G59) -> 2000 | E59: 2000 | F59: =$E59 -> 2000 | G59: =$E59 -> 2000
A60: Variable admin per property | B60: £ / property / yr | C60: =CHOOSE($C$5,E60,F60,G60) -> 150 | E60: 150 | F60: =$E60 -> 150 | G60: =$E60 -> 150
A61: RESERVES
A62: Target reserve | B62: months of debt service | C62: =CHOOSE($C$5,E62,F62,G62) -> 6 | E62: 6 | F62: =$E62 -> 6 | G62: =$E62 -> 6
A63: Minimum covenant | B63: months of debt service | C63: =CHOOSE($C$5,E63,F63,G63) -> 3 | E63: 3 | F63: =$E63 -> 3 | G63: =$E63 -> 3
A64: Target reserve fully built by | B64: model year | C64: =CHOOSE($C$5,E64,F64,G64) -> 10 | E64: 10 | F64: =$E64 -> 10 | G64: =$E64 -> 10
A65: Minimum operating cash buffer | B65: £ | C65: =CHOOSE($C$5,E65,F65,G65) -> 25000 | E65: 25000 | F65: =$E65 -> 25000 | G65: =$E65 -> 25000
A66: GROWTH CURVE
A67: Properties acquired — Year 1 | B67: properties | C67: =CHOOSE($C$5,E67,F67,G67) -> 1 | E67: 1 | F67: =$E67 -> 1 | G67: =$E67 -> 1
A68: Properties acquired — Year 2 | B68: properties | C68: =CHOOSE($C$5,E68,F68,G68) -> 2 | E68: 2 | F68: =$E68 -> 2 | G68: =$E68 -> 2
A69: Properties acquired — Year 3 | B69: properties | C69: =CHOOSE($C$5,E69,F69,G69) -> 3 | E69: 3 | F69: =$E69 -> 3 | G69: =$E69 -> 3
A70: Logistic growth begins | B70: model year | C70: =CHOOSE($C$5,E70,F70,G70) -> 4 | E70: 4 | F70: =$E70 -> 4 | G70: =$E70 -> 4
A71: Logistic floor (min acquisitions p.a.) | B71: properties | C71: =CHOOSE($C$5,E71,F71,G71) -> 3 | E71: 3 | F71: =$E71 -> 3 | G71: =$E71 -> 3
A72: Logistic ceiling (max portfolio) | B72: properties | C72: =CHOOSE($C$5,E72,F72,G72) -> 200 | E72: 200 | F72: 250 | G72: =$E72 -> 200
A73: Doubling rate | B73: years | C73: =CHOOSE($C$5,E73,F73,G73) -> 4 | E73: 4 | F73: 3 | G73: =$E73 -> 4
A74: CAPEX & MAINTENANCE
A75: Sinking fund contribution | B75: £ / property / yr | C75: =CHOOSE($C$5,E75,F75,G75) -> 1500 | E75: 1500 | F75: =$E75 -> 1500 | G75: =$E75 -> 1500
A76: Structural maintenance spend | B76: £ / property / yr | C76: =CHOOSE($C$5,E76,F76,G76) -> 700 | E76: 700 | F76: =$E76 -> 700 | G76: =$E76 -> 700
A77: Sinking fund investment return | B77: % p.a. | C77: =CHOOSE($C$5,E77,F77,G77) -> 0 | E77: 0 | F77: 0.02 | G77: =$E77 -> 0
A78: MARKET SHOCK OVERRIDES
A79: One-off HPI shock year (0 = none) | B79: model year | C79: =CHOOSE($C$5,E79,F79,G79) -> 0 | E79: 0 | F79: 0 | G79: 5
A80: One-off HPI shock | B80: % | C80: =CHOOSE($C$5,E80,F80,G80) -> -0.2 | E80: -0.2 | F80: 0.1 | G80: =$E80 -> -0.2
A81: Rent shock duration following HPI shock | B81: years | C81: =CHOOSE($C$5,E81,F81,G81) -> 0 | E81: 0 | F81: =$E81 -> 0 | G81: 2
A82: Rent inflation during shock | B82: % p.a. | C82: =CHOOSE($C$5,E82,F82,G82) -> 0 | E82: 0 | F82: =$E82 -> 0 | G82: =$E82 -> 0
A83: TAX & GIFT AID
A84: Corporation tax exempt? (1 = Yes) | B84: 1 / 0 | C84: =CHOOSE($C$5,E84,F84,G84) -> 1 | E84: 1 | F84: =$E84 -> 1 | G84: =$E84 -> 1
A85: Corporation tax rate (if not exempt) | B85: % | C85: =CHOOSE($C$5,E85,F85,G85) -> 0.25 | E85: 0.25 | F85: =$E85 -> 0.25 | G85: =$E85 -> 0.25
A86: Gift Aid applicable? (1 = Yes) | B86: 1 / 0 | C86: =CHOOSE($C$5,E86,F86,G86) -> 1 | E86: 1 | F86: =$E86 -> 1 | G86: =$E86 -> 1
A87: Gift Aid recovery rate | B87: % of qualifying gifts | C87: =CHOOSE($C$5,E87,F87,G87) -> 0.25 | E87: 0.25 | F87: =$E87 -> 0.25 | G87: =$E87 -> 0.25
A88: ACQUISITION FUNDING DISCIPLINE
A89: Cap acquisitions at affordable level? (1 = Yes) | B89: 1 / 0 | C89: =CHOOSE($C$5,E89,F89,G89) -> 1 | E89: 1 | F89: =$E89 -> 1 | G89: =$E89 -> 1
A90: MONTHLY CASH FLOW TIMING (YEARS 1–5)
A91: Month in year when acquisitions complete | B91: month (1–12) | C91: =CHOOSE($C$5,E91,F91,G91) -> 12 | E91: 12 | F91: =$E91 -> 12 | G91: =$E91 -> 12
A92: Debt service payments per year | B92: payments p.a. | C92: =CHOOSE($C$5,E92,F92,G92) -> 4 | E92: 4 | F92: =$E92 -> 4 | G92: =$E92 -> 4
A93: Month in year when dividends are paid | B93: month (1–12) | C93: =CHOOSE($C$5,E93,F93,G93) -> 12 | E93: 12 | F93: =$E93 -> 12 | G93: =$E93 -> 12

Sheet Sheet2

Sheet Scenarios
A1: STROUD LAND COMMONS — SCENARIO DEFINITIONS
A2: LIVE MIRROR — every cell below is a formula reading Control & Parameters. Nothing here is an input and nothing here drives the model. To change an assumption, edit the Base, Optimistic or Stress column on Control & Parameters.
A4: Stress scenario per brief: void rate +10pts (15%), CPI +2pts (4.5%), community share take-up halved, a one-off −20% HPI shock in Year 5, and rent growth held at 0% for the two years following that shock.
A6: PARAMETER | B6: UNIT | C6: BASE | D6: OPTIMISTIC | E6: STRESS
A7: =IF('Control & Parameters'!A7="","",'Control & Parameters'!A7) -> MACRO & INDEXATION | B7: =IF('Control & Parameters'!B7="","",'Control & Parameters'!B7) | C7: =IF('Control & Parameters'!E7="","",'Control & Parameters'!E7) | D7: =IF('Control & Parameters'!F7="","",'Control & Parameters'!F7) | E7: =IF('Control & Parameters'!G7="","",'Control & Parameters'!G7)
A8: =IF('Control & Parameters'!A8="","",'Control & Parameters'!A8) -> General CPI inflation | B8: =IF('Control & Parameters'!B8="","",'Control & Parameters'!B8) -> % p.a. | C8: =IF('Control & Parameters'!E8="","",'Control & Parameters'!E8) -> 0.025 | D8: =IF('Control & Parameters'!F8="","",'Control & Parameters'!F8) -> 0.02 | E8: =IF('Control & Parameters'!G8="","",'Control & Parameters'!G8) -> 0.045
A9: =IF('Control & Parameters'!A9="","",'Control & Parameters'!A9) -> Rent inflation | B9: =IF('Control & Parameters'!B9="","",'Control & Parameters'!B9) -> % p.a. | C9: =IF('Control & Parameters'!E9="","",'Control & Parameters'!E9) -> 0.025 | D9: =IF('Control & Parameters'!F9="","",'Control & Parameters'!F9) -> 0.03 | E9: =IF('Control & Parameters'!G9="","",'Control & Parameters'!G9) -> 0.025
A10: =IF('Control & Parameters'!A10="","",'Control & Parameters'!A10) -> HPI premium over CPI | B10: =IF('Control & Parameters'!B10="","",'Control & Parameters'!B10) -> % p.a. | C10: =IF('Control & Parameters'!E10="","",'Control & Parameters'!E10) -> 0.01 | D10: =IF('Control & Parameters'!F10="","",'Control & Parameters'!F10) -> 0.02 | E10: =IF('Control & Parameters'!G10="","",'Control & Parameters'!G10) -> 0.01
A11: =IF('Control & Parameters'!A11="","",'Control & Parameters'!A11) -> Base calendar year (Year 1) | B11: =IF('Control & Parameters'!B11="","",'Control & Parameters'!B11) -> year | C11: =IF('Control & Parameters'!E11="","",'Control & Parameters'!E11) -> 2026 | D11: =IF('Control & Parameters'!F11="","",'Control & Parameters'!F11) -> 2026 | E11: =IF('Control & Parameters'!G11="","",'Control & Parameters'!G11) -> 2026
A12: =IF('Control & Parameters'!A12="","",'Control & Parameters'!A12) -> TONTINE FUND — CLOSED-END LIFETIME ANNUITY MUTUAL | B12: =IF('Control & Parameters'!B12="","",'Control & Parameters'!B12) | C12: =IF('Control & Parameters'!E12="","",'Control & Parameters'!E12) | D12: =IF('Control & Parameters'!F12="","",'Control & Parameters'!F12) | E12: =IF('Control & Parameters'!G12="","",'Control & Parameters'!G12)
A13: =IF('Control & Parameters'!A13="","",'Control & Parameters'!A13) -> Indexation basis (principal and coupon) | B13: =IF('Control & Parameters'!B13="","",'Control & Parameters'!B13) -> text | C13: =IF('Control & Parameters'!E13="","",'Control & Parameters'!E13) -> CPI | D13: =IF('Control & Parameters'!F13="","",'Control & Parameters'!F13) -> CPI | E13: =IF('Control & Parameters'!G13="","",'Control & Parameters'!G13) -> CPI
A14: =IF('Control & Parameters'!A14="","",'Control & Parameters'!A14) -> Target investor annuity rate — spread over index | B14: =IF('Control & Parameters'!B14="","",'Control & Parameters'!B14) -> % p.a. | C14: =IF('Control & Parameters'!E14="","",'Control & Parameters'!E14) -> 0.03 | D14: =IF('Control & Parameters'!F14="","",'Control & Parameters'!F14) -> 0.03 | E14: =IF('Control & Parameters'!G14="","",'Control & Parameters'!G14) -> 0.03
A15: =IF('Control & Parameters'!A15="","",'Control & Parameters'!A15) -> Fund operating cost margin | B15: =IF('Control & Parameters'!B15="","",'Control & Parameters'!B15) -> % p.a. | C15: =IF('Control & Parameters'!E15="","",'Control & Parameters'!E15) -> 0.005 | D15: =IF('Control & Parameters'!F15="","",'Control & Parameters'!F15) -> 0.005 | E15: =IF('Control & Parameters'!G15="","",'Control & Parameters'!G15) -> 0.005
A16: =IF('Control & Parameters'!A16="","",'Control & Parameters'!A16) -> Fund regulatory capital charge | B16: =IF('Control & Parameters'!B16="","",'Control & Parameters'!B16) -> % p.a. | C16: =IF('Control & Parameters'!E16="","",'Control & Parameters'!E16) -> 0.0025 | D16: =IF('Control & Parameters'!F16="","",'Control & Parameters'!F16) -> 0.0025 | E16: =IF('Control & Parameters'!G16="","",'Control & Parameters'!G16) -> 0.0025
A17: =IF('Control & Parameters'!A17="","",'Control & Parameters'!A17) -> Implied SLC coupon — spread over index (derived) | B17: =IF('Control & Parameters'!B17="","",'Control & Parameters'!B17) -> % p.a. | C17: =IF('Control & Parameters'!E17="","",'Control & Parameters'!E17) -> 0.0375 | D17: =IF('Control & Parameters'!F17="","",'Control & Parameters'!F17) -> 0.0375 | E17: =IF('Control & Parameters'!G17="","",'Control & Parameters'!G17) -> 0.0375
A18: =IF('Control & Parameters'!A18="","",'Control & Parameters'!A18) -> Tontine maximum raise | B18: =IF('Control & Parameters'!B18="","",'Control & Parameters'!B18) -> £ | C18: =IF('Control & Parameters'!E18="","",'Control & Parameters'!E18) -> 50000000 | D18: =IF('Control & Parameters'!F18="","",'Control & Parameters'!F18) -> 50000000 | E18: =IF('Control & Parameters'!G18="","",'Control & Parameters'!G18) -> 50000000
... A93: =IF('Control & Parameters'!A93="","",'Control & Parameters'!A93) -> Month in year when dividends are paid | B93: =IF('Control & Parameters'!B93="","",'Control & Parameters'!B93) -> month (1–12) | C93: =IF('Control & Parameters'!E93="","",'Control & Parameters'!E93) -> 12 | D93: =IF('Control & Parameters'!F93="","",'Control & Parameters'!F93) -> 12 | E93: =IF('Control & Parameters'!G93="","",'Control & Parameters'!G93) -> 12

Sheet Macro & Indexation
A1: MACRO & INDEXATION
A2: All index series start at 1.00 in Year 1. HPI = CPI + premium, plus one-off shock, with a manual override row.
A6: Model year | D6: 1 | E6: 2 | F6: 3 | G6: 4 | H6: 5 | I6: 6 | J6: 7 | K6: 8 | L6: 9 | M6: 10 | N6: 11 | O6: 12 | P6: 13 | Q6: 14 | R6: 15 | S6: 16 | T6: 17 | U6: 18 | V6: 19 | W6: 20 | X6: 21 | Y6: 22 | Z6: 23 | AA6: 24 | AB6: 25 | AC6: 26 | AD6: 27 | AE6: 28 | AF6: 29 | AG6: 30 | AH6: 31 | AI6: 32 | AJ6: 33 | AK6: 34 | AL6: 35 | AM6: 36 | AN6: 37 | AO6: 38 | AP6: 39 | AQ6: 40 | AR6: 41 | AS6: 42 | AT6: 43 | AU6: 44 | AV6: 45 | AW6: 46 | AX6: 47 | AY6: 48 | AZ6: 49 | BA6: 50
A7: Calendar year | D7: =base_calendar_year+D$6-1 -> 2026 | E7: =base_calendar_year+E$6-1 -> 2027 | F7: =base_calendar_year+F$6-1 -> 2028 | G7: =base_calendar_year+G$6-1 -> 2029 | H7: =base_calendar_year+H$6-1 -> 2030 | I7: =base_calendar_year+I$6-1 -> 2031 | J7: =base_calendar_year+J$6-1 -> 2032 | K7: =base_calendar_year+K$6-1 -> 2033 | ... BA7: =base_calendar_year+BA$6-1 -> 2075
A9: General CPI inflation | B9: % p.a. | D9: =cpi_general -> 0.025 | E9: =cpi_general -> 0.025 | F9: =cpi_general -> 0.025 | G9: =cpi_general -> 0.025 | H9: =cpi_general -> 0.025 | I9: =cpi_general -> 0.025 | J9: =cpi_general -> 0.025 | K9: =cpi_general -> 0.025 | ... BA9: =cpi_general -> 0.025
A10: CPI index | B10: Year 1 = 1.00 | D10: =IF(D$6=1,1,C10*(1+D9)) -> 1 | E10: =IF(E$6=1,1,D10*(1+E9)) -> 1.025 | F10: =IF(F$6=1,1,E10*(1+F9)) -> 1.050625 | G10: =IF(G$6=1,1,F10*(1+G9)) -> 1.0768906 | H10: =IF(H$6=1,1,G10*(1+H9)) -> 1.1038129 | I10: =IF(I$6=1,1,H10*(1+I9)) -> 1.1314082 | J10: =IF(J$6=1,1,I10*(1+J9)) -> 1.1596934 | K10: =IF(K$6=1,1,J10*(1+K9)) -> 1.1886858 | ... BA10: =IF(BA$6=1,1,AZ10*(1+BA9)) -> 3.3532768
A11: Rent inflation (shock-adjusted) | B11: % p.a. | D11: =IF(AND(rent_shock_years>0,hpi_shock_year>0,D$6>=hpi_shock_year,D$6<hpi_shock_year+rent_shock_years),rent_shock_rate,rent_inflation) -> 0.025 | E11: =IF(AND(rent_shock_years>0,hpi_shock_year>0,E$6>=hpi_shock_year,E$6<hpi_shock_year+rent_shock_years),rent_shock_rate,rent_inflation) -> 0.025 | F11: =IF(AND(rent_shock_years>0,hpi_shock_year>0,F$6>=hpi_shock_year,F$6<hpi_shock_year+rent_shock_years),rent_shock_rate,rent_inflation) -> 0.025 | G11: =IF(AND(rent_shock_years>0,hpi_shock_year>0,G$6>=hpi_shock_year,G$6<hpi_shock_year+rent_shock_years),rent_shock_rate,rent_inflation) -> 0.025 | H11: =IF(AND(rent_shock_years>0,hpi_shock_year>0,H$6>=hpi_shock_year,H$6<hpi_shock_year+rent_shock_years),rent_shock_rate,rent_inflation) -> 0.025 | I11: =IF(AND(rent_shock_years>0,hpi_shock_year>0,I$6>=hpi_shock_year,I$6<hpi_shock_year+rent_shock_years),rent_shock_rate,rent_inflation) -> 0.025 | J11: =IF(AND(rent_shock_years>0,hpi_shock_year>0,J$6>=hpi_shock_year,J$6<hpi_shock_year+rent_shock_years),rent_shock_rate,rent_inflation) -> 0.025 | K11: =IF(AND(rent_shock_years>0,hpi_shock_year>0,K$6>=hpi_shock_year,K$6<hpi_shock_year+rent_shock_years),rent_shock_rate,rent_inflation) -> 0.025 | ... BA11: =IF(AND(rent_shock_years>0,hpi_shock_year>0,BA$6>=hpi_shock_year,BA$6<hpi_shock_year+rent_shock_years),rent_shock_rate,rent_inflation) -> 0.025
A12: Rent index | B12: Year 1 = 1.00 | D12: =IF(D$6=1,1,C12*(1+D11)) -> 1 | E12: =IF(E$6=1,1,D12*(1+E11)) -> 1.025 | F12: =IF(F$6=1,1,E12*(1+F11)) -> 1.050625 | G12: =IF(G$6=1,1,F12*(1+G11)) -> 1.0768906 | H12: =IF(H$6=1,1,G12*(1+H11)) -> 1.1038129 | I12: =IF(I$6=1,1,H12*(1+I11)) -> 1.1314082 | J12: =IF(J$6=1,1,I12*(1+J11)) -> 1.1596934 | K12: =IF(K$6=1,1,J12*(1+K11)) -> 1.1886858 | ... BA12: =IF(BA$6=1,1,AZ12*(1+BA11)) -> 3.3532768
A13: HPI — base rate | B13: CPI + premium | D13: =cpi_general+hpi_premium -> 0.035 | E13: =cpi_general+hpi_premium -> 0.035 | F13: =cpi_general+hpi_premium -> 0.035 | G13: =cpi_general+hpi_premium -> 0.035 | H13: =cpi_general+hpi_premium -> 0.035 | I13: =cpi_general+hpi_premium -> 0.035 | J13: =cpi_general+hpi_premium -> 0.035 | K13: =cpi_general+hpi_premium -> 0.035 | ... BA13: =cpi_general+hpi_premium -> 0.035
A14: HPI — parameterised one-off shock | B14: from Control | D14: =IF(AND(hpi_shock_year>0,D$6=hpi_shock_year),hpi_shock_pct,0) -> 0 | E14: =IF(AND(hpi_shock_year>0,E$6=hpi_shock_year),hpi_shock_pct,0) -> 0 | F14: =IF(AND(hpi_shock_year>0,F$6=hpi_shock_year),hpi_shock_pct,0) -> 0 | G14: =IF(AND(hpi_shock_year>0,G$6=hpi_shock_year),hpi_shock_pct,0) -> 0 | H14: =IF(AND(hpi_shock_year>0,H$6=hpi_shock_year),hpi_shock_pct,0) -> 0 | I14: =IF(AND(hpi_shock_year>0,I$6=hpi_shock_year),hpi_shock_pct,0) -> 0 | J14: =IF(AND(hpi_shock_year>0,J$6=hpi_shock_year),hpi_shock_pct,0) -> 0 | K14: =IF(AND(hpi_shock_year>0,K$6=hpi_shock_year),hpi_shock_pct,0) -> 0 | ... BA14: =IF(AND(hpi_shock_year>0,BA$6=hpi_shock_year),hpi_shock_pct,0) -> 0
A15: HPI — manual override (blank = use above) | B15: INPUT
A16: HPI — effective rate | B16: % p.a. | D16: =IF(D15<>"",D15,D13+D14) -> 0.035 | E16: =IF(E15<>"",E15,E13+E14) -> 0.035 | F16: =IF(F15<>"",F15,F13+F14) -> 0.035 | G16: =IF(G15<>"",G15,G13+G14) -> 0.035 | H16: =IF(H15<>"",H15,H13+H14) -> 0.035 | I16: =IF(I15<>"",I15,I13+I14) -> 0.035 | J16: =IF(J15<>"",J15,J13+J14) -> 0.035 | K16: =IF(K15<>"",K15,K13+K14) -> 0.035 | ... BA16: =IF(BA15<>"",BA15,BA13+BA14) -> 0.035
A17: House price index (HPI) | B17: Year 1 = 1.00 | D17: =IF(D$6=1,1,C17*(1+D16)) -> 1 | E17: =IF(E$6=1,1,D17*(1+E16)) -> 1.035 | F17: =IF(F$6=1,1,E17*(1+F16)) -> 1.071225 | G17: =IF(G$6=1,1,F17*(1+G16)) -> 1.1087179 | H17: =IF(H$6=1,1,G17*(1+H16)) -> 1.147523 | I17: =IF(I$6=1,1,H17*(1+I16)) -> 1.1876863 | J17: =IF(J$6=1,1,I17*(1+J16)) -> 1.2292553 | K17: =IF(K$6=1,1,J17*(1+K16)) -> 1.2722793 | ... BA17: =IF(BA$6=1,1,AZ17*(1+BA16)) -> 5.3960646
A19: Average property price (indexed) | B19: £ | D19: =avg_price*D17 -> 280000 | E19: =avg_price*E17 -> 289800 | F19: =avg_price*F17 -> 299943 | G19: =avg_price*G17 -> 310441 | H19: =avg_price*H17 -> 321306.44 | I19: =avg_price*I17 -> 332552.17 | J19: =avg_price*J17 -> 344191.49 | K19: =avg_price*K17 -> 356238.19 | ... BA19: =avg_price*BA17 -> 1510898.1
A20: Cost inflation index | B20: CPI index | D20: =D10 -> 1 | E20: =E10 -> 1.025 | F20: =F10 -> 1.050625 | G20: =G10 -> 1.0768906 | H20: =H10 -> 1.1038129 | I20: =I10 -> 1.1314082 | J20: =J10 -> 1.1596934 | K20: =K10 -> 1.1886858 | ... BA20: =BA10 -> 3.3532768

Sheet Growth Engine
A1: GROWTH ENGINE — ACQUISITIONS & ADMIN COST SCALING
A2: Years 1-3: absolute acquisitions. Year 4+: logistic S-curve on the cumulative portfolio (floor / ceiling / doubling rate).
A4: Logistic intrinsic growth rate r = LN(2) / doubling years | B4: r | C4: =LN(2)/logistic_dbl_yrs -> 0.1732868
A6: Model year | D6: 1 | E6: 2 | F6: 3 | G6: 4 | H6: 5 | I6: 6 | J6: 7 | K6: 8 | L6: 9 | M6: 10 | N6: 11 | O6: 12 | P6: 13 | Q6: 14 | R6: 15 | S6: 16 | T6: 17 | U6: 18 | V6: 19 | W6: 20 | X6: 21 | Y6: 22 | Z6: 23 | AA6: 24 | AB6: 25 | AC6: 26 | AD6: 27 | AE6: 28 | AF6: 29 | AG6: 30 | AH6: 31 | AI6: 32 | AJ6: 33 | AK6: 34 | AL6: 35 | AM6: 36 | AN6: 37 | AO6: 38 | AP6: 39 | AQ6: 40 | AR6: 41 | AS6: 42 | AT6: 43 | AU6: 44 | AV6: 45 | AW6: 46 | AX6: 47 | AY6: 48 | AZ6: 49 | BA6: 50
A7: Calendar year | D7: =base_calendar_year+D$6-1 -> 2026 | E7: =base_calendar_year+E$6-1 -> 2027 | F7: =base_calendar_year+F$6-1 -> 2028 | G7: =base_calendar_year+G$6-1 -> 2029 | H7: =base_calendar_year+H$6-1 -> 2030 | I7: =base_calendar_year+I$6-1 -> 2031 | J7: =base_calendar_year+J$6-1 -> 2032 | K7: =base_calendar_year+K$6-1 -> 2033 | ... BA7: =base_calendar_year+BA$6-1 -> 2075
A9: Portfolio — opening | B9: properties | D9: =0 -> 0 | E9: =D11 -> 1 | F9: =E11 -> 3 | G9: =F11 -> 6 | H9: =G11 -> 9 | I9: =H11 -> 12 | J9: =I11 -> 15 | K9: =J11 -> 18 | L9: =K11 -> 21 | ... BA9: =AZ11 -> 48
A10: Properties acquired in year | B10: properties | D10: =MIN(D26,D25) -> 1 | E10: =MIN(E26,E25) -> 2 | F10: =MIN(F26,F25) -> 3 | G10: =MIN(G26,G25) -> 3 | H10: =MIN(H26,H25) -> 3 | I10: =MIN(I26,I25) -> 3 | J10: =MIN(J26,J25) -> 3 | K10: =MIN(K26,K25) -> 3 | ... BA10: =MIN(BA26,BA25) -> 1
A11: Portfolio — closing | B11: properties | D11: =D9+D10 -> 1 | E11: =E9+E10 -> 3 | F11: =F9+F10 -> 6 | G11: =G9+G10 -> 9 | H11: =H9+H10 -> 12 | I11: =I9+I10 -> 15 | J11: =J9+J10 -> 18 | K11: =K9+K10 -> 21 | ... BA11: =BA9+BA10 -> 49
A13: ADMIN COST SCALING
A14: Ramp factor (early → target) | B14: 0 = early, 1 = target | D14: =MIN(1,MAX(0,(D$6-1)/MAX(1,logistic_start_yr-1))) -> 0 | E14: =MIN(1,MAX(0,(E$6-1)/MAX(1,logistic_start_yr-1))) -> 0.33333333 | F14: =MIN(1,MAX(0,(F$6-1)/MAX(1,logistic_start_yr-1))) -> 0.66666667 | G14: =MIN(1,MAX(0,(G$6-1)/MAX(1,logistic_start_yr-1))) -> 1 | H14: =MIN(1,MAX(0,(H$6-1)/MAX(1,logistic_start_yr-1))) -> 1 | I14: =MIN(1,MAX(0,(I$6-1)/MAX(1,logistic_start_yr-1))) -> 1 | J14: =MIN(1,MAX(0,(J$6-1)/MAX(1,logistic_start_yr-1))) -> 1 | K14: =MIN(1,MAX(0,(K$6-1)/MAX(1,logistic_start_yr-1))) -> 1 | ... BA14: =MIN(1,MAX(0,(BA$6-1)/MAX(1,logistic_start_yr-1))) -> 1
A15: Board remuneration | B15: £ | D15: =(board_early+D$14*(board_target-board_early))*'Macro & Indexation'!D$20 -> 0 | E15: =(board_early+E$14*(board_target-board_early))*'Macro & Indexation'!E$20 -> 4100 | F15: =(board_early+F$14*(board_target-board_early))*'Macro & Indexation'!F$20 -> 8405 | G15: =(board_early+G$14*(board_target-board_early))*'Macro & Indexation'!G$20 -> 12922.687 | H15: =(board_early+H$14*(board_target-board_early))*'Macro & Indexation'!H$20 -> 13245.755 | I15: =(board_early+I$14*(board_target-board_early))*'Macro & Indexation'!I$20 -> 13576.899 | J15: =(board_early+J$14*(board_target-board_early))*'Macro & Indexation'!J$20 -> 13916.321 | K15: =(board_early+K$14*(board_target-board_early))*'Macro & Indexation'!K$20 -> 14264.229 | ... BA15: =(board_early+BA$14*(board_target-board_early))*'Macro & Indexation'!BA$20 -> 40239.322
A16: Accounting & audit | B16: £ | D16: =(acct_early+D$14*(acct_target-acct_early))*'Macro & Indexation'!D$20 -> 3000 | E16: =(acct_early+E$14*(acct_target-acct_early))*'Macro & Indexation'!E$20 -> 4783.3333 | F16: =(acct_early+F$14*(acct_target-acct_early))*'Macro & Indexation'!F$20 -> 6653.9583 | G16: =(acct_early+G$14*(acct_target-acct_early))*'Macro & Indexation'!G$20 -> 8615.125 | H16: =(acct_early+H$14*(acct_target-acct_early))*'Macro & Indexation'!H$20 -> 8830.5031 | I16: =(acct_early+I$14*(acct_target-acct_early))*'Macro & Indexation'!I$20 -> 9051.2657 | J16: =(acct_early+J$14*(acct_target-acct_early))*'Macro & Indexation'!J$20 -> 9277.5473 | K16: =(acct_early+K$14*(acct_target-acct_early))*'Macro & Indexation'!K$20 -> 9509.486 | ... BA16: =(acct_early+BA$14*(acct_target-acct_early))*'Macro & Indexation'!BA$20 -> 26826.214
A17: FCA & annual reporting | B17: £ | D17: =(fca_early+D$14*(fca_target-fca_early))*'Macro & Indexation'!D$20 -> 1500 | E17: =(fca_early+E$14*(fca_target-fca_early))*'Macro & Indexation'!E$20 -> 2050 | F17: =(fca_early+F$14*(fca_target-fca_early))*'Macro & Indexation'!F$20 -> 2626.5625 | G17: =(fca_early+G$14*(fca_target-fca_early))*'Macro & Indexation'!G$20 -> 3230.6719 | H17: =(fca_early+H$14*(fca_target-fca_early))*'Macro & Indexation'!H$20 -> 3311.4387 | I17: =(fca_early+I$14*(fca_target-fca_early))*'Macro & Indexation'!I$20 -> 3394.2246 | J17: =(fca_early+J$14*(fca_target-fca_early))*'Macro & Indexation'!J$20 -> 3479.0803 | K17: =(fca_early+K$14*(fca_target-fca_early))*'Macro & Indexation'!K$20 -> 3566.0573 | ... BA17: =(fca_early+BA$14*(fca_target-fca_early))*'Macro & Indexation'!BA$20 -> 10059.83
A18: Insurance | B18: £ | D18: =(ins_early+D$14*(ins_target-ins_early))*'Macro & Indexation'!D$20 -> 1000 | E18: =(ins_early+E$14*(ins_target-ins_early))*'Macro & Indexation'!E$20 -> 1366.6667 | F18: =(ins_early+F$14*(ins_target-ins_early))*'Macro & Indexation'!F$20 -> 1751.0417 | G18: =(ins_early+G$14*(ins_target-ins_early))*'Macro & Indexation'!G$20 -> 2153.7812 | H18: =(ins_early+H$14*(ins_target-ins_early))*'Macro & Indexation'!H$20 -> 2207.6258 | I18: =(ins_early+I$14*(ins_target-ins_early))*'Macro & Indexation'!I$20 -> 2262.8164 | J18: =(ins_early+J$14*(ins_target-ins_early))*'Macro & Indexation'!J$20 -> 2319.3868 | K18: =(ins_early+K$14*(ins_target-ins_early))*'Macro & Indexation'!K$20 -> 2377.3715 | ... BA18: =(ins_early+BA$14*(ins_target-ins_early))*'Macro & Indexation'!BA$20 -> 6706.5536
A19: Variable admin (per property) | B19: £ | D19: =admin_per_prop*D11*'Macro & Indexation'!D$20 -> 150 | E19: =admin_per_prop*E11*'Macro & Indexation'!E$20 -> 461.25 | F19: =admin_per_prop*F11*'Macro & Indexation'!F$20 -> 945.5625 | G19: =admin_per_prop*G11*'Macro & Indexation'!G$20 -> 1453.8023 | H19: =admin_per_prop*H11*'Macro & Indexation'!H$20 -> 1986.8632 | I19: =admin_per_prop*I11*'Macro & Indexation'!I$20 -> 2545.6685 | J19: =admin_per_prop*J11*'Macro & Indexation'!J$20 -> 3131.1722 | K19: =admin_per_prop*K11*'Macro & Indexation'!K$20 -> 3744.3601 | ... BA19: =admin_per_prop*BA11*'Macro & Indexation'!BA$20 -> 24646.584
A20: Total admin costs | B20: £ | D20: =SUM(D15:D19) -> 5650 | E20: =SUM(E15:E19) -> 12761.25 | F20: =SUM(F15:F19) -> 20382.125 | G20: =SUM(G15:G19) -> 28376.068 | H20: =SUM(H15:H19) -> 29582.185 | I20: =SUM(I15:I19) -> 30830.874 | J20: =SUM(J15:J19) -> 32123.508 | K20: =SUM(K15:K19) -> 33461.504 | ... BA20: =SUM(BA15:BA19) -> 108478.5
A22: FUNDING-CONSTRAINED ACQUISITION CAP
A23: Unit acquisition cost (price + SDLT + fees + retrofit) | B23: £ | D23: ='Macro & Indexation'!D19*(1+sdlt_rate)+(conveyancing+survey_cost+retrofit_cost)*'Macro & Indexation'!D20 -> 288300 | E23: ='Macro & Indexation'!E19*(1+sdlt_rate)+(conveyancing+survey_cost+retrofit_cost)*'Macro & Indexation'!E20 -> 298307.5 | F23: ='Macro & Indexation'!F19*(1+sdlt_rate)+(conveyancing+survey_cost+retrofit_cost)*'Macro & Indexation'!F20 -> 308663.19 | G23: ='Macro & Indexation'!G19*(1+sdlt_rate)+(conveyancing+survey_cost+retrofit_cost)*'Macro & Indexation'!G20 -> 319379.2 | H23: ='Macro & Indexation'!H19*(1+sdlt_rate)+(conveyancing+survey_cost+retrofit_cost)*'Macro & Indexation'!H20 -> 330468.09 | I23: ='Macro & Indexation'!I19*(1+sdlt_rate)+(conveyancing+survey_cost+retrofit_cost)*'Macro & Indexation'!I20 -> 341942.85 | J23: ='Macro & Indexation'!J19*(1+sdlt_rate)+(conveyancing+survey_cost+retrofit_cost)*'Macro & Indexation'!J20 -> 353816.95 | K23: ='Macro & Indexation'!K19*(1+sdlt_rate)+(conveyancing+survey_cost+retrofit_cost)*'Macro & Indexation'!K20 -> 366104.29 | ... BA23: ='Macro & Indexation'!BA19*(1+sdlt_rate)+(conveyancing+survey_cost+retrofit_cost)*'Macro & Indexation'!BA20 -> 1538730.3
A24: Funding capacity excl. new gearing on purchases | B24: £ | D24: =D27*MIN(MAX(0,pf_ltv_limit*'Asset Register'!C61-'Capital & Debt'!C43-'Capital & Debt'!C50),MAX(0,pf_max_raise-'Capital & Debt'!C38))+MAX(0,'Financial Statements'!C65-MAX('Capital & Debt'!C60,min_cash_buffer))+'Capital & Debt'!D14+'Capital & Debt'!D22+'Capital & Debt'!D24+'Capital & Debt'!D25 -> 260000 | E24: =E27*MIN(MAX(0,pf_ltv_limit*'Asset Register'!D61-'Capital & Debt'!D43-'Capital & Debt'!D50),MAX(0,pf_max_raise-'Capital & Debt'!D38))+MAX(0,'Financial Statements'!D65-MAX('Capital & Debt'!D60,min_cash_buffer))+'Capital & Debt'!E14+'Capital & Debt'!E22+'Capital & Debt'!E24+'Capital & Debt'!E25 -> 330335.16 | F24: =F27*MIN(MAX(0,pf_ltv_limit*'Asset Register'!E61-'Capital & Debt'!E43-'Capital & Debt'!E50),MAX(0,pf_max_raise-'Capital & Debt'!E38))+MAX(0,'Financial Statements'!E65-MAX('Capital & Debt'!E60,min_cash_buffer))+'Capital & Debt'!F14+'Capital & Debt'!F22+'Capital & Debt'!F24+'Capital & Debt'!F25 -> 381977.76 | G24: =G27*MIN(MAX(0,pf_ltv_limit*'Asset Register'!F61-'Capital & Debt'!F43-'Capital & Debt'!F50),MAX(0,pf_max_raise-'Capital & Debt'!F38))+MAX(0,'Financial Statements'!F65-MAX('Capital & Debt'!F60,min_cash_buffer))+'Capital & Debt'!G14+'Capital & Debt'!G22+'Capital & Debt'!G24+'Capital & Debt'!G25 -> 400774.68 | H24: =H27*MIN(MAX(0,pf_ltv_limit*'Asset Register'!G61-'Capital & Debt'!G43-'Capital & Debt'!G50),MAX(0,pf_max_raise-'Capital & Debt'!G38))+MAX(0,'Financial Statements'!G65-MAX('Capital & Debt'!G60,min_cash_buffer))+'Capital & Debt'!H14+'Capital & Debt'!H22+'Capital & Debt'!H24+'Capital & Debt'!H25 -> 401592.17 | I24: =I27*MIN(MAX(0,pf_ltv_limit*'Asset Register'!H61-'Capital & Debt'!H43-'Capital & Debt'!H50),MAX(0,pf_max_raise-'Capital & Debt'!H38))+MAX(0,'Financial Statements'!H65-MAX('Capital & Debt'!H60,min_cash_buffer))+'Capital & Debt'!I14+'Capital & Debt'!I22+'Capital & Debt'!I24+'Capital & Debt'!I25 -> 398137.69 | J24: =J27*MIN(MAX(0,pf_ltv_limit*'Asset Register'!I61-'Capital & Debt'!I43-'Capital & Debt'!I50),MAX(0,pf_max_raise-'Capital & Debt'!I38))+MAX(0,'Financial Statements'!I65-MAX('Capital & Debt'!I60,min_cash_buffer))+'Capital & Debt'!J14+'Capital & Debt'!J22+'Capital & Debt'!J24+'Capital & Debt'!J25 -> 386348.09 | K24: =K27*MIN(MAX(0,pf_ltv_limit*'Asset Register'!J61-'Capital & Debt'!J43-'Capital & Debt'!J50),MAX(0,pf_max_raise-'Capital & Debt'!J38))+MAX(0,'Financial Statements'!J65-MAX('Capital & Debt'!J60,min_cash_buffer))+'Capital & Debt'!K14+'Capital & Debt'!K22+'Capital & Debt'!K24+'Capital & Debt'!K25 -> 365119.02 | ... BA24: =BA27*MIN(MAX(0,pf_ltv_limit*'Asset Register'!AZ61-'Capital & Debt'!AZ43-'Capital & Debt'!AZ50),MAX(0,pf_max_raise-'Capital & Debt'!AZ38))+MAX(0,'Financial Statements'!AZ65-MAX('Capital & Debt'!AZ60,min_cash_buffer))+'Capital & Debt'!BA14+'Capital & Debt'!BA22+'Capital & Debt'!BA24+'Capital & Debt'!BA25 -> 2949244.1
A25: Affordable properties | B25: properties | D25: =IF(constrain_growth=1,MAX(0,INT(D24/(D23*IF(D27=1,MAX(0.01,1-pf_ltv_limit),1)))),999999) -> 3 | E25: =IF(constrain_growth=1,MAX(0,INT(E24/(E23*IF(E27=1,MAX(0.01,1-pf_ltv_limit),1)))),999999) -> 3 | F25: =IF(constrain_growth=1,MAX(0,INT(F24/(F23*IF(F27=1,MAX(0.01,1-pf_ltv_limit),1)))),999999) -> 4 | G25: =IF(constrain_growth=1,MAX(0,INT(G24/(G23*IF(G27=1,MAX(0.01,1-pf_ltv_limit),1)))),999999) -> 4 | H25: =IF(constrain_growth=1,MAX(0,INT(H24/(H23*IF(H27=1,MAX(0.01,1-pf_ltv_limit),1)))),999999) -> 4 | I25: =IF(constrain_growth=1,MAX(0,INT(I24/(I23*IF(I27=1,MAX(0.01,1-pf_ltv_limit),1)))),999999) -> 3 | J25: =IF(constrain_growth=1,MAX(0,INT(J24/(J23*IF(J27=1,MAX(0.01,1-pf_ltv_limit),1)))),999999) -> 3 | K25: =IF(constrain_growth=1,MAX(0,INT(K24/(K23*IF(K27=1,MAX(0.01,1-pf_ltv_limit),1)))),999999) -> 3 | ... BA25: =IF(constrain_growth=1,MAX(0,INT(BA24/(BA23*IF(BA27=1,MAX(0.01,1-pf_ltv_limit),1)))),999999) -> 1
A26: Growth-curve acquisitions (unconstrained) | B26: properties | D26: =IF(D$6<=3,CHOOSE(D$6,acq_year1,acq_year2,acq_year3),MIN(MAX(logistic_floor,IF(D$6>=logistic_start_yr,ROUND($C$4*D9*(1-D9/logistic_ceiling),0),0)),MAX(0,logistic_ceiling-D9))) -> 1 | E26: =IF(E$6<=3,CHOOSE(E$6,acq_year1,acq_year2,acq_year3),MIN(MAX(logistic_floor,IF(E$6>=logistic_start_yr,ROUND($C$4*E9*(1-E9/logistic_ceiling),0),0)),MAX(0,logistic_ceiling-E9))) -> 2 | F26: =IF(F$6<=3,CHOOSE(F$6,acq_year1,acq_year2,acq_year3),MIN(MAX(logistic_floor,IF(F$6>=logistic_start_yr,ROUND($C$4*F9*(1-F9/logistic_ceiling),0),0)),MAX(0,logistic_ceiling-F9))) -> 3 | G26: =IF(G$6<=3,CHOOSE(G$6,acq_year1,acq_year2,acq_year3),MIN(MAX(logistic_floor,IF(G$6>=logistic_start_yr,ROUND($C$4*G9*(1-G9/logistic_ceiling),0),0)),MAX(0,logistic_ceiling-G9))) -> 3 | H26: =IF(H$6<=3,CHOOSE(H$6,acq_year1,acq_year2,acq_year3),MIN(MAX(logistic_floor,IF(H$6>=logistic_start_yr,ROUND($C$4*H9*(1-H9/logistic_ceiling),0),0)),MAX(0,logistic_ceiling-H9))) -> 3 | I26: =IF(I$6<=3,CHOOSE(I$6,acq_year1,acq_year2,acq_year3),MIN(MAX(logistic_floor,IF(I$6>=logistic_start_yr,ROUND($C$4*I9*(1-I9/logistic_ceiling),0),0)),MAX(0,logistic_ceiling-I9))) -> 3 | J26: =IF(J$6<=3,CHOOSE(J$6,acq_year1,acq_year2,acq_year3),MIN(MAX(logistic_floor,IF(J$6>=logistic_start_yr,ROUND($C$4*J9*(1-J9/logistic_ceiling),0),0)),MAX(0,logistic_ceiling-J9))) -> 3 | K26: =IF(K$6<=3,CHOOSE(K$6,acq_year1,acq_year2,acq_year3),MIN(MAX(logistic_floor,IF(K$6>=logistic_start_yr,ROUND($C$4*K9*(1-K9/logistic_ceiling),0),0)),MAX(0,logistic_ceiling-K9))) -> 3 | ... BA26: =IF(BA$6<=3,CHOOSE(BA$6,acq_year1,acq_year2,acq_year3),MIN(MAX(logistic_floor,IF(BA$6>=logistic_start_yr,ROUND($C$4*BA9*(1-BA9/logistic_ceiling),0),0)),MAX(0,logistic_ceiling-BA9))) -> 6
A27: New Tontine capital available this year? (1 = Yes) | B27: 36526 | D27: =IF(AND(D$6<=pf_invest_phase_yrs,OR(pf_refi_toggle=0,D$6<pf_refi_year),'Capital & Debt'!C38<pf_max_raise),1,0) -> 1 | E27: =IF(AND(E$6<=pf_invest_phase_yrs,OR(pf_refi_toggle=0,E$6<pf_refi_year),'Capital & Debt'!D38<pf_max_raise),1,0) -> 1 | F27: =IF(AND(F$6<=pf_invest_phase_yrs,OR(pf_refi_toggle=0,F$6<pf_refi_year),'Capital & Debt'!E38<pf_max_raise),1,0) -> 1 | G27: =IF(AND(G$6<=pf_invest_phase_yrs,OR(pf_refi_toggle=0,G$6<pf_refi_year),'Capital & Debt'!F38<pf_max_raise),1,0) -> 1 | H27: =IF(AND(H$6<=pf_invest_phase_yrs,OR(pf_refi_toggle=0,H$6<pf_refi_year),'Capital & Debt'!G38<pf_max_raise),1,0) -> 1 | I27: =IF(AND(I$6<=pf_invest_phase_yrs,OR(pf_refi_toggle=0,I$6<pf_refi_year),'Capital & Debt'!H38<pf_max_raise),1,0) -> 1 | J27: =IF(AND(J$6<=pf_invest_phase_yrs,OR(pf_refi_toggle=0,J$6<pf_refi_year),'Capital & Debt'!I38<pf_max_raise),1,0) -> 1 | K27: =IF(AND(K$6<=pf_invest_phase_yrs,OR(pf_refi_toggle=0,K$6<pf_refi_year),'Capital & Debt'!J38<pf_max_raise),1,0) -> 1 | ... BA27: =IF(AND(BA$6<=pf_invest_phase_yrs,OR(pf_refi_toggle=0,BA$6<pf_refi_year),'Capital & Debt'!AZ38<pf_max_raise),1,0) -> 0

Sheet Capital & Debt
A1: CAPITAL & DEBT SCHEDULE
A2: Tontine (index-linked, interest-only) · Community shares (junior debt) · Bequests & gifts. Row 25 dividend rate is a per-year input.
A4: Tontine termination / refinancing year | B4: model year
A5: Commercial mortgage is amortised straight-line over its remaining term.
A6: Model year | D6: 1 | E6: 2 | F6: 3 | G6: 4 | H6: 5 | I6: 6 | J6: 7 | K6: 8 | L6: 9 | M6: 10 | N6: 11 | O6: 12 | P6: 13 | Q6: 14 | R6: 15 | S6: 16 | T6: 17 | U6: 18 | V6: 19 | W6: 20 | X6: 21 | Y6: 22 | Z6: 23 | AA6: 24 | AB6: 25 | AC6: 26 | AD6: 27 | AE6: 28 | AF6: 29 | AG6: 30 | AH6: 31 | AI6: 32 | AJ6: 33 | AK6: 34 | AL6: 35 | AM6: 36 | AN6: 37 | AO6: 38 | AP6: 39 | AQ6: 40 | AR6: 41 | AS6: 42 | AT6: 43 | AU6: 44 | AV6: 45 | AW6: 46 | AX6: 47 | AY6: 48 | AZ6: 49 | BA6: 50
A7: Calendar year | D7: =base_calendar_year+D$6-1 -> 2026 | E7: =base_calendar_year+E$6-1 -> 2027 | F7: =base_calendar_year+F$6-1 -> 2028 | G7: =base_calendar_year+G$6-1 -> 2029 | H7: =base_calendar_year+H$6-1 -> 2030 | I7: =base_calendar_year+I$6-1 -> 2031 | J7: =base_calendar_year+J$6-1 -> 2032 | K7: =base_calendar_year+K$6-1 -> 2033 | ... BA7: =base_calendar_year+BA$6-1 -> 2075
A9: BEQUESTS & GIFTS
A10: Cash gifts from living donors | B10: £ | D10: =gift_baseline*(1+beq_growth_mult)^(D$6-1)*'Macro & Indexation'!D$20 -> 40000 | E10: =gift_baseline*(1+beq_growth_mult)^(E$6-1)*'Macro & Indexation'!E$20 -> 41000 | F10: =gift_baseline*(1+beq_growth_mult)^(F$6-1)*'Macro & Indexation'!F$20 -> 42025 | G10: =gift_baseline*(1+beq_growth_mult)^(G$6-1)*'Macro & Indexation'!G$20 -> 43075.625 | H10: =gift_baseline*(1+beq_growth_mult)^(H$6-1)*'Macro & Indexation'!H$20 -> 44152.516 | I10: =gift_baseline*(1+beq_growth_mult)^(I$6-1)*'Macro & Indexation'!I$20 -> 45256.329 | J10: =gift_baseline*(1+beq_growth_mult)^(J$6-1)*'Macro & Indexation'!J$20 -> 46387.737 | K10: =gift_baseline*(1+beq_growth_mult)^(K$6-1)*'Macro & Indexation'!K$20 -> 47547.43 | ... BA10: =gift_baseline*(1+beq_growth_mult)^(BA$6-1)*'Macro & Indexation'!BA$20 -> 134131.07
A11: Bequests from estates | B11: £ | D11: =beq_baseline*(1+beq_growth_mult)^(D$6-1)*'Macro & Indexation'!D$20 -> 60000 | E11: =beq_baseline*(1+beq_growth_mult)^(E$6-1)*'Macro & Indexation'!E$20 -> 61500 | F11: =beq_baseline*(1+beq_growth_mult)^(F$6-1)*'Macro & Indexation'!F$20 -> 63037.5 | G11: =beq_baseline*(1+beq_growth_mult)^(G$6-1)*'Macro & Indexation'!G$20 -> 64613.437 | H11: =beq_baseline*(1+beq_growth_mult)^(H$6-1)*'Macro & Indexation'!H$20 -> 66228.773 | I11: =beq_baseline*(1+beq_growth_mult)^(I$6-1)*'Macro & Indexation'!I$20 -> 67884.493 | J11: =beq_baseline*(1+beq_growth_mult)^(J$6-1)*'Macro & Indexation'!J$20 -> 69581.605 | K11: =beq_baseline*(1+beq_growth_mult)^(K$6-1)*'Macro & Indexation'!K$20 -> 71321.145 | ... BA11: =beq_baseline*(1+beq_growth_mult)^(BA$6-1)*'Macro & Indexation'!BA$20 -> 201196.61
A12: Founding capital injection | B12: £ | D12: =IF(D$6=1,founding_capital,0) -> 150000 | E12: =IF(E$6=1,founding_capital,0) -> 0 | F12: =IF(F$6=1,founding_capital,0) -> 0 | G12: =IF(G$6=1,founding_capital,0) -> 0 | H12: =IF(H$6=1,founding_capital,0) -> 0 | I12: =IF(I$6=1,founding_capital,0) -> 0 | J12: =IF(J$6=1,founding_capital,0) -> 0 | K12: =IF(K$6=1,founding_capital,0) -> 0 | ... BA12: =IF(BA$6=1,founding_capital,0) -> 0
A13: Gift Aid recovery | B13: £ | D13: =IF(gift_aid_toggle=1,D10*gift_aid_rate,0) -> 10000 | E13: =IF(gift_aid_toggle=1,E10*gift_aid_rate,0) -> 10250 | F13: =IF(gift_aid_toggle=1,F10*gift_aid_rate,0) -> 10506.25 | G13: =IF(gift_aid_toggle=1,G10*gift_aid_rate,0) -> 10768.906 | H13: =IF(gift_aid_toggle=1,H10*gift_aid_rate,0) -> 11038.129 | I13: =IF(gift_aid_toggle=1,I10*gift_aid_rate,0) -> 11314.082 | J13: =IF(gift_aid_toggle=1,J10*gift_aid_rate,0) -> 11596.934 | K13: =IF(gift_aid_toggle=1,K10*gift_aid_rate,0) -> 11886.858 | ... BA13: =IF(gift_aid_toggle=1,BA10*gift_aid_rate,0) -> 33532.768
A14: Total gift income | B14: £ | D14: =SUM(D10:D13) -> 260000 | E14: =SUM(E10:E13) -> 112750 | F14: =SUM(F10:F13) -> 115568.75 | G14: =SUM(G10:G13) -> 118457.97 | H14: =SUM(H10:H13) -> 121419.42 | I14: =SUM(I10:I13) -> 124454.9 | J14: =SUM(J10:J13) -> 127566.28 | K14: =SUM(K10:K13) -> 130755.43 | ... BA14: =SUM(BA10:BA13) -> 368860.45
A15: Cumulative gifts, bequests & founding capital | B15: £ | D15: =D14 -> 260000 | E15: =D15+E14 -> 372750 | F15: =E15+F14 -> 488318.75 | G15: =F15+G14 -> 606776.72 | H15: =G15+H14 -> 728196.14 | I15: =H15+I14 -> 852651.04 | J15: =I15+J14 -> 980217.32 | K15: =J15+K14 -> 1110972.7 | L15: =K15+L14 -> 1244997.1 | ... BA15: =AZ15+BA14 -> 10873278
A17: COMMUNITY SHARES (JUNIOR DEBT)
A18: Target issuance (indexed) | B18: £ | D18: =cs_baseline_issue*cs_takeup_mult*'Macro & Indexation'!D$20 -> 250000 | E18: =cs_baseline_issue*cs_takeup_mult*'Macro & Indexation'!E$20 -> 256250 | F18: =cs_baseline_issue*cs_takeup_mult*'Macro & Indexation'!F$20 -> 262656.25 | G18: =cs_baseline_issue*cs_takeup_mult*'Macro & Indexation'!G$20 -> 269222.66 | H18: =cs_baseline_issue*cs_takeup_mult*'Macro & Indexation'!H$20 -> 275953.22 | I18: =cs_baseline_issue*cs_takeup_mult*'Macro & Indexation'!I$20 -> 282852.05 | J18: =cs_baseline_issue*cs_takeup_mult*'Macro & Indexation'!J$20 -> 289923.35 | K18: =cs_baseline_issue*cs_takeup_mult*'Macro & Indexation'!K$20 -> 297171.44 | ... BA18: =cs_baseline_issue*cs_takeup_mult*'Macro & Indexation'!BA$20 -> 838319.2
A19: Other capital — opening (total capital ex-shares) | B19: £ | D19: =0 -> 0 | E19: ='Financial Statements'!D44-D26 -> 307624.38 | F19: ='Financial Statements'!E44-E26 -> 821883.17 | G19: ='Financial Statements'!F44-F26 -> 1613096.2 | H19: ='Financial Statements'!G44-G26 -> 2392236.7 | I19: ='Financial Statements'!H44-H26 -> 3260995.8 | J19: ='Financial Statements'!I44-I26 -> 4186101.2 | K19: ='Financial Statements'!J44-J26 -> 5184045.5 | L19: ='Financial Statements'!K44-K26 -> 6203511 | ... BA19: ='Financial Statements'!AZ44-AZ26 -> 61377604
A20: Maximum share capital permitted | B20: cap % of total capital | D20: =cs_max_pct_capital/(1-cs_max_pct_capital)*D19 -> 0 | E20: =cs_max_pct_capital/(1-cs_max_pct_capital)*E19 -> 76906.094 | F20: =cs_max_pct_capital/(1-cs_max_pct_capital)*F19 -> 205470.79 | G20: =cs_max_pct_capital/(1-cs_max_pct_capital)*G19 -> 403274.05 | H20: =cs_max_pct_capital/(1-cs_max_pct_capital)*H19 -> 598059.18 | I20: =cs_max_pct_capital/(1-cs_max_pct_capital)*I19 -> 815248.94 | J20: =cs_max_pct_capital/(1-cs_max_pct_capital)*J19 -> 1046525.3 | K20: =cs_max_pct_capital/(1-cs_max_pct_capital)*K19 -> 1296011.4 | ... BA20: =cs_max_pct_capital/(1-cs_max_pct_capital)*BA19 -> 15344401
A21: Opening share capital | B21: £ | D21: =0 -> 0 | E21: =D26 -> 0 | F21: =E26 -> 76906.094 | G21: =F26 -> 205470.79 | H21: =G26 -> 403274.05 | I21: =H26 -> 598059.18 | J21: =I26 -> 815248.94 | K21: =J26 -> 1044987.2 | L21: =K26 -> 1291902 | ... BA21: =AZ26 -> 13288451
A22: Shares issued | B22: £ | D22: =MIN(D18,MAX(0,D20-D21)) -> 0 | E22: =MIN(E18,MAX(0,E20-E21)) -> 76906.094 | F22: =MIN(F18,MAX(0,F20-F21)) -> 128564.7 | G22: =MIN(G18,MAX(0,G20-G21)) -> 197803.25 | H22: =MIN(H18,MAX(0,H20-H21)) -> 194785.14 | I22: =MIN(I18,MAX(0,I20-I21)) -> 217189.76 | J22: =MIN(J18,MAX(0,J20-J21)) -> 231276.35 | K22: =MIN(K18,MAX(0,K20-K21)) -> 251024.22 | ... BA22: =MIN(BA18,MAX(0,BA20-BA21)) -> 838319.2
A23: Shares eligible for withdrawal | B23: £ | D23: =IF(D$6-MAX(1,cs_withdrawal_years)<1,0,OFFSET($D$26,0,D$6-1-MAX(1,cs_withdrawal_years))) -> 0 | E23: =IF(E$6-MAX(1,cs_withdrawal_years)<1,0,OFFSET($D$26,0,E$6-1-MAX(1,cs_withdrawal_years))) -> 0 | F23: =IF(F$6-MAX(1,cs_withdrawal_years)<1,0,OFFSET($D$26,0,F$6-1-MAX(1,cs_withdrawal_years))) -> 0 | G23: =IF(G$6-MAX(1,cs_withdrawal_years)<1,0,OFFSET($D$26,0,G$6-1-MAX(1,cs_withdrawal_years))) -> 0 | H23: =IF(H$6-MAX(1,cs_withdrawal_years)<1,0,OFFSET($D$26,0,H$6-1-MAX(1,cs_withdrawal_years))) -> 0 | I23: =IF(I$6-MAX(1,cs_withdrawal_years)<1,0,OFFSET($D$26,0,I$6-1-MAX(1,cs_withdrawal_years))) -> 0 | J23: =IF(J$6-MAX(1,cs_withdrawal_years)<1,0,OFFSET($D$26,0,J$6-1-MAX(1,cs_withdrawal_years))) -> 76906.094 | K23: =IF(K$6-MAX(1,cs_withdrawal_years)<1,0,OFFSET($D$26,0,K$6-1-MAX(1,cs_withdrawal_years))) -> 205470.79 | ... BA23: =IF(BA$6-MAX(1,cs_withdrawal_years)<1,0,OFFSET($D$26,0,BA$6-1-MAX(1,cs_withdrawal_years))) -> 10892580
A24: Withdrawals | B24: £ | D24: =-MIN(D21,D23*cs_withdrawal_rate) -> 0 | E24: =-MIN(E21,E23*cs_withdrawal_rate) -> 0 | F24: =-MIN(F21,F23*cs_withdrawal_rate) -> 0 | G24: =-MIN(G21,G23*cs_withdrawal_rate) -> 0 | H24: =-MIN(H21,H23*cs_withdrawal_rate) -> 0 | I24: =-MIN(I21,I23*cs_withdrawal_rate) -> 0 | J24: =-MIN(J21,J23*cs_withdrawal_rate) -> -1538.1219 | K24: =-MIN(K21,K23*cs_withdrawal_rate) -> -4109.4158 | ... BA24: =-MIN(BA21,BA23*cs_withdrawal_rate) -> -217851.61
A25: Issuance / marketing costs | B25: £ | D25: =-D22*cs_issue_cost_pct -> 0 | E25: =-E22*cs_issue_cost_pct -> -3845.3047 | F25: =-F22*cs_issue_cost_pct -> -6428.2349 | G25: =-G22*cs_issue_cost_pct -> -9890.1627 | H25: =-H22*cs_issue_cost_pct -> -9739.2569 | I25: =-I22*cs_issue_cost_pct -> -10859.488 | J25: =-J22*cs_issue_cost_pct -> -11563.817 | K25: =-K22*cs_issue_cost_pct -> -12551.211 | ... BA25: =-BA22*cs_issue_cost_pct -> -41915.96
A26: Closing share capital | B26: £ | D26: =D21+D22+D24 -> 0 | E26: =E21+E22+E24 -> 76906.094 | F26: =F21+F22+F24 -> 205470.79 | G26: =G21+G22+G24 -> 403274.05 | H26: =H21+H22+H24 -> 598059.18 | I26: =I21+I22+I24 -> 815248.94 | J26: =J21+J22+J24 -> 1044987.2 | K26: =K21+K22+K24 -> 1291902 | ... BA26: =BA21+BA22+BA24 -> 13908919
A27: Dividend rate — per year (INPUT) | B27: % p.a. | D27: =cs_dividend_rate -> 0.03 | E27: =cs_dividend_rate -> 0.03 | F27: =cs_dividend_rate -> 0.03 | G27: =cs_dividend_rate -> 0.03 | H27: =cs_dividend_rate -> 0.03 | I27: =cs_dividend_rate -> 0.03 | J27: =cs_dividend_rate -> 0.03 | K27: =cs_dividend_rate -> 0.03 | ... BA27: =cs_dividend_rate -> 0.03
A28: Dividends payable (capped by surplus) | B28: £ | D28: =MIN(D21*D27,MAX(0,'Financial Statements'!D23)) -> 0 | E28: =MIN(E21*E27,MAX(0,'Financial Statements'!E23)) -> 0 | F28: =MIN(F21*F27,MAX(0,'Financial Statements'!F23)) -> 2307.1828 | G28: =MIN(G21*G27,MAX(0,'Financial Statements'!G23)) -> 6164.1238 | H28: =MIN(H21*H27,MAX(0,'Financial Statements'!H23)) -> 1278.9368 | I28: =MIN(I21*I27,MAX(0,'Financial Statements'!I23)) -> 0 | J28: =MIN(J21*J27,MAX(0,'Financial Statements'!J23)) -> 0 | K28: =MIN(K21*K27,MAX(0,'Financial Statements'!K23)) -> 0 | ... BA28: =MIN(BA21*BA27,MAX(0,'Financial Statements'!BA23)) -> 398653.54
A29: TONTINE FUND — CLOSED-END LIFETIME ANNUITY MUTUAL
A30: Opening balance | B30: £ | D30: =0 -> 0 | E30: =D43 -> 53300 | F30: =E43 -> 465436.71 | G30: =F43 -> 1165357 | H30: =G43 -> 1860651.5 | I30: =H43 -> 2631621.6 | J30: =I43 -> 3451190.3 | K30: =J43 -> 4336812.8 | L30: =K43 -> 5236701.4 | ... BA30: =AZ43 -> 4022629.9
A31: CPI indexation uplift on principal | B31: £ | D31: =D30*'Macro & Indexation'!D$9 -> 0 | E31: =E30*'Macro & Indexation'!E$9 -> 1332.5 | F31: =F30*'Macro & Indexation'!F$9 -> 11635.918 | G31: =G30*'Macro & Indexation'!G$9 -> 29133.924 | H31: =H30*'Macro & Indexation'!H$9 -> 46516.286 | I31: =I30*'Macro & Indexation'!I$9 -> 65790.54 | J31: =J30*'Macro & Indexation'!J$9 -> 86279.758 | K31: =K30*'Macro & Indexation'!K$9 -> 108420.32 | ... BA31: =BA30*'Macro & Indexation'!BA$9 -> 100565.75
A32: Indexed opening balance | B32: £ | D32: =D30+D31 -> 0 | E32: =E30+E31 -> 54632.5 | F32: =F30+F31 -> 477072.63 | G32: =G30+G31 -> 1194490.9 | H32: =H30+H31 -> 1907167.7 | I32: =I30+I31 -> 2697412.1 | J32: =J30+J31 -> 3537470.1 | K32: =K30+K31 -> 4445233.1 | ... BA32: =BA30+BA31 -> 4123195.6
A33: Cumulative capital raised — opening | B33: £ | D33: =0 -> 0 | E33: =D38 -> 53300 | F33: =E38 -> 464104.21 | G33: =F38 -> 1152388.6 | H33: =G38 -> 1818549.1 | I33: =H38 -> 2543003 | J33: =I38 -> 3296781.2 | K33: =J38 -> 4096123.9 | L33: =K38 -> 4887592.2 | ... BA33: =AZ38 -> 6577569.3
A34: Remaining raise capacity | B34: £ | D34: =MAX(0,pf_max_raise-D33) -> 50000000 | E34: =MAX(0,pf_max_raise-E33) -> 49946700 | F34: =MAX(0,pf_max_raise-F33) -> 49535896 | G34: =MAX(0,pf_max_raise-G33) -> 48847611 | H34: =MAX(0,pf_max_raise-H33) -> 48181451 | I34: =MAX(0,pf_max_raise-I33) -> 47456997 | J34: =MAX(0,pf_max_raise-J33) -> 46703219 | K34: =MAX(0,pf_max_raise-K33) -> 45903876 | ... BA34: =MAX(0,pf_max_raise-BA33) -> 43422431
A35: LTV headroom | B35: £ | D35: =MAX(0,pf_ltv_limit*'Asset Register'!D61-D32-D46) -> 196000 | E35: =MAX(0,pf_ltv_limit*'Asset Register'!E61-E32-E46) -> 553947.5 | F35: =MAX(0,pf_ltv_limit*'Asset Register'!F61-F32-F46) -> 782687.97 | G35: =MAX(0,pf_ltv_limit*'Asset Register'!G61-G32-G46) -> 761287.43 | H35: =MAX(0,pf_ltv_limit*'Asset Register'!H61-H32-H46) -> 791806.35 | I35: =MAX(0,pf_ltv_limit*'Asset Register'!I61-I32-I46) -> 794385.61 | J35: =MAX(0,pf_ltv_limit*'Asset Register'!J61-J32-J46) -> 799342.69 | K35: =MAX(0,pf_ltv_limit*'Asset Register'!K61-K32-K46) -> 791468.33 | ... BA35: =MAX(0,pf_ltv_limit*'Asset Register'!BA61-BA32-BA46) -> 47700609
A36: Funding requirement | B36: £ | D36: =MAX(0,'Asset Register'!D128-D14-(D22+D24+D25)+MAX(0,MAX(C60,min_cash_buffer)-'Financial Statements'!C65)) -> 53300 | E36: =MAX(0,'Asset Register'!E128-E14-(E22+E24+E25)+MAX(0,MAX(D60,min_cash_buffer)-'Financial Statements'!D65)) -> 410804.21 | F36: =MAX(0,'Asset Register'!F128-F14-(F22+F24+F25)+MAX(0,MAX(E60,min_cash_buffer)-'Financial Statements'!E65)) -> 688284.35 | G36: =MAX(0,'Asset Register'!G128-G14-(G22+G24+G25)+MAX(0,MAX(F60,min_cash_buffer)-'Financial Statements'!F65)) -> 666160.56 | H36: =MAX(0,'Asset Register'!H128-H14-(H22+H24+H25)+MAX(0,MAX(G60,min_cash_buffer)-'Financial Statements'!G65)) -> 724453.84 | I36: =MAX(0,'Asset Register'!I128-I14-(I22+I24+I25)+MAX(0,MAX(H60,min_cash_buffer)-'Financial Statements'!H65)) -> 753778.21 | J36: =MAX(0,'Asset Register'!J128-J14-(J22+J24+J25)+MAX(0,MAX(I60,min_cash_buffer)-'Financial Statements'!I65)) -> 800515.78 | K36: =MAX(0,'Asset Register'!K128-K14-(K22+K24+K25)+MAX(0,MAX(J60,min_cash_buffer)-'Financial Statements'!J65)) -> 842662.63 | ... BA36: =MAX(0,'Asset Register'!BA128-BA14-(BA22+BA24+BA25)+MAX(0,MAX(AZ60,min_cash_buffer)-'Financial Statements'!AZ65)) -> 591318.2
A37: Drawdown | B37: £ | D37: =IF(AND(D$6<=pf_invest_phase_yrs,OR(pf_refi_toggle=0,D$6<pf_refi_year)),MIN(D36,D35,D34),0) -> 53300 | E37: =IF(AND(E$6<=pf_invest_phase_yrs,OR(pf_refi_toggle=0,E$6<pf_refi_year)),MIN(E36,E35,E34),0) -> 410804.21 | F37: =IF(AND(F$6<=pf_invest_phase_yrs,OR(pf_refi_toggle=0,F$6<pf_refi_year)),MIN(F36,F35,F34),0) -> 688284.35 | G37: =IF(AND(G$6<=pf_invest_phase_yrs,OR(pf_refi_toggle=0,G$6<pf_refi_year)),MIN(G36,G35,G34),0) -> 666160.56 | H37: =IF(AND(H$6<=pf_invest_phase_yrs,OR(pf_refi_toggle=0,H$6<pf_refi_year)),MIN(H36,H35,H34),0) -> 724453.84 | I37: =IF(AND(I$6<=pf_invest_phase_yrs,OR(pf_refi_toggle=0,I$6<pf_refi_year)),MIN(I36,I35,I34),0) -> 753778.21 | J37: =IF(AND(J$6<=pf_invest_phase_yrs,OR(pf_refi_toggle=0,J$6<pf_refi_year)),MIN(J36,J35,J34),0) -> 799342.69 | K37: =IF(AND(K$6<=pf_invest_phase_yrs,OR(pf_refi_toggle=0,K$6<pf_refi_year)),MIN(K36,K35,K34),0) -> 791468.33 | ... BA37: =IF(AND(BA$6<=pf_invest_phase_yrs,OR(pf_refi_toggle=0,BA$6<pf_refi_year)),MIN(BA36,BA35,BA34),0) -> 0
A38: Cumulative capital raised — closing | B38: £ | D38: =D33+D37 -> 53300 | E38: =E33+E37 -> 464104.21 | F38: =F33+F37 -> 1152388.6 | G38: =G33+G37 -> 1818549.1 | H38: =H33+H37 -> 2543003 | I38: =I33+I37 -> 3296781.2 | J38: =J33+J37 -> 4096123.9 | K38: =K33+K37 -> 4887592.2 | ... BA38: =BA33+BA37 -> 6577569.3
A39: Implied SLC coupon rate (index + spread) | B39: % p.a. | D39: ='Macro & Indexation'!D$9+pf_coupon_spread -> 0.0625 | E39: ='Macro & Indexation'!E$9+pf_coupon_spread -> 0.0625 | F39: ='Macro & Indexation'!F$9+pf_coupon_spread -> 0.0625 | G39: ='Macro & Indexation'!G$9+pf_coupon_spread -> 0.0625 | H39: ='Macro & Indexation'!H$9+pf_coupon_spread -> 0.0625 | I39: ='Macro & Indexation'!I$9+pf_coupon_spread -> 0.0625 | J39: ='Macro & Indexation'!J$9+pf_coupon_spread -> 0.0625 | K39: ='Macro & Indexation'!K$9+pf_coupon_spread -> 0.0625 | ... BA39: ='Macro & Indexation'!BA$9+pf_coupon_spread -> 0.0625
A40: Interest paid | B40: £ | D40: =-(D32+D37/2)*D39 -> -1665.625 | E40: =-(E32+E37/2)*E39 -> -16252.163 | F40: =-(F32+F37/2)*F39 -> -51325.925 | G40: =-(G32+G37/2)*G39 -> -95473.199 | H40: =-(H32+H37/2)*H39 -> -141837.17 | I40: =-(I32+I37/2)*I39 -> -192143.83 | J40: =-(J32+J37/2)*J39 -> -246071.34 | K40: =-(K32+K37/2)*K39 -> -302560.45 | ... BA40: =-(BA32+BA37/2)*BA39 -> -257699.73
A41: Progressive release to SLC reserves | B41: £ | D41: =-IF(D$6>=pf_release_start_yr,(D32+D37)*pf_release_rate,0) -> 0 | E41: =-IF(E$6>=pf_release_start_yr,(E32+E37)*pf_release_rate,0) -> 0 | F41: =-IF(F$6>=pf_release_start_yr,(F32+F37)*pf_release_rate,0) -> 0 | G41: =-IF(G$6>=pf_release_start_yr,(G32+G37)*pf_release_rate,0) -> 0 | H41: =-IF(H$6>=pf_release_start_yr,(H32+H37)*pf_release_rate,0) -> 0 | I41: =-IF(I$6>=pf_release_start_yr,(I32+I37)*pf_release_rate,0) -> 0 | J41: =-IF(J$6>=pf_release_start_yr,(J32+J37)*pf_release_rate,0) -> 0 | K41: =-IF(K$6>=pf_release_start_yr,(K32+K37)*pf_release_rate,0) -> 0 | ... BA41: =-IF(BA$6>=pf_release_start_yr,(BA32+BA37)*pf_release_rate,0) -> -247391.74
A42: Transferred to commercial mortgage (refinancing) | B42: £ | D42: =IF(AND(pf_refi_toggle=1,D$6=pf_refi_year),-(D32+D37+D41),0) -> 0 | E42: =IF(AND(pf_refi_toggle=1,E$6=pf_refi_year),-(E32+E37+E41),0) -> 0 | F42: =IF(AND(pf_refi_toggle=1,F$6=pf_refi_year),-(F32+F37+F41),0) -> 0 | G42: =IF(AND(pf_refi_toggle=1,G$6=pf_refi_year),-(G32+G37+G41),0) -> 0 | H42: =IF(AND(pf_refi_toggle=1,H$6=pf_refi_year),-(H32+H37+H41),0) -> 0 | I42: =IF(AND(pf_refi_toggle=1,I$6=pf_refi_year),-(I32+I37+I41),0) -> 0 | J42: =IF(AND(pf_refi_toggle=1,J$6=pf_refi_year),-(J32+J37+J41),0) -> 0 | K42: =IF(AND(pf_refi_toggle=1,K$6=pf_refi_year),-(K32+K37+K41),0) -> 0 | ... BA42: =IF(AND(pf_refi_toggle=1,BA$6=pf_refi_year),-(BA32+BA37+BA41),0) -> 0
A43: Closing balance | B43: £ | D43: =D32+D37+D41+D42 -> 53300 | E43: =E32+E37+E41+E42 -> 465436.71 | F43: =F32+F37+F41+F42 -> 1165357 | G43: =G32+G37+G41+G42 -> 1860651.5 | H43: =H32+H37+H41+H42 -> 2631621.6 | I43: =I32+I37+I41+I42 -> 3451190.3 | J43: =J32+J37+J41+J42 -> 4336812.8 | K43: =K32+K37+K41+K42 -> 5236701.4 | ... BA43: =BA32+BA37+BA41+BA42 -> 3875803.9
A45: COMMERCIAL MORTGAGE (POST-REFINANCING)
A46: Opening balance | B46: £ | D46: =0 -> 0 | E46: =D50 -> 0 | F46: =E50 -> 0 | G46: =F50 -> 0 | H46: =G50 -> 0 | I46: =H50 -> 0 | J46: =I50 -> 0 | K46: =J50 -> 0 | L46: =K50 -> 0 | ... BA46: =AZ50 -> 0
A47: Drawdown on refinancing | B47: £ | D47: =-D42 -> 0 | E47: =-E42 -> 0 | F47: =-F42 -> 0 | G47: =-G42 -> 0 | H47: =-H42 -> 0 | I47: =-I42 -> 0 | J47: =-J42 -> 0 | K47: =-K42 -> 0 | ... BA47: =-BA42 -> 0
A48: Interest paid | B48: £ | D48: =-(D46+D47)*pf_refi_rate -> 0 | E48: =-(E46+E47)*pf_refi_rate -> 0 | F48: =-(F46+F47)*pf_refi_rate -> 0 | G48: =-(G46+G47)*pf_refi_rate -> 0 | H48: =-(H46+H47)*pf_refi_rate -> 0 | I48: =-(I46+I47)*pf_refi_rate -> 0 | J48: =-(J46+J47)*pf_refi_rate -> 0 | K48: =-(K46+K47)*pf_refi_rate -> 0 | ... BA48: =-(BA46+BA47)*pf_refi_rate -> 0
A49: Principal repaid | B49: £ | D49: =-MIN(D46+D47,IF(D46+D47=0,0,(D46+D47)/MAX(1,pf_refi_amort_yrs-(D$6-pf_refi_year)))) -> 0 | E49: =-MIN(E46+E47,IF(E46+E47=0,0,(E46+E47)/MAX(1,pf_refi_amort_yrs-(E$6-pf_refi_year)))) -> 0 | F49: =-MIN(F46+F47,IF(F46+F47=0,0,(F46+F47)/MAX(1,pf_refi_amort_yrs-(F$6-pf_refi_year)))) -> 0 | G49: =-MIN(G46+G47,IF(G46+G47=0,0,(G46+G47)/MAX(1,pf_refi_amort_yrs-(G$6-pf_refi_year)))) -> 0 | H49: =-MIN(H46+H47,IF(H46+H47=0,0,(H46+H47)/MAX(1,pf_refi_amort_yrs-(H$6-pf_refi_year)))) -> 0 | I49: =-MIN(I46+I47,IF(I46+I47=0,0,(I46+I47)/MAX(1,pf_refi_amort_yrs-(I$6-pf_refi_year)))) -> 0 | J49: =-MIN(J46+J47,IF(J46+J47=0,0,(J46+J47)/MAX(1,pf_refi_amort_yrs-(J$6-pf_refi_year)))) -> 0 | K49: =-MIN(K46+K47,IF(K46+K47=0,0,(K46+K47)/MAX(1,pf_refi_amort_yrs-(K$6-pf_refi_year)))) -> 0 | ... BA49: =-MIN(BA46+BA47,IF(BA46+BA47=0,0,(BA46+BA47)/MAX(1,pf_refi_amort_yrs-(BA$6-pf_refi_year)))) -> 0
A50: Closing balance | B50: £ | D50: =D46+D47+D49 -> 0 | E50: =E46+E47+E49 -> 0 | F50: =F46+F47+F49 -> 0 | G50: =G46+G47+G49 -> 0 | H50: =H46+H47+H49 -> 0 | I50: =I46+I47+I49 -> 0 | J50: =J46+J47+J49 -> 0 | K50: =K46+K47+K49 -> 0 | ... BA50: =BA46+BA47+BA49 -> 0
A52: DEBT SERVICE, LEVERAGE & RESERVES
A53: Total interest paid | B53: £ | D53: =-(D40+D48) -> 1665.625 | E53: =-(E40+E48) -> 16252.163 | F53: =-(F40+F48) -> 51325.925 | G53: =-(G40+G48) -> 95473.199 | H53: =-(H40+H48) -> 141837.17 | I53: =-(I40+I48) -> 192143.83 | J53: =-(J40+J48) -> 246071.34 | K53: =-(K40+K48) -> 302560.45 | ... BA53: =-(BA40+BA48) -> 257699.73
A54: Total principal repaid | B54: £ | D54: =-D49 -> 0 | E54: =-E49 -> 0 | F54: =-F49 -> 0 | G54: =-G49 -> 0 | H54: =-H49 -> 0 | I54: =-I49 -> 0 | J54: =-J49 -> 0 | K54: =-K49 -> 0 | ... BA54: =-BA49 -> 0
A55: Total debt service | B55: £ | D55: =D53+D54 -> 1665.625 | E55: =E53+E54 -> 16252.163 | F55: =F53+F54 -> 51325.925 | G55: =G53+G54 -> 95473.199 | H55: =H53+H54 -> 141837.17 | I55: =I53+I54 -> 192143.83 | J55: =J53+J54 -> 246071.34 | K55: =K53+K54 -> 302560.45 | ... BA55: =BA53+BA54 -> 257699.73
A56: Total debt outstanding | B56: £ | D56: =D43+D50 -> 53300 | E56: =E43+E50 -> 465436.71 | F56: =F43+F50 -> 1165357 | G56: =G43+G50 -> 1860651.5 | H56: =H43+H50 -> 2631621.6 | I56: =I43+I50 -> 3451190.3 | J56: =J43+J50 -> 4336812.8 | K56: =K43+K50 -> 5236701.4 | ... BA56: =BA43+BA50 -> 3875803.9
A57: Loan-to-value (LTV) | B57: % | D57: =IF('Asset Register'!D61=0,0,D56/'Asset Register'!D61) -> 0.19035714 | E57: =IF('Asset Register'!E61=0,0,E56/'Asset Register'!E61) -> 0.53535393 | F57: =IF('Asset Register'!F61=0,0,F56/'Asset Register'!F61) -> 0.64754358 | G57: =IF('Asset Register'!G61=0,0,G56/'Asset Register'!G61) -> 0.66595278 | H57: =IF('Asset Register'!H61=0,0,H56/'Asset Register'!H61) -> 0.6825316 | I57: =IF('Asset Register'!I61=0,0,I56/'Asset Register'!I61) -> 0.69185944 | J57: =IF('Asset Register'!J61=0,0,J56/'Asset Register'!J61) -> 0.7 | K57: =IF('Asset Register'!K61=0,0,K56/'Asset Register'!K61) -> 0.7 | ... BA57: =IF('Asset Register'!BA61=0,0,BA56/'Asset Register'!BA61) -> 0.05235167
A58: Total capital employed (liabilities + reserves) | B58: £ | D58: ='Financial Statements'!D44 -> 307624.38 | E58: ='Financial Statements'!E44 -> 898789.26 | F58: ='Financial Statements'!F44 -> 1818567 | G58: ='Financial Statements'!G44 -> 2795510.8 | H58: ='Financial Statements'!H44 -> 3859055 | I58: ='Financial Statements'!I44 -> 5001350.1 | J58: ='Financial Statements'!J44 -> 6229032.7 | K58: ='Financial Statements'!K44 -> 7495413 | ... BA58: ='Financial Statements'!BA44 -> 79303187
A59: Community shares % of total capital | B59: % | D59: =IF(D58=0,0,D26/D58) -> 0 | E59: =IF(E58=0,0,E26/E58) -> 0.085566325 | F59: =IF(F58=0,0,F26/F58) -> 0.112985 | G59: =IF(G58=0,0,G26/G58) -> 0.14425773 | H59: =IF(H58=0,0,H26/H58) -> 0.15497555 | I59: =IF(I58=0,0,I26/I58) -> 0.16300577 | J59: =IF(J58=0,0,J26/J58) -> 0.16776075 | K59: =IF(K58=0,0,K26/K58) -> 0.17235901 | ... BA59: =IF(BA58=0,0,BA26/BA58) -> 0.17538916
A60: Target reserve | B60: £ | D60: =reserve_tgt_months/12*D55*MIN(1,D$6/reserve_build_year) -> 83.28125 | E60: =reserve_tgt_months/12*E55*MIN(1,E$6/reserve_build_year) -> 1625.2163 | F60: =reserve_tgt_months/12*F55*MIN(1,F$6/reserve_build_year) -> 7698.8888 | G60: =reserve_tgt_months/12*G55*MIN(1,G$6/reserve_build_year) -> 19094.64 | H60: =reserve_tgt_months/12*H55*MIN(1,H$6/reserve_build_year) -> 35459.292 | I60: =reserve_tgt_months/12*I55*MIN(1,I$6/reserve_build_year) -> 57643.148 | J60: =reserve_tgt_months/12*J55*MIN(1,J$6/reserve_build_year) -> 86124.969 | K60: =reserve_tgt_months/12*K55*MIN(1,K$6/reserve_build_year) -> 121024.18 | ... BA60: =reserve_tgt_months/12*BA55*MIN(1,BA$6/reserve_build_year) -> 128849.86
A61: Minimum reserve covenant | B61: £ | D61: =reserve_min_months/12*D55 -> 416.40625 | E61: =reserve_min_months/12*E55 -> 4063.0407 | F61: =reserve_min_months/12*F55 -> 12831.481 | G61: =reserve_min_months/12*G55 -> 23868.3 | H61: =reserve_min_months/12*H55 -> 35459.292 | I61: =reserve_min_months/12*I55 -> 48035.957 | J61: =reserve_min_months/12*J55 -> 61517.835 | K61: =reserve_min_months/12*K55 -> 75640.114 | ... BA61: =reserve_min_months/12*BA55 -> 64424.931
A62: Unfunded requirement (LTV cap binding) | B62: £ | D62: =MAX(0,D36-D37) -> 0 | E62: =MAX(0,E36-E37) -> 0 | F62: =MAX(0,F36-F37) -> 0 | G62: =MAX(0,G36-G37) -> 0 | H62: =MAX(0,H36-H37) -> 0 | I62: =MAX(0,I36-I37) -> 0 | J62: =MAX(0,J36-J37) -> 1173.0872 | K62: =MAX(0,K36-K37) -> 51194.293 | ... BA62: =MAX(0,BA36-BA37) -> 591318.2
A64: DSCR (operating surplus / debt service) | B64: x | D64: =IF(D55<=0,"",'Financial Statements'!D19/D55) -> 153.69006 | E64: =IF(E55<=0,"",'Financial Statements'!E19/E55) -> 6.7625919 | F64: =IF(F55<=0,"",'Financial Statements'!F19/F55) -> 2.4574866 | G64: =IF(G55<=0,"",'Financial Statements'!G19/G55) -> 1.5881869 | H64: =IF(H55<=0,"",'Financial Statements'!H19/H55) -> 1.3369725 | I64: =IF(I55<=0,"",'Financial Statements'!I19/I55) -> 1.1893294 | J64: =IF(J55<=0,"",'Financial Statements'!J19/J55) -> 1.0975806 | K64: =IF(K55<=0,"",'Financial Statements'!K19/K55) -> 1.0368735 | ... BA64: =IF(BA55<=0,"",'Financial Statements'!BA19/BA55) -> 8.6167902
A65: Reserve cover | B65: months of debt service | D65: =IF(D55<=0,"",'Financial Statements'!D65/(D55/12)) -> 193.25629 | E65: =IF(E55<=0,"",'Financial Statements'!E65/(E55/12)) -> 19.292887 | F65: =IF(F55<=0,"",'Financial Statements'!F65/(F55/12)) -> 2.479677 | G65: =IF(G55<=0,"",'Financial Statements'!G65/(G55/12)) -> -1.824371 | H65: =IF(H55<=0,"",'Financial Statements'!H65/(H55/12)) -> -1.9692049 | I65: =IF(I55<=0,"",'Financial Statements'!I65/(I55/12)) -> -1.6963842 | J65: =IF(J55<=0,"",'Financial Statements'!J65/(J55/12)) -> -1.138393 | K65: =IF(K55<=0,"",'Financial Statements'!K65/(K55/12)) -> -2.4783964 | ... BA65: =IF(BA55<=0,"",'Financial Statements'!BA65/(BA55/12)) -> 124.69747

Sheet Asset Register
A1: PROPERTY PORTFOLIO — ASSET REGISTER
A2: Each acquisition year is tracked as its own cohort. Values grow with HPI; cohort rents grow with rent inflation from the purchase-year rent.
A6: Model year | D6: 1 | E6: 2 | F6: 3 | G6: 4 | H6: 5 | I6: 6 | J6: 7 | K6: 8 | L6: 9 | M6: 10 | N6: 11 | O6: 12 | P6: 13 | Q6: 14 | R6: 15 | S6: 16 | T6: 17 | U6: 18 | V6: 19 | W6: 20 | X6: 21 | Y6: 22 | Z6: 23 | AA6: 24 | AB6: 25 | AC6: 26 | AD6: 27 | AE6: 28 | AF6: 29 | AG6: 30 | AH6: 31 | AI6: 32 | AJ6: 33 | AK6: 34 | AL6: 35 | AM6: 36 | AN6: 37 | AO6: 38 | AP6: 39 | AQ6: 40 | AR6: 41 | AS6: 42 | AT6: 43 | AU6: 44 | AV6: 45 | AW6: 46 | AX6: 47 | AY6: 48 | AZ6: 49 | BA6: 50
A7: Calendar year | D7: =base_calendar_year+D$6-1 -> 2026 | E7: =base_calendar_year+E$6-1 -> 2027 | F7: =base_calendar_year+F$6-1 -> 2028 | G7: =base_calendar_year+G$6-1 -> 2029 | H7: =base_calendar_year+H$6-1 -> 2030 | I7: =base_calendar_year+I$6-1 -> 2031 | J7: =base_calendar_year+J$6-1 -> 2032 | K7: =base_calendar_year+K$6-1 -> 2033 | ... BA7: =base_calendar_year+BA$6-1 -> 2075
A9: COHORT PORTFOLIO VALUE (£, HPI-indexed)
A10: Cohort — Year 1 | B10: 1 | D10: =IF(D$6<$B10,0,IF(D$6=$B10,'Growth Engine'!D$10*'Macro & Indexation'!D$19,C10*(1+'Macro & Indexation'!D$16))) -> 280000 | E10: =IF(E$6<$B10,0,IF(E$6=$B10,'Growth Engine'!E$10*'Macro & Indexation'!E$19,D10*(1+'Macro & Indexation'!E$16))) -> 289800 | F10: =IF(F$6<$B10,0,IF(F$6=$B10,'Growth Engine'!F$10*'Macro & Indexation'!F$19,E10*(1+'Macro & Indexation'!F$16))) -> 299943 | G10: =IF(G$6<$B10,0,IF(G$6=$B10,'Growth Engine'!G$10*'Macro & Indexation'!G$19,F10*(1+'Macro & Indexation'!G$16))) -> 310441.01 | H10: =IF(H$6<$B10,0,IF(H$6=$B10,'Growth Engine'!H$10*'Macro & Indexation'!H$19,G10*(1+'Macro & Indexation'!H$16))) -> 321306.44 | I10: =IF(I$6<$B10,0,IF(I$6=$B10,'Growth Engine'!I$10*'Macro & Indexation'!I$19,H10*(1+'Macro & Indexation'!I$16))) -> 332552.17 | J10: =IF(J$6<$B10,0,IF(J$6=$B10,'Growth Engine'!J$10*'Macro & Indexation'!J$19,I10*(1+'Macro & Indexation'!J$16))) -> 344191.49 | K10: =IF(K$6<$B10,0,IF(K$6=$B10,'Growth Engine'!K$10*'Macro & Indexation'!K$19,J10*(1+'Macro & Indexation'!K$16))) -> 356238.19 | ... BA10: =IF(BA$6<$B10,0,IF(BA$6=$B10,'Growth Engine'!BA$10*'Macro & Indexation'!BA$19,AZ10*(1+'Macro & Indexation'!BA$16))) -> 1510898.1
A11: Cohort — Year 2 | B11: 2 | D11: =IF(D$6<$B11,0,IF(D$6=$B11,'Growth Engine'!D$10*'Macro & Indexation'!D$19,C11*(1+'Macro & Indexation'!D$16))) -> 0 | E11: =IF(E$6<$B11,0,IF(E$6=$B11,'Growth Engine'!E$10*'Macro & Indexation'!E$19,D11*(1+'Macro & Indexation'!E$16))) -> 579600 | F11: =IF(F$6<$B11,0,IF(F$6=$B11,'Growth Engine'!F$10*'Macro & Indexation'!F$19,E11*(1+'Macro & Indexation'!F$16))) -> 599886 | G11: =IF(G$6<$B11,0,IF(G$6=$B11,'Growth Engine'!G$10*'Macro & Indexation'!G$19,F11*(1+'Macro & Indexation'!G$16))) -> 620882.01 | H11: =IF(H$6<$B11,0,IF(H$6=$B11,'Growth Engine'!H$10*'Macro & Indexation'!H$19,G11*(1+'Macro & Indexation'!H$16))) -> 642612.88 | I11: =IF(I$6<$B11,0,IF(I$6=$B11,'Growth Engine'!I$10*'Macro & Indexation'!I$19,H11*(1+'Macro & Indexation'!I$16))) -> 665104.33 | J11: =IF(J$6<$B11,0,IF(J$6=$B11,'Growth Engine'!J$10*'Macro & Indexation'!J$19,I11*(1+'Macro & Indexation'!J$16))) -> 688382.98 | K11: =IF(K$6<$B11,0,IF(K$6=$B11,'Growth Engine'!K$10*'Macro & Indexation'!K$19,J11*(1+'Macro & Indexation'!K$16))) -> 712476.39 | ... BA11: =IF(BA$6<$B11,0,IF(BA$6=$B11,'Growth Engine'!BA$10*'Macro & Indexation'!BA$19,AZ11*(1+'Macro & Indexation'!BA$16))) -> 3021796.2
A12: Cohort — Year 3 | B12: 3 | D12: =IF(D$6<$B12,0,IF(D$6=$B12,'Growth Engine'!D$10*'Macro & Indexation'!D$19,C12*(1+'Macro & Indexation'!D$16))) -> 0 | E12: =IF(E$6<$B12,0,IF(E$6=$B12,'Growth Engine'!E$10*'Macro & Indexation'!E$19,D12*(1+'Macro & Indexation'!E$16))) -> 0 | F12: =IF(F$6<$B12,0,IF(F$6=$B12,'Growth Engine'!F$10*'Macro & Indexation'!F$19,E12*(1+'Macro & Indexation'!F$16))) -> 899829 | G12: =IF(G$6<$B12,0,IF(G$6=$B12,'Growth Engine'!G$10*'Macro & Indexation'!G$19,F12*(1+'Macro & Indexation'!G$16))) -> 931323.01 | H12: =IF(H$6<$B12,0,IF(H$6=$B12,'Growth Engine'!H$10*'Macro & Indexation'!H$19,G12*(1+'Macro & Indexation'!H$16))) -> 963919.32 | I12: =IF(I$6<$B12,0,IF(I$6=$B12,'Growth Engine'!I$10*'Macro & Indexation'!I$19,H12*(1+'Macro & Indexation'!I$16))) -> 997656.5 | J12: =IF(J$6<$B12,0,IF(J$6=$B12,'Growth Engine'!J$10*'Macro & Indexation'!J$19,I12*(1+'Macro & Indexation'!J$16))) -> 1032574.5 | K12: =IF(K$6<$B12,0,IF(K$6=$B12,'Growth Engine'!K$10*'Macro & Indexation'!K$19,J12*(1+'Macro & Indexation'!K$16))) -> 1068714.6 | ... BA12: =IF(BA$6<$B12,0,IF(BA$6=$B12,'Growth Engine'!BA$10*'Macro & Indexation'!BA$19,AZ12*(1+'Macro & Indexation'!BA$16))) -> 4532694.3
A13: Cohort — Year 4 | B13: 4 | D13: =IF(D$6<$B13,0,IF(D$6=$B13,'Growth Engine'!D$10*'Macro & Indexation'!D$19,C13*(1+'Macro & Indexation'!D$16))) -> 0 | E13: =IF(E$6<$B13,0,IF(E$6=$B13,'Growth Engine'!E$10*'Macro & Indexation'!E$19,D13*(1+'Macro & Indexation'!E$16))) -> 0 | F13: =IF(F$6<$B13,0,IF(F$6=$B13,'Growth Engine'!F$10*'Macro & Indexation'!F$19,E13*(1+'Macro & Indexation'!F$16))) -> 0 | G13: =IF(G$6<$B13,0,IF(G$6=$B13,'Growth Engine'!G$10*'Macro & Indexation'!G$19,F13*(1+'Macro & Indexation'!G$16))) -> 931323.01 | H13: =IF(H$6<$B13,0,IF(H$6=$B13,'Growth Engine'!H$10*'Macro & Indexation'!H$19,G13*(1+'Macro & Indexation'!H$16))) -> 963919.32 | I13: =IF(I$6<$B13,0,IF(I$6=$B13,'Growth Engine'!I$10*'Macro & Indexation'!I$19,H13*(1+'Macro & Indexation'!I$16))) -> 997656.5 | J13: =IF(J$6<$B13,0,IF(J$6=$B13,'Growth Engine'!J$10*'Macro & Indexation'!J$19,I13*(1+'Macro & Indexation'!J$16))) -> 1032574.5 | K13: =IF(K$6<$B13,0,IF(K$6=$B13,'Growth Engine'!K$10*'Macro & Indexation'!K$19,J13*(1+'Macro & Indexation'!K$16))) -> 1068714.6 | ... BA13: =IF(BA$6<$B13,0,IF(BA$6=$B13,'Growth Engine'!BA$10*'Macro & Indexation'!BA$19,AZ13*(1+'Macro & Indexation'!BA$16))) -> 4532694.3
A14: Cohort — Year 5 | B14: 5 | D14: =IF(D$6<$B14,0,IF(D$6=$B14,'Growth Engine'!D$10*'Macro & Indexation'!D$19,C14*(1+'Macro & Indexation'!D$16))) -> 0 | E14: =IF(E$6<$B14,0,IF(E$6=$B14,'Growth Engine'!E$10*'Macro & Indexation'!E$19,D14*(1+'Macro & Indexation'!E$16))) -> 0 | F14: =IF(F$6<$B14,0,IF(F$6=$B14,'Growth Engine'!F$10*'Macro & Indexation'!F$19,E14*(1+'Macro & Indexation'!F$16))) -> 0 | G14: =IF(G$6<$B14,0,IF(G$6=$B14,'Growth Engine'!G$10*'Macro & Indexation'!G$19,F14*(1+'Macro & Indexation'!G$16))) -> 0 | H14: =IF(H$6<$B14,0,IF(H$6=$B14,'Growth Engine'!H$10*'Macro & Indexation'!H$19,G14*(1+'Macro & Indexation'!H$16))) -> 963919.32 | I14: =IF(I$6<$B14,0,IF(I$6=$B14,'Growth Engine'!I$10*'Macro & Indexation'!I$19,H14*(1+'Macro & Indexation'!I$16))) -> 997656.5 | J14: =IF(J$6<$B14,0,IF(J$6=$B14,'Growth Engine'!J$10*'Macro & Indexation'!J$19,I14*(1+'Macro & Indexation'!J$16))) -> 1032574.5 | K14: =IF(K$6<$B14,0,IF(K$6=$B14,'Growth Engine'!K$10*'Macro & Indexation'!K$19,J14*(1+'Macro & Indexation'!K$16))) -> 1068714.6 | ... BA14: =IF(BA$6<$B14,0,IF(BA$6=$B14,'Growth Engine'!BA$10*'Macro & Indexation'!BA$19,AZ14*(1+'Macro & Indexation'!BA$16))) -> 4532694.3
A15: Cohort — Year 6 | B15: 6 | D15: =IF(D$6<$B15,0,IF(D$6=$B15,'Growth Engine'!D$10*'Macro & Indexation'!D$19,C15*(1+'Macro & Indexation'!D$16))) -> 0 | E15: =IF(E$6<$B15,0,IF(E$6=$B15,'Growth Engine'!E$10*'Macro & Indexation'!E$19,D15*(1+'Macro & Indexation'!E$16))) -> 0 | F15: =IF(F$6<$B15,0,IF(F$6=$B15,'Growth Engine'!F$10*'Macro & Indexation'!F$19,E15*(1+'Macro & Indexation'!F$16))) -> 0 | G15: =IF(G$6<$B15,0,IF(G$6=$B15,'Growth Engine'!G$10*'Macro & Indexation'!G$19,F15*(1+'Macro & Indexation'!G$16))) -> 0 | H15: =IF(H$6<$B15,0,IF(H$6=$B15,'Growth Engine'!H$10*'Macro & Indexation'!H$19,G15*(1+'Macro & Indexation'!H$16))) -> 0 | I15: =IF(I$6<$B15,0,IF(I$6=$B15,'Growth Engine'!I$10*'Macro & Indexation'!I$19,H15*(1+'Macro & Indexation'!I$16))) -> 997656.5 | J15: =IF(J$6<$B15,0,IF(J$6=$B15,'Growth Engine'!J$10*'Macro & Indexation'!J$19,I15*(1+'Macro & Indexation'!J$16))) -> 1032574.5 | K15: =IF(K$6<$B15,0,IF(K$6=$B15,'Growth Engine'!K$10*'Macro & Indexation'!K$19,J15*(1+'Macro & Indexation'!K$16))) -> 1068714.6 | ... BA15: =IF(BA$6<$B15,0,IF(BA$6=$B15,'Growth Engine'!BA$10*'Macro & Indexation'!BA$19,AZ15*(1+'Macro & Indexation'!BA$16))) -> 4532694.3
A16: Cohort — Year 7 | B16: 7 | D16: =IF(D$6<$B16,0,IF(D$6=$B16,'Growth Engine'!D$10*'Macro & Indexation'!D$19,C16*(1+'Macro & Indexation'!D$16))) -> 0 | E16: =IF(E$6<$B16,0,IF(E$6=$B16,'Growth Engine'!E$10*'Macro & Indexation'!E$19,D16*(1+'Macro & Indexation'!E$16))) -> 0 | F16: =IF(F$6<$B16,0,IF(F$6=$B16,'Growth Engine'!F$10*'Macro & Indexation'!F$19,E16*(1+'Macro & Indexation'!F$16))) -> 0 | G16: =IF(G$6<$B16,0,IF(G$6=$B16,'Growth Engine'!G$10*'Macro & Indexation'!G$19,F16*(1+'Macro & Indexation'!G$16))) -> 0 | H16: =IF(H$6<$B16,0,IF(H$6=$B16,'Growth Engine'!H$10*'Macro & Indexation'!H$19,G16*(1+'Macro & Indexation'!H$16))) -> 0 | I16: =IF(I$6<$B16,0,IF(I$6=$B16,'Growth Engine'!I$10*'Macro & Indexation'!I$19,H16*(1+'Macro & Indexation'!I$16))) -> 0 | J16: =IF(J$6<$B16,0,IF(J$6=$B16,'Growth Engine'!J$10*'Macro & Indexation'!J$19,I16*(1+'Macro & Indexation'!J$16))) -> 1032574.5 | K16: =IF(K$6<$B16,0,IF(K$6=$B16,'Growth Engine'!K$10*'Macro & Indexation'!K$19,J16*(1+'Macro & Indexation'!K$16))) -> 1068714.6 | ... BA16: =IF(BA$6<$B16,0,IF(BA$6=$B16,'Growth Engine'!BA$10*'Macro & Indexation'!BA$19,AZ16*(1+'Macro & Indexation'!BA$16))) -> 4532694.3
A17: Cohort — Year 8 | B17: 8 | D17: =IF(D$6<$B17,0,IF(D$6=$B17,'Growth Engine'!D$10*'Macro & Indexation'!D$19,C17*(1+'Macro & Indexation'!D$16))) -> 0 | E17: =IF(E$6<$B17,0,IF(E$6=$B17,'Growth Engine'!E$10*'Macro & Indexation'!E$19,D17*(1+'Macro & Indexation'!E$16))) -> 0 | F17: =IF(F$6<$B17,0,IF(F$6=$B17,'Growth Engine'!F$10*'Macro & Indexation'!F$19,E17*(1+'Macro & Indexation'!F$16))) -> 0 | G17: =IF(G$6<$B17,0,IF(G$6=$B17,'Growth Engine'!G$10*'Macro & Indexation'!G$19,F17*(1+'Macro & Indexation'!G$16))) -> 0 | H17: =IF(H$6<$B17,0,IF(H$6=$B17,'Growth Engine'!H$10*'Macro & Indexation'!H$19,G17*(1+'Macro & Indexation'!H$16))) -> 0 | I17: =IF(I$6<$B17,0,IF(I$6=$B17,'Growth Engine'!I$10*'Macro & Indexation'!I$19,H17*(1+'Macro & Indexation'!I$16))) -> 0 | J17: =IF(J$6<$B17,0,IF(J$6=$B17,'Growth Engine'!J$10*'Macro & Indexation'!J$19,I17*(1+'Macro & Indexation'!J$16))) -> 0 | K17: =IF(K$6<$B17,0,IF(K$6=$B17,'Growth Engine'!K$10*'Macro & Indexation'!K$19,J17*(1+'Macro & Indexation'!K$16))) -> 1068714.6 | ... BA17: =IF(BA$6<$B17,0,IF(BA$6=$B17,'Growth Engine'!BA$10*'Macro & Indexation'!BA$19,AZ17*(1+'Macro & Indexation'!BA$16))) -> 4532694.3
A18: Cohort — Year 9 | B18: 9 | D18: =IF(D$6<$B18,0,IF(D$6=$B18,'Growth Engine'!D$10*'Macro & Indexation'!D$19,C18*(1+'Macro & Indexation'!D$16))) -> 0 | E18: =IF(E$6<$B18,0,IF(E$6=$B18,'Growth Engine'!E$10*'Macro & Indexation'!E$19,D18*(1+'Macro & Indexation'!E$16))) -> 0 | F18: =IF(F$6<$B18,0,IF(F$6=$B18,'Growth Engine'!F$10*'Macro & Indexation'!F$19,E18*(1+'Macro & Indexation'!F$16))) -> 0 | G18: =IF(G$6<$B18,0,IF(G$6=$B18,'Growth Engine'!G$10*'Macro & Indexation'!G$19,F18*(1+'Macro & Indexation'!G$16))) -> 0 | H18: =IF(H$6<$B18,0,IF(H$6=$B18,'Growth Engine'!H$10*'Macro & Indexation'!H$19,G18*(1+'Macro & Indexation'!H$16))) -> 0 | I18: =IF(I$6<$B18,0,IF(I$6=$B18,'Growth Engine'!I$10*'Macro & Indexation'!I$19,H18*(1+'Macro & Indexation'!I$16))) -> 0 | J18: =IF(J$6<$B18,0,IF(J$6=$B18,'Growth Engine'!J$10*'Macro & Indexation'!J$19,I18*(1+'Macro & Indexation'!J$16))) -> 0 | K18: =IF(K$6<$B18,0,IF(K$6=$B18,'Growth Engine'!K$10*'Macro & Indexation'!K$19,J18*(1+'Macro & Indexation'!K$16))) -> 0 | ... BA18: =IF(BA$6<$B18,0,IF(BA$6=$B18,'Growth Engine'!BA$10*'Macro & Indexation'!BA$19,AZ18*(1+'Macro & Indexation'!BA$16))) -> 4532694.3
A19: Cohort — Year 10 | B19: 10 | D19: =IF(D$6<$B19,0,IF(D$6=$B19,'Growth Engine'!D$10*'Macro & Indexation'!D$19,C19*(1+'Macro & Indexation'!D$16))) -> 0 | E19: =IF(E$6<$B19,0,IF(E$6=$B19,'Growth Engine'!E$10*'Macro & Indexation'!E$19,D19*(1+'Macro & Indexation'!E$16))) -> 0 | F19: =IF(F$6<$B19,0,IF(F$6=$B19,'Growth Engine'!F$10*'Macro & Indexation'!F$19,E19*(1+'Macro & Indexation'!F$16))) -> 0 | G19: =IF(G$6<$B19,0,IF(G$6=$B19,'Growth Engine'!G$10*'Macro & Indexation'!G$19,F19*(1+'Macro & Indexation'!G$16))) -> 0 | H19: =IF(H$6<$B19,0,IF(H$6=$B19,'Growth Engine'!H$10*'Macro & Indexation'!H$19,G19*(1+'Macro & Indexation'!H$16))) -> 0 | I19: =IF(I$6<$B19,0,IF(I$6=$B19,'Growth Engine'!I$10*'Macro & Indexation'!I$19,H19*(1+'Macro & Indexation'!I$16))) -> 0 | J19: =IF(J$6<$B19,0,IF(J$6=$B19,'Growth Engine'!J$10*'Macro & Indexation'!J$19,I19*(1+'Macro & Indexation'!J$16))) -> 0 | K19: =IF(K$6<$B19,0,IF(K$6=$B19,'Growth Engine'!K$10*'Macro & Indexation'!K$19,J19*(1+'Macro & Indexation'!K$16))) -> 0 | ... BA19: =IF(BA$6<$B19,0,IF(BA$6=$B19,'Growth Engine'!BA$10*'Macro & Indexation'!BA$19,AZ19*(1+'Macro & Indexation'!BA$16))) -> 4532694.3
A20: Cohort — Year 11 | B20: 11 | D20: =IF(D$6<$B20,0,IF(D$6=$B20,'Growth Engine'!D$10*'Macro & Indexation'!D$19,C20*(1+'Macro & Indexation'!D$16))) -> 0 | E20: =IF(E$6<$B20,0,IF(E$6=$B20,'Growth Engine'!E$10*'Macro & Indexation'!E$19,D20*(1+'Macro & Indexation'!E$16))) -> 0 | F20: =IF(F$6<$B20,0,IF(F$6=$B20,'Growth Engine'!F$10*'Macro & Indexation'!F$19,E20*(1+'Macro & Indexation'!F$16))) -> 0 | G20: =IF(G$6<$B20,0,IF(G$6=$B20,'Growth Engine'!G$10*'Macro & Indexation'!G$19,F20*(1+'Macro & Indexation'!G$16))) -> 0 | H20: =IF(H$6<$B20,0,IF(H$6=$B20,'Growth Engine'!H$10*'Macro & Indexation'!H$19,G20*(1+'Macro & Indexation'!H$16))) -> 0 | I20: =IF(I$6<$B20,0,IF(I$6=$B20,'Growth Engine'!I$10*'Macro & Indexation'!I$19,H20*(1+'Macro & Indexation'!I$16))) -> 0 | J20: =IF(J$6<$B20,0,IF(J$6=$B20,'Growth Engine'!J$10*'Macro & Indexation'!J$19,I20*(1+'Macro & Indexation'!J$16))) -> 0 | K20: =IF(K$6<$B20,0,IF(K$6=$B20,'Growth Engine'!K$10*'Macro & Indexation'!K$19,J20*(1+'Macro & Indexation'!K$16))) -> 0 | ... BA20: =IF(BA$6<$B20,0,IF(BA$6=$B20,'Growth Engine'!BA$10*'Macro & Indexation'!BA$19,AZ20*(1+'Macro & Indexation'!BA$16))) -> 1510898.1
A21: Cohort — Year 12 | B21: 12 | D21: =IF(D$6<$B21,0,IF(D$6=$B21,'Growth Engine'!D$10*'Macro & Indexation'!D$19,C21*(1+'Macro & Indexation'!D$16))) -> 0 | E21: =IF(E$6<$B21,0,IF(E$6=$B21,'Growth Engine'!E$10*'Macro & Indexation'!E$19,D21*(1+'Macro & Indexation'!E$16))) -> 0 | F21: =IF(F$6<$B21,0,IF(F$6=$B21,'Growth Engine'!F$10*'Macro & Indexation'!F$19,E21*(1+'Macro & Indexation'!F$16))) -> 0 | G21: =IF(G$6<$B21,0,IF(G$6=$B21,'Growth Engine'!G$10*'Macro & Indexation'!G$19,F21*(1+'Macro & Indexation'!G$16))) -> 0 | H21: =IF(H$6<$B21,0,IF(H$6=$B21,'Growth Engine'!H$10*'Macro & Indexation'!H$19,G21*(1+'Macro & Indexation'!H$16))) -> 0 | I21: =IF(I$6<$B21,0,IF(I$6=$B21,'Growth Engine'!I$10*'Macro & Indexation'!I$19,H21*(1+'Macro & Indexation'!I$16))) -> 0 | J21: =IF(J$6<$B21,0,IF(J$6=$B21,'Growth Engine'!J$10*'Macro & Indexation'!J$19,I21*(1+'Macro & Indexation'!J$16))) -> 0 | K21: =IF(K$6<$B21,0,IF(K$6=$B21,'Growth Engine'!K$10*'Macro & Indexation'!K$19,J21*(1+'Macro & Indexation'!K$16))) -> 0 | ... BA21: =IF(BA$6<$B21,0,IF(BA$6=$B21,'Growth Engine'!BA$10*'Macro & Indexation'!BA$19,AZ21*(1+'Macro & Indexation'!BA$16))) -> 0
... A59: Cohort — Year 50 | B59: 50 | D59: =IF(D$6<$B59,0,IF(D$6=$B59,'Growth Engine'!D$10*'Macro & Indexation'!D$19,C59*(1+'Macro & Indexation'!D$16))) -> 0 | E59: =IF(E$6<$B59,0,IF(E$6=$B59,'Growth Engine'!E$10*'Macro & Indexation'!E$19,D59*(1+'Macro & Indexation'!E$16))) -> 0 | F59: =IF(F$6<$B59,0,IF(F$6=$B59,'Growth Engine'!F$10*'Macro & Indexation'!F$19,E59*(1+'Macro & Indexation'!F$16))) -> 0 | G59: =IF(G$6<$B59,0,IF(G$6=$B59,'Growth Engine'!G$10*'Macro & Indexation'!G$19,F59*(1+'Macro & Indexation'!G$16))) -> 0 | H59: =IF(H$6<$B59,0,IF(H$6=$B59,'Growth Engine'!H$10*'Macro & Indexation'!H$19,G59*(1+'Macro & Indexation'!H$16))) -> 0 | I59: =IF(I$6<$B59,0,IF(I$6=$B59,'Growth Engine'!I$10*'Macro & Indexation'!I$19,H59*(1+'Macro & Indexation'!I$16))) -> 0 | J59: =IF(J$6<$B59,0,IF(J$6=$B59,'Growth Engine'!J$10*'Macro & Indexation'!J$19,I59*(1+'Macro & Indexation'!J$16))) -> 0 | K59: =IF(K$6<$B59,0,IF(K$6=$B59,'Growth Engine'!K$10*'Macro & Indexation'!K$19,J59*(1+'Macro & Indexation'!K$16))) -> 0 | ... BA59: =IF(BA$6<$B59,0,IF(BA$6=$B59,'Growth Engine'!BA$10*'Macro & Indexation'!BA$19,AZ59*(1+'Macro & Indexation'!BA$16))) -> 1510898.1
A61: Total portfolio value — closing | B61: £ | D61: =SUM(D10:D59) -> 280000 | E61: =SUM(E10:E59) -> 869400 | F61: =SUM(F10:F59) -> 1799658 | G61: =SUM(G10:G59) -> 2793969 | H61: =SUM(H10:H59) -> 3855677.3 | I61: =SUM(I10:I59) -> 4988282.5 | J61: =SUM(J10:J59) -> 6195446.8 | K61: =SUM(K10:K59) -> 7481002.1 | ... BA61: =SUM(BA10:BA59) -> 74034006
A62: Additions at cost in year | B62: £ | D62: ='Growth Engine'!D10*'Macro & Indexation'!D19 -> 280000 | E62: ='Growth Engine'!E10*'Macro & Indexation'!E19 -> 579600 | F62: ='Growth Engine'!F10*'Macro & Indexation'!F19 -> 899829 | G62: ='Growth Engine'!G10*'Macro & Indexation'!G19 -> 931323.01 | H62: ='Growth Engine'!H10*'Macro & Indexation'!H19 -> 963919.32 | I62: ='Growth Engine'!I10*'Macro & Indexation'!I19 -> 997656.5 | J62: ='Growth Engine'!J10*'Macro & Indexation'!J19 -> 1032574.5 | K62: ='Growth Engine'!K10*'Macro & Indexation'!K19 -> 1068714.6 | ... BA62: ='Growth Engine'!BA10*'Macro & Indexation'!BA19 -> 1510898.1
A63: HPI revaluation gain / (loss) | B63: £ | D63: =D61-D62 -> 0 | E63: =E61-D61-E62 -> 9800 | F63: =F61-E61-F62 -> 30429 | G63: =G61-F61-G62 -> 62988.03 | H63: =H61-G61-H62 -> 97788.917 | I63: =I61-H61-I62 -> 134948.7 | J63: =J61-I61-J62 -> 174589.89 | K63: =K61-J61-K62 -> 216840.64 | L63: =L61-K61-L62 -> 261835.07 | ... BA63: =BA61-AZ61-BA62 -> 2452472.3
A65: COHORT GROSS ANNUAL RENT (£)
A66: Cohort — Year 1 | B66: 1 | D66: =IF(D$6<$B66,0,IF(D$6=$B66,'Growth Engine'!D$10*'Macro & Indexation'!D$19*gross_yield,C66*(1+'Macro & Indexation'!D$11))) -> 14000 | E66: =IF(E$6<$B66,0,IF(E$6=$B66,'Growth Engine'!E$10*'Macro & Indexation'!E$19*gross_yield,D66*(1+'Macro & Indexation'!E$11))) -> 14350 | F66: =IF(F$6<$B66,0,IF(F$6=$B66,'Growth Engine'!F$10*'Macro & Indexation'!F$19*gross_yield,E66*(1+'Macro & Indexation'!F$11))) -> 14708.75 | G66: =IF(G$6<$B66,0,IF(G$6=$B66,'Growth Engine'!G$10*'Macro & Indexation'!G$19*gross_yield,F66*(1+'Macro & Indexation'!G$11))) -> 15076.469 | H66: =IF(H$6<$B66,0,IF(H$6=$B66,'Growth Engine'!H$10*'Macro & Indexation'!H$19*gross_yield,G66*(1+'Macro & Indexation'!H$11))) -> 15453.38 | I66: =IF(I$6<$B66,0,IF(I$6=$B66,'Growth Engine'!I$10*'Macro & Indexation'!I$19*gross_yield,H66*(1+'Macro & Indexation'!I$11))) -> 15839.715 | J66: =IF(J$6<$B66,0,IF(J$6=$B66,'Growth Engine'!J$10*'Macro & Indexation'!J$19*gross_yield,I66*(1+'Macro & Indexation'!J$11))) -> 16235.708 | K66: =IF(K$6<$B66,0,IF(K$6=$B66,'Growth Engine'!K$10*'Macro & Indexation'!K$19*gross_yield,J66*(1+'Macro & Indexation'!K$11))) -> 16641.601 | ... BA66: =IF(BA$6<$B66,0,IF(BA$6=$B66,'Growth Engine'!BA$10*'Macro & Indexation'!BA$19*gross_yield,AZ66*(1+'Macro & Indexation'!BA$11))) -> 46945.875
A67: Cohort — Year 2 | B67: 2 | D67: =IF(D$6<$B67,0,IF(D$6=$B67,'Growth Engine'!D$10*'Macro & Indexation'!D$19*gross_yield,C67*(1+'Macro & Indexation'!D$11))) -> 0 | E67: =IF(E$6<$B67,0,IF(E$6=$B67,'Growth Engine'!E$10*'Macro & Indexation'!E$19*gross_yield,D67*(1+'Macro & Indexation'!E$11))) -> 28980 | F67: =IF(F$6<$B67,0,IF(F$6=$B67,'Growth Engine'!F$10*'Macro & Indexation'!F$19*gross_yield,E67*(1+'Macro & Indexation'!F$11))) -> 29704.5 | G67: =IF(G$6<$B67,0,IF(G$6=$B67,'Growth Engine'!G$10*'Macro & Indexation'!G$19*gross_yield,F67*(1+'Macro & Indexation'!G$11))) -> 30447.112 | H67: =IF(H$6<$B67,0,IF(H$6=$B67,'Growth Engine'!H$10*'Macro & Indexation'!H$19*gross_yield,G67*(1+'Macro & Indexation'!H$11))) -> 31208.29 | I67: =IF(I$6<$B67,0,IF(I$6=$B67,'Growth Engine'!I$10*'Macro & Indexation'!I$19*gross_yield,H67*(1+'Macro & Indexation'!I$11))) -> 31988.498 | J67: =IF(J$6<$B67,0,IF(J$6=$B67,'Growth Engine'!J$10*'Macro & Indexation'!J$19*gross_yield,I67*(1+'Macro & Indexation'!J$11))) -> 32788.21 | K67: =IF(K$6<$B67,0,IF(K$6=$B67,'Growth Engine'!K$10*'Macro & Indexation'!K$19*gross_yield,J67*(1+'Macro & Indexation'!K$11))) -> 33607.915 | ... BA67: =IF(BA$6<$B67,0,IF(BA$6=$B67,'Growth Engine'!BA$10*'Macro & Indexation'!BA$19*gross_yield,AZ67*(1+'Macro & Indexation'!BA$11))) -> 94807.767
A68: Cohort — Year 3 | B68: 3 | D68: =IF(D$6<$B68,0,IF(D$6=$B68,'Growth Engine'!D$10*'Macro & Indexation'!D$19*gross_yield,C68*(1+'Macro & Indexation'!D$11))) -> 0 | E68: =IF(E$6<$B68,0,IF(E$6=$B68,'Growth Engine'!E$10*'Macro & Indexation'!E$19*gross_yield,D68*(1+'Macro & Indexation'!E$11))) -> 0 | F68: =IF(F$6<$B68,0,IF(F$6=$B68,'Growth Engine'!F$10*'Macro & Indexation'!F$19*gross_yield,E68*(1+'Macro & Indexation'!F$11))) -> 44991.45 | G68: =IF(G$6<$B68,0,IF(G$6=$B68,'Growth Engine'!G$10*'Macro & Indexation'!G$19*gross_yield,F68*(1+'Macro & Indexation'!G$11))) -> 46116.236 | H68: =IF(H$6<$B68,0,IF(H$6=$B68,'Growth Engine'!H$10*'Macro & Indexation'!H$19*gross_yield,G68*(1+'Macro & Indexation'!H$11))) -> 47269.142 | I68: =IF(I$6<$B68,0,IF(I$6=$B68,'Growth Engine'!I$10*'Macro & Indexation'!I$19*gross_yield,H68*(1+'Macro & Indexation'!I$11))) -> 48450.871 | J68: =IF(J$6<$B68,0,IF(J$6=$B68,'Growth Engine'!J$10*'Macro & Indexation'!J$19*gross_yield,I68*(1+'Macro & Indexation'!J$11))) -> 49662.142 | K68: =IF(K$6<$B68,0,IF(K$6=$B68,'Growth Engine'!K$10*'Macro & Indexation'!K$19*gross_yield,J68*(1+'Macro & Indexation'!K$11))) -> 50903.696 | ... BA68: =IF(BA$6<$B68,0,IF(BA$6=$B68,'Growth Engine'!BA$10*'Macro & Indexation'!BA$19*gross_yield,AZ68*(1+'Macro & Indexation'!BA$11))) -> 143599.08
A69: Cohort — Year 4 | B69: 4 | D69: =IF(D$6<$B69,0,IF(D$6=$B69,'Growth Engine'!D$10*'Macro & Indexation'!D$19*gross_yield,C69*(1+'Macro & Indexation'!D$11))) -> 0 | E69: =IF(E$6<$B69,0,IF(E$6=$B69,'Growth Engine'!E$10*'Macro & Indexation'!E$19*gross_yield,D69*(1+'Macro & Indexation'!E$11))) -> 0 | F69: =IF(F$6<$B69,0,IF(F$6=$B69,'Growth Engine'!F$10*'Macro & Indexation'!F$19*gross_yield,E69*(1+'Macro & Indexation'!F$11))) -> 0 | G69: =IF(G$6<$B69,0,IF(G$6=$B69,'Growth Engine'!G$10*'Macro & Indexation'!G$19*gross_yield,F69*(1+'Macro & Indexation'!G$11))) -> 46566.151 | H69: =IF(H$6<$B69,0,IF(H$6=$B69,'Growth Engine'!H$10*'Macro & Indexation'!H$19*gross_yield,G69*(1+'Macro & Indexation'!H$11))) -> 47730.305 | I69: =IF(I$6<$B69,0,IF(I$6=$B69,'Growth Engine'!I$10*'Macro & Indexation'!I$19*gross_yield,H69*(1+'Macro & Indexation'!I$11))) -> 48923.562 | J69: =IF(J$6<$B69,0,IF(J$6=$B69,'Growth Engine'!J$10*'Macro & Indexation'!J$19*gross_yield,I69*(1+'Macro & Indexation'!J$11))) -> 50146.651 | K69: =IF(K$6<$B69,0,IF(K$6=$B69,'Growth Engine'!K$10*'Macro & Indexation'!K$19*gross_yield,J69*(1+'Macro & Indexation'!K$11))) -> 51400.317 | ... BA69: =IF(BA$6<$B69,0,IF(BA$6=$B69,'Growth Engine'!BA$10*'Macro & Indexation'!BA$19*gross_yield,AZ69*(1+'Macro & Indexation'!BA$11))) -> 145000.05
A70: Cohort — Year 5 | B70: 5 | D70: =IF(D$6<$B70,0,IF(D$6=$B70,'Growth Engine'!D$10*'Macro & Indexation'!D$19*gross_yield,C70*(1+'Macro & Indexation'!D$11))) -> 0 | E70: =IF(E$6<$B70,0,IF(E$6=$B70,'Growth Engine'!E$10*'Macro & Indexation'!E$19*gross_yield,D70*(1+'Macro & Indexation'!E$11))) -> 0 | F70: =IF(F$6<$B70,0,IF(F$6=$B70,'Growth Engine'!F$10*'Macro & Indexation'!F$19*gross_yield,E70*(1+'Macro & Indexation'!F$11))) -> 0 | G70: =IF(G$6<$B70,0,IF(G$6=$B70,'Growth Engine'!G$10*'Macro & Indexation'!G$19*gross_yield,F70*(1+'Macro & Indexation'!G$11))) -> 0 | H70: =IF(H$6<$B70,0,IF(H$6=$B70,'Growth Engine'!H$10*'Macro & Indexation'!H$19*gross_yield,G70*(1+'Macro & Indexation'!H$11))) -> 48195.966 | I70: =IF(I$6<$B70,0,IF(I$6=$B70,'Growth Engine'!I$10*'Macro & Indexation'!I$19*gross_yield,H70*(1+'Macro & Indexation'!I$11))) -> 49400.865 | J70: =IF(J$6<$B70,0,IF(J$6=$B70,'Growth Engine'!J$10*'Macro & Indexation'!J$19*gross_yield,I70*(1+'Macro & Indexation'!J$11))) -> 50635.887 | K70: =IF(K$6<$B70,0,IF(K$6=$B70,'Growth Engine'!K$10*'Macro & Indexation'!K$19*gross_yield,J70*(1+'Macro & Indexation'!K$11))) -> 51901.784 | ... BA70: =IF(BA$6<$B70,0,IF(BA$6=$B70,'Growth Engine'!BA$10*'Macro & Indexation'!BA$19*gross_yield,AZ70*(1+'Macro & Indexation'!BA$11))) -> 146414.68
A71: Cohort — Year 6 | B71: 6 | D71: =IF(D$6<$B71,0,IF(D$6=$B71,'Growth Engine'!D$10*'Macro & Indexation'!D$19*gross_yield,C71*(1+'Macro & Indexation'!D$11))) -> 0 | E71: =IF(E$6<$B71,0,IF(E$6=$B71,'Growth Engine'!E$10*'Macro & Indexation'!E$19*gross_yield,D71*(1+'Macro & Indexation'!E$11))) -> 0 | F71: =IF(F$6<$B71,0,IF(F$6=$B71,'Growth Engine'!F$10*'Macro & Indexation'!F$19*gross_yield,E71*(1+'Macro & Indexation'!F$11))) -> 0 | G71: =IF(G$6<$B71,0,IF(G$6=$B71,'Growth Engine'!G$10*'Macro & Indexation'!G$19*gross_yield,F71*(1+'Macro & Indexation'!G$11))) -> 0 | H71: =IF(H$6<$B71,0,IF(H$6=$B71,'Growth Engine'!H$10*'Macro & Indexation'!H$19*gross_yield,G71*(1+'Macro & Indexation'!H$11))) -> 0 | I71: =IF(I$6<$B71,0,IF(I$6=$B71,'Growth Engine'!I$10*'Macro & Indexation'!I$19*gross_yield,H71*(1+'Macro & Indexation'!I$11))) -> 49882.825 | J71: =IF(J$6<$B71,0,IF(J$6=$B71,'Growth Engine'!J$10*'Macro & Indexation'!J$19*gross_yield,I71*(1+'Macro & Indexation'!J$11))) -> 51129.895 | K71: =IF(K$6<$B71,0,IF(K$6=$B71,'Growth Engine'!K$10*'Macro & Indexation'!K$19*gross_yield,J71*(1+'Macro & Indexation'!K$11))) -> 52408.143 | ... BA71: =IF(BA$6<$B71,0,IF(BA$6=$B71,'Growth Engine'!BA$10*'Macro & Indexation'!BA$19*gross_yield,AZ71*(1+'Macro & Indexation'!BA$11))) -> 147843.12
A72: Cohort — Year 7 | B72: 7 | D72: =IF(D$6<$B72,0,IF(D$6=$B72,'Growth Engine'!D$10*'Macro & Indexation'!D$19*gross_yield,C72*(1+'Macro & Indexation'!D$11))) -> 0 | E72: =IF(E$6<$B72,0,IF(E$6=$B72,'Growth Engine'!E$10*'Macro & Indexation'!E$19*gross_yield,D72*(1+'Macro & Indexation'!E$11))) -> 0 | F72: =IF(F$6<$B72,0,IF(F$6=$B72,'Growth Engine'!F$10*'Macro & Indexation'!F$19*gross_yield,E72*(1+'Macro & Indexation'!F$11))) -> 0 | G72: =IF(G$6<$B72,0,IF(G$6=$B72,'Growth Engine'!G$10*'Macro & Indexation'!G$19*gross_yield,F72*(1+'Macro & Indexation'!G$11))) -> 0 | H72: =IF(H$6<$B72,0,IF(H$6=$B72,'Growth Engine'!H$10*'Macro & Indexation'!H$19*gross_yield,G72*(1+'Macro & Indexation'!H$11))) -> 0 | I72: =IF(I$6<$B72,0,IF(I$6=$B72,'Growth Engine'!I$10*'Macro & Indexation'!I$19*gross_yield,H72*(1+'Macro & Indexation'!I$11))) -> 0 | J72: =IF(J$6<$B72,0,IF(J$6=$B72,'Growth Engine'!J$10*'Macro & Indexation'!J$19*gross_yield,I72*(1+'Macro & Indexation'!J$11))) -> 51628.724 | K72: =IF(K$6<$B72,0,IF(K$6=$B72,'Growth Engine'!K$10*'Macro & Indexation'!K$19*gross_yield,J72*(1+'Macro & Indexation'!K$11))) -> 52919.442 | ... BA72: =IF(BA$6<$B72,0,IF(BA$6=$B72,'Growth Engine'!BA$10*'Macro & Indexation'!BA$19*gross_yield,AZ72*(1+'Macro & Indexation'!BA$11))) -> 149285.49
A73: Cohort — Year 8 | B73: 8 | D73: =IF(D$6<$B73,0,IF(D$6=$B73,'Growth Engine'!D$10*'Macro & Indexation'!D$19*gross_yield,C73*(1+'Macro & Indexation'!D$11))) -> 0 | E73: =IF(E$6<$B73,0,IF(E$6=$B73,'Growth Engine'!E$10*'Macro & Indexation'!E$19*gross_yield,D73*(1+'Macro & Indexation'!E$11))) -> 0 | F73: =IF(F$6<$B73,0,IF(F$6=$B73,'Growth Engine'!F$10*'Macro & Indexation'!F$19*gross_yield,E73*(1+'Macro & Indexation'!F$11))) -> 0 | G73: =IF(G$6<$B73,0,IF(G$6=$B73,'Growth Engine'!G$10*'Macro & Indexation'!G$19*gross_yield,F73*(1+'Macro & Indexation'!G$11))) -> 0 | H73: =IF(H$6<$B73,0,IF(H$6=$B73,'Growth Engine'!H$10*'Macro & Indexation'!H$19*gross_yield,G73*(1+'Macro & Indexation'!H$11))) -> 0 | I73: =IF(I$6<$B73,0,IF(I$6=$B73,'Growth Engine'!I$10*'Macro & Indexation'!I$19*gross_yield,H73*(1+'Macro & Indexation'!I$11))) -> 0 | J73: =IF(J$6<$B73,0,IF(J$6=$B73,'Growth Engine'!J$10*'Macro & Indexation'!J$19*gross_yield,I73*(1+'Macro & Indexation'!J$11))) -> 0 | K73: =IF(K$6<$B73,0,IF(K$6=$B73,'Growth Engine'!K$10*'Macro & Indexation'!K$19*gross_yield,J73*(1+'Macro & Indexation'!K$11))) -> 53435.729 | ... BA73: =IF(BA$6<$B73,0,IF(BA$6=$B73,'Growth Engine'!BA$10*'Macro & Indexation'!BA$19*gross_yield,AZ73*(1+'Macro & Indexation'!BA$11))) -> 150741.93
A74: Cohort — Year 9 | B74: 9 | D74: =IF(D$6<$B74,0,IF(D$6=$B74,'Growth Engine'!D$10*'Macro & Indexation'!D$19*gross_yield,C74*(1+'Macro & Indexation'!D$11))) -> 0 | E74: =IF(E$6<$B74,0,IF(E$6=$B74,'Growth Engine'!E$10*'Macro & Indexation'!E$19*gross_yield,D74*(1+'Macro & Indexation'!E$11))) -> 0 | F74: =IF(F$6<$B74,0,IF(F$6=$B74,'Growth Engine'!F$10*'Macro & Indexation'!F$19*gross_yield,E74*(1+'Macro & Indexation'!F$11))) -> 0 | G74: =IF(G$6<$B74,0,IF(G$6=$B74,'Growth Engine'!G$10*'Macro & Indexation'!G$19*gross_yield,F74*(1+'Macro & Indexation'!G$11))) -> 0 | H74: =IF(H$6<$B74,0,IF(H$6=$B74,'Growth Engine'!H$10*'Macro & Indexation'!H$19*gross_yield,G74*(1+'Macro & Indexation'!H$11))) -> 0 | I74: =IF(I$6<$B74,0,IF(I$6=$B74,'Growth Engine'!I$10*'Macro & Indexation'!I$19*gross_yield,H74*(1+'Macro & Indexation'!I$11))) -> 0 | J74: =IF(J$6<$B74,0,IF(J$6=$B74,'Growth Engine'!J$10*'Macro & Indexation'!J$19*gross_yield,I74*(1+'Macro & Indexation'!J$11))) -> 0 | K74: =IF(K$6<$B74,0,IF(K$6=$B74,'Growth Engine'!K$10*'Macro & Indexation'!K$19*gross_yield,J74*(1+'Macro & Indexation'!K$11))) -> 0 | ... BA74: =IF(BA$6<$B74,0,IF(BA$6=$B74,'Growth Engine'!BA$10*'Macro & Indexation'!BA$19*gross_yield,AZ74*(1+'Macro & Indexation'!BA$11))) -> 152212.59
A75: Cohort — Year 10 | B75: 10 | D75: =IF(D$6<$B75,0,IF(D$6=$B75,'Growth Engine'!D$10*'Macro & Indexation'!D$19*gross_yield,C75*(1+'Macro & Indexation'!D$11))) -> 0 | E75: =IF(E$6<$B75,0,IF(E$6=$B75,'Growth Engine'!E$10*'Macro & Indexation'!E$19*gross_yield,D75*(1+'Macro & Indexation'!E$11))) -> 0 | F75: =IF(F$6<$B75,0,IF(F$6=$B75,'Growth Engine'!F$10*'Macro & Indexation'!F$19*gross_yield,E75*(1+'Macro & Indexation'!F$11))) -> 0 | G75: =IF(G$6<$B75,0,IF(G$6=$B75,'Growth Engine'!G$10*'Macro & Indexation'!G$19*gross_yield,F75*(1+'Macro & Indexation'!G$11))) -> 0 | H75: =IF(H$6<$B75,0,IF(H$6=$B75,'Growth Engine'!H$10*'Macro & Indexation'!H$19*gross_yield,G75*(1+'Macro & Indexation'!H$11))) -> 0 | I75: =IF(I$6<$B75,0,IF(I$6=$B75,'Growth Engine'!I$10*'Macro & Indexation'!I$19*gross_yield,H75*(1+'Macro & Indexation'!I$11))) -> 0 | J75: =IF(J$6<$B75,0,IF(J$6=$B75,'Growth Engine'!J$10*'Macro & Indexation'!J$19*gross_yield,I75*(1+'Macro & Indexation'!J$11))) -> 0 | K75: =IF(K$6<$B75,0,IF(K$6=$B75,'Growth Engine'!K$10*'Macro & Indexation'!K$19*gross_yield,J75*(1+'Macro & Indexation'!K$11))) -> 0 | ... BA75: =IF(BA$6<$B75,0,IF(BA$6=$B75,'Growth Engine'!BA$10*'Macro & Indexation'!BA$19*gross_yield,AZ75*(1+'Macro & Indexation'!BA$11))) -> 153697.59
A76: Cohort — Year 11 | B76: 11 | D76: =IF(D$6<$B76,0,IF(D$6=$B76,'Growth Engine'!D$10*'Macro & Indexation'!D$19*gross_yield,C76*(1+'Macro & Indexation'!D$11))) -> 0 | E76: =IF(E$6<$B76,0,IF(E$6=$B76,'Growth Engine'!E$10*'Macro & Indexation'!E$19*gross_yield,D76*(1+'Macro & Indexation'!E$11))) -> 0 | F76: =IF(F$6<$B76,0,IF(F$6=$B76,'Growth Engine'!F$10*'Macro & Indexation'!F$19*gross_yield,E76*(1+'Macro & Indexation'!F$11))) -> 0 | G76: =IF(G$6<$B76,0,IF(G$6=$B76,'Growth Engine'!G$10*'Macro & Indexation'!G$19*gross_yield,F76*(1+'Macro & Indexation'!G$11))) -> 0 | H76: =IF(H$6<$B76,0,IF(H$6=$B76,'Growth Engine'!H$10*'Macro & Indexation'!H$19*gross_yield,G76*(1+'Macro & Indexation'!H$11))) -> 0 | I76: =IF(I$6<$B76,0,IF(I$6=$B76,'Growth Engine'!I$10*'Macro & Indexation'!I$19*gross_yield,H76*(1+'Macro & Indexation'!I$11))) -> 0 | J76: =IF(J$6<$B76,0,IF(J$6=$B76,'Growth Engine'!J$10*'Macro & Indexation'!J$19*gross_yield,I76*(1+'Macro & Indexation'!J$11))) -> 0 | K76: =IF(K$6<$B76,0,IF(K$6=$B76,'Growth Engine'!K$10*'Macro & Indexation'!K$19*gross_yield,J76*(1+'Macro & Indexation'!K$11))) -> 0 | ... BA76: =IF(BA$6<$B76,0,IF(BA$6=$B76,'Growth Engine'!BA$10*'Macro & Indexation'!BA$19*gross_yield,AZ76*(1+'Macro & Indexation'!BA$11))) -> 51732.359
A77: Cohort — Year 12 | B77: 12 | D77: =IF(D$6<$B77,0,IF(D$6=$B77,'Growth Engine'!D$10*'Macro & Indexation'!D$19*gross_yield,C77*(1+'Macro & Indexation'!D$11))) -> 0 | E77: =IF(E$6<$B77,0,IF(E$6=$B77,'Growth Engine'!E$10*'Macro & Indexation'!E$19*gross_yield,D77*(1+'Macro & Indexation'!E$11))) -> 0 | F77: =IF(F$6<$B77,0,IF(F$6=$B77,'Growth Engine'!F$10*'Macro & Indexation'!F$19*gross_yield,E77*(1+'Macro & Indexation'!F$11))) -> 0 | G77: =IF(G$6<$B77,0,IF(G$6=$B77,'Growth Engine'!G$10*'Macro & Indexation'!G$19*gross_yield,F77*(1+'Macro & Indexation'!G$11))) -> 0 | H77: =IF(H$6<$B77,0,IF(H$6=$B77,'Growth Engine'!H$10*'Macro & Indexation'!H$19*gross_yield,G77*(1+'Macro & Indexation'!H$11))) -> 0 | I77: =IF(I$6<$B77,0,IF(I$6=$B77,'Growth Engine'!I$10*'Macro & Indexation'!I$19*gross_yield,H77*(1+'Macro & Indexation'!I$11))) -> 0 | J77: =IF(J$6<$B77,0,IF(J$6=$B77,'Growth Engine'!J$10*'Macro & Indexation'!J$19*gross_yield,I77*(1+'Macro & Indexation'!J$11))) -> 0 | K77: =IF(K$6<$B77,0,IF(K$6=$B77,'Growth Engine'!K$10*'Macro & Indexation'!K$19*gross_yield,J77*(1+'Macro & Indexation'!K$11))) -> 0 | ... BA77: =IF(BA$6<$B77,0,IF(BA$6=$B77,'Growth Engine'!BA$10*'Macro & Indexation'!BA$19*gross_yield,AZ77*(1+'Macro & Indexation'!BA$11))) -> 0
... A115: Cohort — Year 50 | B115: 50 | D115: =IF(D$6<$B115,0,IF(D$6=$B115,'Growth Engine'!D$10*'Macro & Indexation'!D$19*gross_yield,C115*(1+'Macro & Indexation'!D$11))) -> 0 | E115: =IF(E$6<$B115,0,IF(E$6=$B115,'Growth Engine'!E$10*'Macro & Indexation'!E$19*gross_yield,D115*(1+'Macro & Indexation'!E$11))) -> 0 | F115: =IF(F$6<$B115,0,IF(F$6=$B115,'Growth Engine'!F$10*'Macro & Indexation'!F$19*gross_yield,E115*(1+'Macro & Indexation'!F$11))) -> 0 | G115: =IF(G$6<$B115,0,IF(G$6=$B115,'Growth Engine'!G$10*'Macro & Indexation'!G$19*gross_yield,F115*(1+'Macro & Indexation'!G$11))) -> 0 | H115: =IF(H$6<$B115,0,IF(H$6=$B115,'Growth Engine'!H$10*'Macro & Indexation'!H$19*gross_yield,G115*(1+'Macro & Indexation'!H$11))) -> 0 | I115: =IF(I$6<$B115,0,IF(I$6=$B115,'Growth Engine'!I$10*'Macro & Indexation'!I$19*gross_yield,H115*(1+'Macro & Indexation'!I$11))) -> 0 | J115: =IF(J$6<$B115,0,IF(J$6=$B115,'Growth Engine'!J$10*'Macro & Indexation'!J$19*gross_yield,I115*(1+'Macro & Indexation'!J$11))) -> 0 | K115: =IF(K$6<$B115,0,IF(K$6=$B115,'Growth Engine'!K$10*'Macro & Indexation'!K$19*gross_yield,J115*(1+'Macro & Indexation'!K$11))) -> 0 | ... BA115: =IF(BA$6<$B115,0,IF(BA$6=$B115,'Growth Engine'!BA$10*'Macro & Indexation'!BA$19*gross_yield,AZ115*(1+'Macro & Indexation'!BA$11))) -> 75544.904
A117: Total gross annual rent | B117: £ | D117: =SUM(D66:D115) -> 14000 | E117: =SUM(E66:E115) -> 43330 | F117: =SUM(F66:F115) -> 89404.7 | G117: =SUM(G66:G115) -> 138205.97 | H117: =SUM(H66:H115) -> 189857.08 | I117: =SUM(I66:I115) -> 244486.34 | J117: =SUM(J66:J115) -> 302227.22 | K117: =SUM(K66:K115) -> 363218.63 | ... BA117: =SUM(BA66:BA115) -> 2822273.8
A119: Land Commons net rental income | B119: gross × share × (1 − void) | D119: =D117*lc_share*(1-void_rate) -> 10640 | E119: =E117*lc_share*(1-void_rate) -> 32930.8 | F119: =F117*lc_share*(1-void_rate) -> 67947.572 | G119: =G117*lc_share*(1-void_rate) -> 105036.54 | H119: =H117*lc_share*(1-void_rate) -> 144291.38 | I119: =I117*lc_share*(1-void_rate) -> 185809.61 | J119: =J117*lc_share*(1-void_rate) -> 229692.69 | K119: =K117*lc_share*(1-void_rate) -> 276046.16 | ... BA119: =BA117*lc_share*(1-void_rate) -> 2144928.1
A121: ACQUISITION COSTS
A122: Purchase price paid | B122: £ | D122: =D62 -> 280000 | E122: =E62 -> 579600 | F122: =F62 -> 899829 | G122: =G62 -> 931323.01 | H122: =H62 -> 963919.32 | I122: =I62 -> 997656.5 | J122: =J62 -> 1032574.5 | K122: =K62 -> 1068714.6 | ... BA122: =BA62 -> 1510898.1
A123: SDLT | B123: £ | D123: =D122*sdlt_rate -> 0 | E123: =E122*sdlt_rate -> 0 | F123: =F122*sdlt_rate -> 0 | G123: =G122*sdlt_rate -> 0 | H123: =H122*sdlt_rate -> 0 | I123: =I122*sdlt_rate -> 0 | J123: =J122*sdlt_rate -> 0 | K123: =K122*sdlt_rate -> 0 | ... BA123: =BA122*sdlt_rate -> 0
A124: Conveyancing | B124: £ | D124: ='Growth Engine'!D10*conveyancing*'Macro & Indexation'!D$20 -> 2500 | E124: ='Growth Engine'!E10*conveyancing*'Macro & Indexation'!E$20 -> 5125 | F124: ='Growth Engine'!F10*conveyancing*'Macro & Indexation'!F$20 -> 7879.6875 | G124: ='Growth Engine'!G10*conveyancing*'Macro & Indexation'!G$20 -> 8076.6797 | H124: ='Growth Engine'!H10*conveyancing*'Macro & Indexation'!H$20 -> 8278.5967 | I124: ='Growth Engine'!I10*conveyancing*'Macro & Indexation'!I$20 -> 8485.5616 | J124: ='Growth Engine'!J10*conveyancing*'Macro & Indexation'!J$20 -> 8697.7006 | K124: ='Growth Engine'!K10*conveyancing*'Macro & Indexation'!K$20 -> 8915.1432 | ... BA124: ='Growth Engine'!BA10*conveyancing*'Macro & Indexation'!BA$20 -> 8383.192
A125: Surveys | B125: £ | D125: ='Growth Engine'!D10*survey_cost*'Macro & Indexation'!D$20 -> 800 | E125: ='Growth Engine'!E10*survey_cost*'Macro & Indexation'!E$20 -> 1640 | F125: ='Growth Engine'!F10*survey_cost*'Macro & Indexation'!F$20 -> 2521.5 | G125: ='Growth Engine'!G10*survey_cost*'Macro & Indexation'!G$20 -> 2584.5375 | H125: ='Growth Engine'!H10*survey_cost*'Macro & Indexation'!H$20 -> 2649.1509 | I125: ='Growth Engine'!I10*survey_cost*'Macro & Indexation'!I$20 -> 2715.3797 | J125: ='Growth Engine'!J10*survey_cost*'Macro & Indexation'!J$20 -> 2783.2642 | K125: ='Growth Engine'!K10*survey_cost*'Macro & Indexation'!K$20 -> 2852.8458 | ... BA125: ='Growth Engine'!BA10*survey_cost*'Macro & Indexation'!BA$20 -> 2682.6214
A126: Initial retrofit | B126: £ | D126: ='Growth Engine'!D10*retrofit_cost*'Macro & Indexation'!D$20 -> 5000 | E126: ='Growth Engine'!E10*retrofit_cost*'Macro & Indexation'!E$20 -> 10250 | F126: ='Growth Engine'!F10*retrofit_cost*'Macro & Indexation'!F$20 -> 15759.375 | G126: ='Growth Engine'!G10*retrofit_cost*'Macro & Indexation'!G$20 -> 16153.359 | H126: ='Growth Engine'!H10*retrofit_cost*'Macro & Indexation'!H$20 -> 16557.193 | I126: ='Growth Engine'!I10*retrofit_cost*'Macro & Indexation'!I$20 -> 16971.123 | J126: ='Growth Engine'!J10*retrofit_cost*'Macro & Indexation'!J$20 -> 17395.401 | K126: ='Growth Engine'!K10*retrofit_cost*'Macro & Indexation'!K$20 -> 17830.286 | ... BA126: ='Growth Engine'!BA10*retrofit_cost*'Macro & Indexation'!BA$20 -> 16766.384
A127: Total transaction costs | B127: £ | D127: =SUM(D123:D126) -> 8300 | E127: =SUM(E123:E126) -> 17015 | F127: =SUM(F123:F126) -> 26160.562 | G127: =SUM(G123:G126) -> 26814.577 | H127: =SUM(H123:H126) -> 27484.941 | I127: =SUM(I123:I126) -> 28172.065 | J127: =SUM(J123:J126) -> 28876.366 | K127: =SUM(K123:K126) -> 29598.275 | ... BA127: =SUM(BA123:BA126) -> 27832.197
A128: Total acquisition cash cost | B128: £ | D128: =D122+D127 -> 288300 | E128: =E122+E127 -> 596615 | F128: =F122+F127 -> 925989.56 | G128: =G122+G127 -> 958137.59 | H128: =H122+H127 -> 991404.26 | I128: =I122+I127 -> 1025828.6 | J128: =J122+J127 -> 1061450.8 | K128: =K122+K127 -> 1098312.9 | ... BA128: =BA122+BA127 -> 1538730.3
A130: CAPEX SINKING FUND
A131: Opening balance | B131: £ | D131: =0 -> 0 | E131: =D135 -> 800 | F131: =E135 -> 3260 | G131: =F135 -> 8303 | H131: =G135 -> 16056.613 | I131: =H135 -> 26653.216 | J131: =I135 -> 40230.115 | K131: =J135 -> 56929.7 | L131: =K135 -> 76899.621 | ... BA131: =AZ135 -> 2459856.6
A132: Contribution | B132: £ | D132: =sinking_per_prop*'Growth Engine'!D11*'Macro & Indexation'!D$20 -> 1500 | E132: =sinking_per_prop*'Growth Engine'!E11*'Macro & Indexation'!E$20 -> 4612.5 | F132: =sinking_per_prop*'Growth Engine'!F11*'Macro & Indexation'!F$20 -> 9455.625 | G132: =sinking_per_prop*'Growth Engine'!G11*'Macro & Indexation'!G$20 -> 14538.023 | H132: =sinking_per_prop*'Growth Engine'!H11*'Macro & Indexation'!H$20 -> 19868.632 | I132: =sinking_per_prop*'Growth Engine'!I11*'Macro & Indexation'!I$20 -> 25456.685 | J132: =sinking_per_prop*'Growth Engine'!J11*'Macro & Indexation'!J$20 -> 31311.722 | K132: =sinking_per_prop*'Growth Engine'!K11*'Macro & Indexation'!K$20 -> 37443.601 | ... BA132: =sinking_per_prop*'Growth Engine'!BA11*'Macro & Indexation'!BA$20 -> 246465.84
A133: Investment return on fund balance | B133: £ | D133: =D131*sinking_return -> 0 | E133: =E131*sinking_return -> 0 | F133: =F131*sinking_return -> 0 | G133: =G131*sinking_return -> 0 | H133: =H131*sinking_return -> 0 | I133: =I131*sinking_return -> 0 | J133: =J131*sinking_return -> 0 | K133: =K131*sinking_return -> 0 | ... BA133: =BA131*sinking_return -> 0
A134: Structural maintenance spend | B134: £ | D134: =-maint_per_prop*'Growth Engine'!D11*'Macro & Indexation'!D$20 -> -700 | E134: =-maint_per_prop*'Growth Engine'!E11*'Macro & Indexation'!E$20 -> -2152.5 | F134: =-maint_per_prop*'Growth Engine'!F11*'Macro & Indexation'!F$20 -> -4412.625 | G134: =-maint_per_prop*'Growth Engine'!G11*'Macro & Indexation'!G$20 -> -6784.4109 | H134: =-maint_per_prop*'Growth Engine'!H11*'Macro & Indexation'!H$20 -> -9272.0283 | I134: =-maint_per_prop*'Growth Engine'!I11*'Macro & Indexation'!I$20 -> -11879.786 | J134: =-maint_per_prop*'Growth Engine'!J11*'Macro & Indexation'!J$20 -> -14612.137 | K134: =-maint_per_prop*'Growth Engine'!K11*'Macro & Indexation'!K$20 -> -17473.681 | ... BA134: =-maint_per_prop*'Growth Engine'!BA11*'Macro & Indexation'!BA$20 -> -115017.39
A135: Closing balance | B135: £ | D135: =SUM(D131:D134) -> 800 | E135: =SUM(E131:E134) -> 3260 | F135: =SUM(F131:F134) -> 8303 | G135: =SUM(G131:G134) -> 16056.613 | H135: =SUM(H131:H134) -> 26653.216 | I135: =SUM(I131:I134) -> 40230.115 | J135: =SUM(J131:J134) -> 56929.7 | K135: =SUM(K131:K134) -> 76899.621 | ... BA135: =SUM(BA131:BA134) -> 2591305.1

Sheet Financial Statements
A1: FINANCIAL STATEMENTS — 50-YEAR PROJECTION
A2: P&L, Balance Sheet and Cash Flow. Row 46 is the balance-sheet integrity check and must read zero in every year.
A6: Model year | D6: 1 | E6: 2 | F6: 3 | G6: 4 | H6: 5 | I6: 6 | J6: 7 | K6: 8 | L6: 9 | M6: 10 | N6: 11 | O6: 12 | P6: 13 | Q6: 14 | R6: 15 | S6: 16 | T6: 17 | U6: 18 | V6: 19 | W6: 20 | X6: 21 | Y6: 22 | Z6: 23 | AA6: 24 | AB6: 25 | AC6: 26 | AD6: 27 | AE6: 28 | AF6: 29 | AG6: 30 | AH6: 31 | AI6: 32 | AJ6: 33 | AK6: 34 | AL6: 35 | AM6: 36 | AN6: 37 | AO6: 38 | AP6: 39 | AQ6: 40 | AR6: 41 | AS6: 42 | AT6: 43 | AU6: 44 | AV6: 45 | AW6: 46 | AX6: 47 | AY6: 48 | AZ6: 49 | BA6: 50
A7: Calendar year | D7: =base_calendar_year+D$6-1 -> 2026 | E7: =base_calendar_year+E$6-1 -> 2027 | F7: =base_calendar_year+F$6-1 -> 2028 | G7: =base_calendar_year+G$6-1 -> 2029 | H7: =base_calendar_year+H$6-1 -> 2030 | I7: =base_calendar_year+I$6-1 -> 2031 | J7: =base_calendar_year+J$6-1 -> 2032 | K7: =base_calendar_year+K$6-1 -> 2033 | ... BA7: =base_calendar_year+BA$6-1 -> 2075
A9: PROFIT & LOSS
A10: Rental income (Land Commons share, net of voids) | B10: £ | D10: ='Asset Register'!D119 -> 10640 | E10: ='Asset Register'!E119 -> 32930.8 | F10: ='Asset Register'!F119 -> 67947.572 | G10: ='Asset Register'!G119 -> 105036.54 | H10: ='Asset Register'!H119 -> 144291.38 | I10: ='Asset Register'!I119 -> 185809.61 | J10: ='Asset Register'!J119 -> 229692.69 | K10: ='Asset Register'!K119 -> 276046.16 | ... BA10: ='Asset Register'!BA119 -> 2144928.1
A11: Bequests, gifts & founding capital | B11: £ | D11: ='Capital & Debt'!D10+'Capital & Debt'!D11+'Capital & Debt'!D12 -> 250000 | E11: ='Capital & Debt'!E10+'Capital & Debt'!E11+'Capital & Debt'!E12 -> 102500 | F11: ='Capital & Debt'!F10+'Capital & Debt'!F11+'Capital & Debt'!F12 -> 105062.5 | G11: ='Capital & Debt'!G10+'Capital & Debt'!G11+'Capital & Debt'!G12 -> 107689.06 | H11: ='Capital & Debt'!H10+'Capital & Debt'!H11+'Capital & Debt'!H12 -> 110381.29 | I11: ='Capital & Debt'!I10+'Capital & Debt'!I11+'Capital & Debt'!I12 -> 113140.82 | J11: ='Capital & Debt'!J10+'Capital & Debt'!J11+'Capital & Debt'!J12 -> 115969.34 | K11: ='Capital & Debt'!K10+'Capital & Debt'!K11+'Capital & Debt'!K12 -> 118868.58 | ... BA11: ='Capital & Debt'!BA10+'Capital & Debt'!BA11+'Capital & Debt'!BA12 -> 335327.68
A12: Gift Aid recovery | B12: £ | D12: ='Capital & Debt'!D13 -> 10000 | E12: ='Capital & Debt'!E13 -> 10250 | F12: ='Capital & Debt'!F13 -> 10506.25 | G12: ='Capital & Debt'!G13 -> 10768.906 | H12: ='Capital & Debt'!H13 -> 11038.129 | I12: ='Capital & Debt'!I13 -> 11314.082 | J12: ='Capital & Debt'!J13 -> 11596.934 | K12: ='Capital & Debt'!K13 -> 11886.858 | ... BA12: ='Capital & Debt'!BA13 -> 33532.768
A13: Total income | B13: £ | D13: =SUM(D10:D12) -> 270640 | E13: =SUM(E10:E12) -> 145680.8 | F13: =SUM(F10:F12) -> 183516.32 | G13: =SUM(G10:G12) -> 223494.5 | H13: =SUM(H10:H12) -> 265710.8 | I13: =SUM(I10:I12) -> 310264.52 | J13: =SUM(J10:J12) -> 357258.96 | K13: =SUM(K10:K12) -> 406801.59 | ... BA13: =SUM(BA10:BA12) -> 2513788.5
A14: Admin costs | B14: £ | D14: =-'Growth Engine'!D20 -> -5650 | E14: =-'Growth Engine'!E20 -> -12761.25 | F14: =-'Growth Engine'!F20 -> -20382.125 | G14: =-'Growth Engine'!G20 -> -28376.068 | H14: =-'Growth Engine'!H20 -> -29582.185 | I14: =-'Growth Engine'!I20 -> -30830.874 | J14: =-'Growth Engine'!J20 -> -32123.508 | K14: =-'Growth Engine'!K20 -> -33461.504 | ... BA14: =-'Growth Engine'!BA20 -> -108478.5
A15: Acquisition transaction costs | B15: £ | D15: =-'Asset Register'!D127 -> -8300 | E15: =-'Asset Register'!E127 -> -17015 | F15: =-'Asset Register'!F127 -> -26160.562 | G15: =-'Asset Register'!G127 -> -26814.577 | H15: =-'Asset Register'!H127 -> -27484.941 | I15: =-'Asset Register'!I127 -> -28172.065 | J15: =-'Asset Register'!J127 -> -28876.366 | K15: =-'Asset Register'!K127 -> -29598.275 | ... BA15: =-'Asset Register'!BA127 -> -27832.197
A16: Structural maintenance | B16: £ | D16: ='Asset Register'!D134 -> -700 | E16: ='Asset Register'!E134 -> -2152.5 | F16: ='Asset Register'!F134 -> -4412.625 | G16: ='Asset Register'!G134 -> -6784.4109 | H16: ='Asset Register'!H134 -> -9272.0283 | I16: ='Asset Register'!I134 -> -11879.786 | J16: ='Asset Register'!J134 -> -14612.137 | K16: ='Asset Register'!K134 -> -17473.681 | ... BA16: ='Asset Register'!BA134 -> -115017.39
A17: Community share issuance costs | B17: £ | D17: ='Capital & Debt'!D25 -> 0 | E17: ='Capital & Debt'!E25 -> -3845.3047 | F17: ='Capital & Debt'!F25 -> -6428.2349 | G17: ='Capital & Debt'!G25 -> -9890.1627 | H17: ='Capital & Debt'!H25 -> -9739.2569 | I17: ='Capital & Debt'!I25 -> -10859.488 | J17: ='Capital & Debt'!J25 -> -11563.817 | K17: ='Capital & Debt'!K25 -> -12551.211 | ... BA17: ='Capital & Debt'!BA25 -> -41915.96
A18: Total operating costs | B18: £ | D18: =SUM(D14:D17) -> -14650 | E18: =SUM(E14:E17) -> -35774.055 | F18: =SUM(F14:F17) -> -57383.547 | G18: =SUM(G14:G17) -> -71865.218 | H18: =SUM(H14:H17) -> -76078.412 | I18: =SUM(I14:I17) -> -81742.213 | J18: =SUM(J14:J17) -> -87175.828 | K18: =SUM(K14:K17) -> -93084.671 | ... BA18: =SUM(BA14:BA17) -> -293244.06
A19: Operating surplus | B19: £ | D19: =D13+D18 -> 255990 | E19: =E13+E18 -> 109906.75 | F19: =F13+F18 -> 126132.77 | G19: =G13+G18 -> 151629.29 | H19: =H13+H18 -> 189632.39 | I19: =I13+I18 -> 228522.31 | J19: =J13+J18 -> 270083.13 | K19: =K13+K18 -> 313716.92 | ... BA19: =BA13+BA18 -> 2220544.5
A20: Interest — Tontine | B20: £ | D20: ='Capital & Debt'!D40 -> -1665.625 | E20: ='Capital & Debt'!E40 -> -16252.163 | F20: ='Capital & Debt'!F40 -> -51325.925 | G20: ='Capital & Debt'!G40 -> -95473.199 | H20: ='Capital & Debt'!H40 -> -141837.17 | I20: ='Capital & Debt'!I40 -> -192143.83 | J20: ='Capital & Debt'!J40 -> -246071.34 | K20: ='Capital & Debt'!K40 -> -302560.45 | ... BA20: ='Capital & Debt'!BA40 -> -257699.73
A21: Interest — commercial mortgage | B21: £ | D21: ='Capital & Debt'!D48 -> 0 | E21: ='Capital & Debt'!E48 -> 0 | F21: ='Capital & Debt'!F48 -> 0 | G21: ='Capital & Debt'!G48 -> 0 | H21: ='Capital & Debt'!H48 -> 0 | I21: ='Capital & Debt'!I48 -> 0 | J21: ='Capital & Debt'!J48 -> 0 | K21: ='Capital & Debt'!K48 -> 0 | ... BA21: ='Capital & Debt'!BA48 -> 0
A22: Indexation uplift on Tontine principal (non-cash) | D22: =-'Capital & Debt'!D31 -> 0 | E22: =-'Capital & Debt'!E31 -> -1332.5 | F22: =-'Capital & Debt'!F31 -> -11635.918 | G22: =-'Capital & Debt'!G31 -> -29133.924 | H22: =-'Capital & Debt'!H31 -> -46516.286 | I22: =-'Capital & Debt'!I31 -> -65790.54 | J22: =-'Capital & Debt'!J31 -> -86279.758 | K22: =-'Capital & Debt'!K31 -> -108420.32 | ... BA22: =-'Capital & Debt'!BA31 -> -100565.75
A23: Surplus before dividends & tax | B23: £ | D23: =D19+D20+D21+D22 -> 254324.38 | E23: =E19+E20+E21+E22 -> 92322.082 | F23: =F19+F20+F21+F22 -> 63170.932 | G23: =G19+G20+G21+G22 -> 27022.163 | H23: =H19+H20+H21+H22 -> 1278.9368 | I23: =I19+I20+I21+I22 -> -29412.061 | J23: =J19+J20+J21+J22 -> -62267.966 | K23: =K19+K20+K21+K22 -> -97263.856 | ... BA23: =BA19+BA20+BA21+BA22 -> 1862279
A24: Community share dividends | B24: £ | D24: =-'Capital & Debt'!D28 -> 0 | E24: =-'Capital & Debt'!E28 -> 0 | F24: =-'Capital & Debt'!F28 -> -2307.1828 | G24: =-'Capital & Debt'!G28 -> -6164.1238 | H24: =-'Capital & Debt'!H28 -> -1278.9368 | I24: =-'Capital & Debt'!I28 -> 0 | J24: =-'Capital & Debt'!J28 -> 0 | K24: =-'Capital & Debt'!K28 -> 0 | ... BA24: =-'Capital & Debt'!BA28 -> -398653.54
A25: Corporation tax | B25: £ | D25: =-IF(ct_exempt_toggle=1,0,MAX(0,D23+D24)*ct_rate) -> 0 | E25: =-IF(ct_exempt_toggle=1,0,MAX(0,E23+E24)*ct_rate) -> 0 | F25: =-IF(ct_exempt_toggle=1,0,MAX(0,F23+F24)*ct_rate) -> 0 | G25: =-IF(ct_exempt_toggle=1,0,MAX(0,G23+G24)*ct_rate) -> 0 | H25: =-IF(ct_exempt_toggle=1,0,MAX(0,H23+H24)*ct_rate) -> 0 | I25: =-IF(ct_exempt_toggle=1,0,MAX(0,I23+I24)*ct_rate) -> 0 | J25: =-IF(ct_exempt_toggle=1,0,MAX(0,J23+J24)*ct_rate) -> 0 | K25: =-IF(ct_exempt_toggle=1,0,MAX(0,K23+K24)*ct_rate) -> 0 | ... BA25: =-IF(ct_exempt_toggle=1,0,MAX(0,BA23+BA24)*ct_rate) -> 0
A26: Retained surplus for the year | B26: £ | D26: =D23+D24+D25 -> 254324.38 | E26: =E23+E24+E25 -> 92322.082 | F26: =F23+F24+F25 -> 60863.749 | G26: =G23+G24+G25 -> 20858.04 | H26: =H23+H24+H25 -> 0 | I26: =I23+I24+I25 -> -29412.061 | J26: =J23+J24+J25 -> -62267.966 | K26: =K23+K24+K25 -> -97263.856 | ... BA26: =BA23+BA24+BA25 -> 1463625.5
A27: Cumulative retained surplus | B27: £ | D27: =D26 -> 254324.38 | E27: =D27+E26 -> 346646.46 | F27: =E27+F26 -> 407510.21 | G27: =F27+G26 -> 428368.25 | H27: =G27+H26 -> 428368.25 | I27: =H27+I26 -> 398956.18 | J27: =I27+J26 -> 336688.22 | K27: =J27+K26 -> 239424.36 | L27: =K27+L26 -> 107599.47 | ... BA27: =AZ27+BA26 -> 9248816.4
A29: BALANCE SHEET
A30: Property portfolio at HPI value | B30: £ | D30: ='Asset Register'!D61 -> 280000 | E30: ='Asset Register'!E61 -> 869400 | F30: ='Asset Register'!F61 -> 1799658 | G30: ='Asset Register'!G61 -> 2793969 | H30: ='Asset Register'!H61 -> 3855677.3 | I30: ='Asset Register'!I61 -> 4988282.5 | J30: ='Asset Register'!J61 -> 6195446.8 | K30: ='Asset Register'!K61 -> 7481002.1 | ... BA30: ='Asset Register'!BA61 -> 74034006
A31: CapEx sinking fund | B31: £ | D31: ='Asset Register'!D135 -> 800 | E31: ='Asset Register'!E135 -> 3260 | F31: ='Asset Register'!F135 -> 8303 | G31: ='Asset Register'!G135 -> 16056.613 | H31: ='Asset Register'!H135 -> 26653.216 | I31: ='Asset Register'!I135 -> 40230.115 | J31: ='Asset Register'!J135 -> 56929.7 | K31: ='Asset Register'!K135 -> 76899.621 | ... BA31: ='Asset Register'!BA135 -> 2591305.1
A32: Free cash / operating reserves | B32: £ | D32: =D65 -> 26824.375 | E32: =E65 -> 26129.262 | F32: =F65 -> 10605.976 | G32: =G65 -> -14514.878 | H32: =H65 -> -23275.537 | I32: =I65 -> -27162.479 | J32: =J65 -> -23343.824 | K32: =K65 -> -62488.728 | ... BA32: =BA65 -> 2677875.3
A33: Total assets | B33: £ | D33: =SUM(D30:D32) -> 307624.38 | E33: =SUM(E30:E32) -> 898789.26 | F33: =SUM(F30:F32) -> 1818567 | G33: =SUM(G30:G32) -> 2795510.8 | H33: =SUM(H30:H32) -> 3859055 | I33: =SUM(I30:I32) -> 5001350.1 | J33: =SUM(J30:J32) -> 6229032.7 | K33: =SUM(K30:K32) -> 7495413 | ... BA33: =SUM(BA30:BA32) -> 79303187
A35: Pension fund loan (Tontine) | B35: £ | D35: ='Capital & Debt'!D43 -> 53300 | E35: ='Capital & Debt'!E43 -> 465436.71 | F35: ='Capital & Debt'!F43 -> 1165357 | G35: ='Capital & Debt'!G43 -> 1860651.5 | H35: ='Capital & Debt'!H43 -> 2631621.6 | I35: ='Capital & Debt'!I43 -> 3451190.3 | J35: ='Capital & Debt'!J43 -> 4336812.8 | K35: ='Capital & Debt'!K43 -> 5236701.4 | ... BA35: ='Capital & Debt'!BA43 -> 3875803.9
A36: Commercial mortgage | B36: £ | D36: ='Capital & Debt'!D50 -> 0 | E36: ='Capital & Debt'!E50 -> 0 | F36: ='Capital & Debt'!F50 -> 0 | G36: ='Capital & Debt'!G50 -> 0 | H36: ='Capital & Debt'!H50 -> 0 | I36: ='Capital & Debt'!I50 -> 0 | J36: ='Capital & Debt'!J50 -> 0 | K36: ='Capital & Debt'!K50 -> 0 | ... BA36: ='Capital & Debt'!BA50 -> 0
A37: Community share capital (junior debt) | B37: £ | D37: ='Capital & Debt'!D26 -> 0 | E37: ='Capital & Debt'!E26 -> 76906.094 | F37: ='Capital & Debt'!F26 -> 205470.79 | G37: ='Capital & Debt'!G26 -> 403274.05 | H37: ='Capital & Debt'!H26 -> 598059.18 | I37: ='Capital & Debt'!I26 -> 815248.94 | J37: ='Capital & Debt'!J26 -> 1044987.2 | K37: ='Capital & Debt'!K26 -> 1291902 | ... BA37: ='Capital & Debt'!BA26 -> 13908919
A38: Total liabilities | B38: £ | D38: =SUM(D35:D37) -> 53300 | E38: =SUM(E35:E37) -> 542342.8 | F38: =SUM(F35:F37) -> 1370827.8 | G38: =SUM(G35:G37) -> 2263925.5 | H38: =SUM(H35:H37) -> 3229680.8 | I38: =SUM(I35:I37) -> 4266439.3 | J38: =SUM(J35:J37) -> 5381800 | K38: =SUM(K35:K37) -> 6528603.4 | ... BA38: =SUM(BA35:BA37) -> 17784723
A40: Cumulative retained surplus | B40: £ | D40: =D27 -> 254324.38 | E40: =E27 -> 346646.46 | F40: =F27 -> 407510.21 | G40: =G27 -> 428368.25 | H40: =H27 -> 428368.25 | I40: =I27 -> 398956.18 | J40: =J27 -> 336688.22 | K40: =K27 -> 239424.36 | ... BA40: =BA27 -> 9248816.4
A41: HPI revaluation reserve | B41: £ | D41: ='Asset Register'!D63 -> 0 | E41: =D41+'Asset Register'!E63 -> 9800 | F41: =E41+'Asset Register'!F63 -> 40229 | G41: =F41+'Asset Register'!G63 -> 103217.03 | H41: =G41+'Asset Register'!H63 -> 201005.95 | I41: =H41+'Asset Register'!I63 -> 335954.65 | J41: =I41+'Asset Register'!J63 -> 510544.54 | K41: =J41+'Asset Register'!K63 -> 727385.18 | L41: =K41+'Asset Register'!L63 -> 989220.25 | ... BA41: =AZ41+'Asset Register'!BA63 -> 41628963
A42: Tontine principal released to reserves | B42: £ | D42: =-'Capital & Debt'!D41 -> 0 | E42: =D42-'Capital & Debt'!E41 -> 0 | F42: =E42-'Capital & Debt'!F41 -> 0 | G42: =F42-'Capital & Debt'!G41 -> 0 | H42: =G42-'Capital & Debt'!H41 -> 0 | I42: =H42-'Capital & Debt'!I41 -> 0 | J42: =I42-'Capital & Debt'!J41 -> 0 | K42: =J42-'Capital & Debt'!K41 -> 0 | L42: =K42-'Capital & Debt'!L41 -> 0 | ... BA42: =AZ42-'Capital & Debt'!BA41 -> 10640685
A43: Total reserves / net assets | B43: £ | D43: =SUM(D40:D42) -> 254324.38 | E43: =SUM(E40:E42) -> 356446.46 | F43: =SUM(F40:F42) -> 447739.21 | G43: =SUM(G40:G42) -> 531585.28 | H43: =SUM(H40:H42) -> 629374.19 | I43: =SUM(I40:I42) -> 734910.84 | J43: =SUM(J40:J42) -> 847232.76 | K43: =SUM(K40:K42) -> 966809.54 | ... BA43: =SUM(BA40:BA42) -> 61518464
A44: Total liabilities & reserves | B44: £ | D44: =D38+D43 -> 307624.38 | E44: =E38+E43 -> 898789.26 | F44: =F38+F43 -> 1818567 | G44: =G38+G43 -> 2795510.8 | H44: =H38+H43 -> 3859055 | I44: =I38+I43 -> 5001350.1 | J44: =J38+J43 -> 6229032.7 | K44: =K38+K43 -> 7495413 | ... BA44: =BA38+BA43 -> 79303187
A46: CHECK: assets − liabilities − reserves | B46: must be 0 | D46: =D33-D44 -> 0 | E46: =E33-E44 -> 0 | F46: =F33-F44 -> 0 | G46: =G33-G44 -> 0 | H46: =H33-H44 -> 0 | I46: =I33-I44 -> 0 | J46: =J33-J44 -> 0 | K46: =K33-K44 -> 0 | ... BA46: =BA33-BA44 -> 0
A48: CASH FLOW
A49: Operating surplus | B49: £ | D49: =D19 -> 255990 | E49: =E19 -> 109906.75 | F49: =F19 -> 126132.77 | G49: =G19 -> 151629.29 | H49: =H19 -> 189632.39 | I49: =I19 -> 228522.31 | J49: =J19 -> 270083.13 | K49: =K19 -> 313716.92 | ... BA49: =BA19 -> 2220544.5
A50: Interest paid | B50: £ | D50: =D20+D21 -> -1665.625 | E50: =E20+E21 -> -16252.163 | F50: =F20+F21 -> -51325.925 | G50: =G20+G21 -> -95473.199 | H50: =H20+H21 -> -141837.17 | I50: =I20+I21 -> -192143.83 | J50: =J20+J21 -> -246071.34 | K50: =K20+K21 -> -302560.45 | ... BA50: =BA20+BA21 -> -257699.73
A51: Dividends paid | B51: £ | D51: =D24 -> 0 | E51: =E24 -> 0 | F51: =F24 -> -2307.1828 | G51: =G24 -> -6164.1238 | H51: =H24 -> -1278.9368 | I51: =I24 -> 0 | J51: =J24 -> 0 | K51: =K24 -> 0 | ... BA51: =BA24 -> -398653.54
A52: Tax paid | B52: £ | D52: =D25 -> 0 | E52: =E25 -> 0 | F52: =F25 -> 0 | G52: =G25 -> 0 | H52: =H25 -> 0 | I52: =I25 -> 0 | J52: =J25 -> 0 | K52: =K25 -> 0 | ... BA52: =BA25 -> 0
A53: Net cash from operations | B53: £ | D53: =SUM(D49:D52) -> 254324.38 | E53: =SUM(E49:E52) -> 93654.582 | F53: =SUM(F49:F52) -> 72499.667 | G53: =SUM(G49:G52) -> 49991.964 | H53: =SUM(H49:H52) -> 46516.286 | I53: =SUM(I49:I52) -> 36378.479 | J53: =SUM(J49:J52) -> 24011.793 | K53: =SUM(K49:K52) -> 11156.464 | ... BA53: =SUM(BA49:BA52) -> 1564191.2
A54: Property purchases (capitalised) | B54: £ | D54: =-'Asset Register'!D122 -> -280000 | E54: =-'Asset Register'!E122 -> -579600 | F54: =-'Asset Register'!F122 -> -899829 | G54: =-'Asset Register'!G122 -> -931323.01 | H54: =-'Asset Register'!H122 -> -963919.32 | I54: =-'Asset Register'!I122 -> -997656.5 | J54: =-'Asset Register'!J122 -> -1032574.5 | K54: =-'Asset Register'!K122 -> -1068714.6 | ... BA54: =-'Asset Register'!BA122 -> -1510898.1
A55: Net cash from investing | B55: £ | D55: =D54 -> -280000 | E55: =E54 -> -579600 | F55: =F54 -> -899829 | G55: =G54 -> -931323.01 | H55: =H54 -> -963919.32 | I55: =I54 -> -997656.5 | J55: =J54 -> -1032574.5 | K55: =K54 -> -1068714.6 | ... BA55: =BA54 -> -1510898.1
A56: Tontine drawdown | B56: £ | D56: ='Capital & Debt'!D37 -> 53300 | E56: ='Capital & Debt'!E37 -> 410804.21 | F56: ='Capital & Debt'!F37 -> 688284.35 | G56: ='Capital & Debt'!G37 -> 666160.56 | H56: ='Capital & Debt'!H37 -> 724453.84 | I56: ='Capital & Debt'!I37 -> 753778.21 | J56: ='Capital & Debt'!J37 -> 799342.69 | K56: ='Capital & Debt'!K37 -> 791468.33 | ... BA56: ='Capital & Debt'!BA37 -> 0
A57: Community shares issued | B57: £ | D57: ='Capital & Debt'!D22 -> 0 | E57: ='Capital & Debt'!E22 -> 76906.094 | F57: ='Capital & Debt'!F22 -> 128564.7 | G57: ='Capital & Debt'!G22 -> 197803.25 | H57: ='Capital & Debt'!H22 -> 194785.14 | I57: ='Capital & Debt'!I22 -> 217189.76 | J57: ='Capital & Debt'!J22 -> 231276.35 | K57: ='Capital & Debt'!K22 -> 251024.22 | ... BA57: ='Capital & Debt'!BA22 -> 838319.2
A58: Community shares withdrawn | B58: £ | D58: ='Capital & Debt'!D24 -> 0 | E58: ='Capital & Debt'!E24 -> 0 | F58: ='Capital & Debt'!F24 -> 0 | G58: ='Capital & Debt'!G24 -> 0 | H58: ='Capital & Debt'!H24 -> 0 | I58: ='Capital & Debt'!I24 -> 0 | J58: ='Capital & Debt'!J24 -> -1538.1219 | K58: ='Capital & Debt'!K24 -> -4109.4158 | ... BA58: ='Capital & Debt'!BA24 -> -217851.61
A59: Commercial mortgage principal repaid | B59: £ | D59: ='Capital & Debt'!D49 -> 0 | E59: ='Capital & Debt'!E49 -> 0 | F59: ='Capital & Debt'!F49 -> 0 | G59: ='Capital & Debt'!G49 -> 0 | H59: ='Capital & Debt'!H49 -> 0 | I59: ='Capital & Debt'!I49 -> 0 | J59: ='Capital & Debt'!J49 -> 0 | K59: ='Capital & Debt'!K49 -> 0 | ... BA59: ='Capital & Debt'!BA49 -> 0
A60: Net cash from financing | B60: £ | D60: =SUM(D56:D59) -> 53300 | E60: =SUM(E56:E59) -> 487710.3 | F60: =SUM(F56:F59) -> 816849.05 | G60: =SUM(G56:G59) -> 863963.81 | H60: =SUM(H56:H59) -> 919238.98 | I60: =SUM(I56:I59) -> 970967.97 | J60: =SUM(J56:J59) -> 1029080.9 | K60: =SUM(K56:K59) -> 1038383.1 | ... BA60: =SUM(BA56:BA59) -> 620467.59
A61: Net change in cash | B61: £ | D61: =D53+D55+D60 -> 27624.375 | E61: =E53+E55+E60 -> 1764.8872 | F61: =F53+F55+F60 -> -10480.286 | G61: =G53+G55+G60 -> -17367.242 | H61: =H53+H55+H60 -> 1835.9444 | I61: =I53+I55+I60 -> 9689.957 | J61: =J53+J55+J60 -> 20518.24 | K61: =K53+K55+K60 -> -19174.983 | ... BA61: =BA53+BA55+BA60 -> 673760.72
A62: Cash — opening | B62: £ | D62: =0 -> 0 | E62: =D63 -> 27624.375 | F62: =E63 -> 29389.262 | G62: =F63 -> 18908.976 | H62: =G63 -> 1541.7345 | I62: =H63 -> 3377.6788 | J62: =I63 -> 13067.636 | K62: =J63 -> 33585.876 | L62: =K63 -> 14410.893 | ... BA62: =AZ63 -> 4595419.7
A63: Cash — closing (total) | B63: £ | D63: =D62+D61 -> 27624.375 | E63: =E62+E61 -> 29389.262 | F63: =F62+F61 -> 18908.976 | G63: =G62+G61 -> 1541.7345 | H63: =H62+H61 -> 3377.6788 | I63: =I62+I61 -> 13067.636 | J63: =J62+J61 -> 33585.876 | K63: =K62+K61 -> 14410.893 | ... BA63: =BA62+BA61 -> 5269180.4
A64: Less: CapEx sinking fund (earmarked) | B64: £ | D64: =-'Asset Register'!D135 -> -800 | E64: =-'Asset Register'!E135 -> -3260 | F64: =-'Asset Register'!F135 -> -8303 | G64: =-'Asset Register'!G135 -> -16056.613 | H64: =-'Asset Register'!H135 -> -26653.216 | I64: =-'Asset Register'!I135 -> -40230.115 | J64: =-'Asset Register'!J135 -> -56929.7 | K64: =-'Asset Register'!K135 -> -76899.621 | ... BA64: =-'Asset Register'!BA135 -> -2591305.1
A65: Free cash / operating reserves | B65: £ | D65: =D63+D64 -> 26824.375 | E65: =E63+E64 -> 26129.262 | F65: =F63+F64 -> 10605.976 | G65: =G63+G64 -> -14514.878 | H65: =H63+H64 -> -23275.537 | I65: =I63+I64 -> -27162.479 | J65: =J63+J64 -> -23343.824 | K65: =K63+K64 -> -62488.728 | ... BA65: =BA63+BA64 -> 2677875.3
A67: MEMORANDUM — CAPITAL MOVEMENTS AND CASH BUFFER (not P&L items)
A68: Community share capital raised in year | B68: £ | D68: ='Capital & Debt'!D22 -> 0 | E68: ='Capital & Debt'!E22 -> 76906.094 | F68: ='Capital & Debt'!F22 -> 128564.7 | G68: ='Capital & Debt'!G22 -> 197803.25 | H68: ='Capital & Debt'!H22 -> 194785.14 | I68: ='Capital & Debt'!I22 -> 217189.76 | J68: ='Capital & Debt'!J22 -> 231276.35 | K68: ='Capital & Debt'!K22 -> 251024.22 | ... BA68: ='Capital & Debt'!BA22 -> 838319.2
A69: Tontine capital drawn in year | B69: £ | D69: ='Capital & Debt'!D37 -> 53300 | E69: ='Capital & Debt'!E37 -> 410804.21 | F69: ='Capital & Debt'!F37 -> 688284.35 | G69: ='Capital & Debt'!G37 -> 666160.56 | H69: ='Capital & Debt'!H37 -> 724453.84 | I69: ='Capital & Debt'!I37 -> 753778.21 | J69: ='Capital & Debt'!J37 -> 799342.69 | K69: ='Capital & Debt'!K37 -> 791468.33 | ... BA69: ='Capital & Debt'!BA37 -> 0
A70: Total capital raised in year | B70: £ | D70: =D68+D69 -> 53300 | E70: =E68+E69 -> 487710.3 | F70: =F68+F69 -> 816849.05 | G70: =G68+G69 -> 863963.81 | H70: =H68+H69 -> 919238.98 | I70: =I68+I69 -> 970967.97 | J70: =J68+J69 -> 1030619 | K70: =K68+K69 -> 1042492.5 | ... BA70: =BA68+BA69 -> 838319.2
A71: Cash buffer shortfall — capital call required | B71: £ | D71: =MAX(0,min_cash_buffer-D65) -> 0 | E71: =MAX(0,min_cash_buffer-E65) -> 0 | F71: =MAX(0,min_cash_buffer-F65) -> 14394.024 | G71: =MAX(0,min_cash_buffer-G65) -> 39514.878 | H71: =MAX(0,min_cash_buffer-H65) -> 48275.537 | I71: =MAX(0,min_cash_buffer-I65) -> 52162.479 | J71: =MAX(0,min_cash_buffer-J65) -> 48343.824 | K71: =MAX(0,min_cash_buffer-K65) -> 87488.728 | ... BA71: =MAX(0,min_cash_buffer-BA65) -> 0

Sheet Dashboard
A1: STROUD LAND COMMONS — SCENARIO DASHBOARD
A2: Version 2.1 — closed-end Tontine annuity mechanics and independent-review remediation. Last updated 26 July 2026.
A3: Scenario | C3: Base
A4: Review year (1 – 50) | C4: 20 | D4: ← type any year from 1 to 50
A5: Calendar year | C5: =base_calendar_year+$C$4-1 -> 2045
A6: ="VIABILITY WARNING — minimum DSCR of "&TEXT(MIN('Capital & Debt'!$D$64:$BA$64),"0.00")&"x falls below the "&TEXT($E$30,"0.00")&"x covenant minimum in "&COUNTIF('Capital & Debt'!$D$64:$BA$64,"<"&$E$30)&" of the 50 years. A DSCR under 1.00x means the rental surplus does not cover debt service at all. In covenant breach a lender may block further drawdowns, require additional security, or accelerate repayment." -> VIABILITY WARNING — minimum DSCR of 0.97x falls below the 1.20x covenant minimum in 21 of the 50 years. A DSCR under 1.00x means the rental surplus does not cover debt service at all. In covenant breach a lender may block further drawdowns, require additional security, or accelerate repayment.
A7: ="Primary levers on DSCR, in order of effect: gross rental yield (now "&TEXT(gross_yield,"0.0%")&"), Land Commons share of gross rent ("&TEXT(lc_share,"0.0%")&"), the implied SLC coupon ("&TEXT(pf_coupon_spread,"0.00%")&" over index, driven by the target investor annuity rate), void rate ("&TEXT(void_rate,"0.0%")&") and the LTV limit ("&TEXT(pf_ltv_limit,"0.0%")&"). Free cash additionally carries the CapEx sinking fund at "&TEXT(sinking_per_prop,"£#,##0")&" per property per year." -> Primary levers on DSCR, in order of effect: gross rental yield (now 5.0%), Land Commons share of gross rent (80.0%), the implied SLC coupon (3.75% over index, driven by the target investor annuity rate), void rate (5.0%) and the LTV limit (70.0%). Free cash additionally carries the CapEx sinking fund at £1,500 per property per year.
A9: KEY METRICS — REVIEW YEAR
A10: Properties in portfolio | C10: {=INDEX('Growth Engine'!$D$11:$BA$11,$C$4)} -> 28
A11: Portfolio value (HPI-indexed) | C11: {=INDEX('Asset Register'!$D$61:$BA$61,$C$4)} -> 15072410
A12: Net rental income to Land Commons | C12: {=INDEX('Financial Statements'!$D$10:$BA$10,$C$4)} -> 500834.02
A13: Total income | C13: {=INDEX('Financial Statements'!$D$13:$BA$13,$C$4)} -> 676685.54
A14: Operating surplus | C14: {=INDEX('Financial Statements'!$D$19:$BA$19,$C$4)} -> 589983.9
A15: Retained surplus for the year | C15: {=INDEX('Financial Statements'!$D$26:$BA$26,$C$4)} -> -212234.56
A16: Tontine loan outstanding | C16: {=INDEX('Capital & Debt'!$D$43:$BA$43,$C$4)} -> 9232549.3
A17: Commercial mortgage outstanding | C17: {=INDEX('Capital & Debt'!$D$50:$BA$50,$C$4)} -> 0
A18: Community share capital | C18: {=INDEX('Capital & Debt'!$D$26:$BA$26,$C$4)} -> 3051562.3
A19: Cumulative bequests & gifts | C19: {=INDEX('Capital & Debt'!$D$15:$BA$15,$C$4)} -> 2959912.3
A20: Total debt service | C20: {=INDEX('Capital & Debt'!$D$55:$BA$55,$C$4)} -> 577034.33
A21: Free cash / operating reserves | C21: {=INDEX('Financial Statements'!$D$65:$BA$65,$C$4)} -> 457451.54
A22: CapEx sinking fund | C22: {=INDEX('Financial Statements'!$D$31:$BA$31,$C$4)} -> 448512.98
A23: Net assets | C23: {=INDEX('Financial Statements'!$D$43:$BA$43,$C$4)} -> 3694263.2
A24: Cumulative Tontine capital raised | C24: {=INDEX('Capital & Debt'!$D$38:$BA$38,$C$4)} -> 6577569.3
A25: Cumulative Tontine principal released to reserves | C25: {=INDEX('Financial Statements'!$D$42:$BA$42,$C$4)} -> 0
A27: HEALTH CHECK — REVIEW YEAR
A29: Indicator | C29: Value | D29: Target | E29: Limit / Min | F29: Status
A30: Debt service coverage ratio (DSCR) | C30: {=IF(INDEX('Capital & Debt'!$D$55:$BA$55,$C$4)<=0,"n/a",INDEX('Capital & Debt'!$D$64:$BA$64,$C$4))} -> 1.0224416 | D30: =1.5 -> 1.5 | E30: =1.2 -> 1.2 | F30: =IF(C30="n/a","n/a",IF(C30>=D30,"GREEN",IF(C30>=E30,"AMBER","RED"))) -> RED
A31: Loan-to-value (LTV) | C31: {=INDEX('Capital & Debt'!$D$57:$BA$57,$C$4)} -> 0.61254631 | D31: =pf_ltv_limit-0.1 -> 0.6 | E31: =pf_ltv_limit -> 0.7 | F31: =IF(C31="n/a","n/a",IF(C31<=D31,"GREEN",IF(C31<=E31,"AMBER","RED"))) -> AMBER
A32: Reserve cover (months of debt service) | C32: {=IF(INDEX('Capital & Debt'!$D$55:$BA$55,$C$4)<=0,"n/a",INDEX('Capital & Debt'!$D$65:$BA$65,$C$4))} -> 9.5131574 | D32: =reserve_tgt_months -> 6 | E32: =reserve_min_months -> 3 | F32: =IF(C32="n/a","n/a",IF(C32>=D32,"GREEN",IF(C32>=E32,"AMBER","RED"))) -> GREEN
A33: Community shares as % of total capital | C33: {=INDEX('Capital & Debt'!$D$59:$BA$59,$C$4)} -> 0.19098077 | D33: =cs_max_pct_capital-0.02 -> 0.18 | E33: =cs_max_pct_capital -> 0.2 | F33: =IF(C33="n/a","n/a",IF(C33<=D33,"GREEN",IF(C33<=E33,"AMBER","RED"))) -> AMBER
A34: Unfunded acquisition requirement | C34: {=INDEX('Capital & Debt'!$D$62:$BA$62,$C$4)} -> 0 | D34: =0 -> 0 | E34: =1 -> 1 | F34: =IF(C34="n/a","n/a",IF(C34<=D34,"GREEN",IF(C34<=E34,"AMBER","RED"))) -> GREEN
A35: Cash buffer shortfall (capital call required) | C35: {=INDEX('Financial Statements'!$D$71:$BA$71,$C$4)} -> 0 | D35: =0 -> 0 | E35: =1 -> 1 | F35: =IF(C35<=D35,"GREEN",IF(C35<=E35,"AMBER","RED")) -> GREEN
A36: Balance sheet check (must be nil) | C36: {=ROUND(INDEX('Financial Statements'!$D$46:$BA$46,$C$4),0)} -> 0 | D36: =0 -> 0 | E36: =1 -> 1 | F36: =IF(C36="n/a","n/a",IF(C36<=D36,"GREEN",IF(C36<=E36,"AMBER","RED"))) -> GREEN
A38: WORST CASE ACROSS THE FULL 50-YEAR HORIZON
A39: Minimum DSCR (years with debt service) | C39: =MIN('Capital & Debt'!$D$64:$BA$64) -> 0.96509183
A40: Maximum LTV | C40: =MAX('Capital & Debt'!$D$57:$BA$57) -> 0.7
A41: Minimum reserve cover | C41: =MIN('Capital & Debt'!$D$65:$BA$65) -> -8.2439617
A42: Minimum free cash / reserves | C42: =MIN('Financial Statements'!$D$65:$BA$65) -> -317425.33
A43: Years with an unfunded acquisition requirement | C43: =COUNTIF('Capital & Debt'!$D$62:$BA$62,">1") -> 30
A44: Largest balance sheet discrepancy | C44: {=SUMPRODUCT(MAX(ABS('Financial Statements'!$D$46:$BA$46)))} -> 0
A45: Cumulative retained surplus, Year 50 | C45: ='Financial Statements'!$BA$27 -> 9248816.4
A46: Net assets, Year 50 | C46: ='Financial Statements'!$BA$43 -> 61518464
A47: Years requiring a capital call (cash below buffer) | C47: =COUNTIF('Financial Statements'!$D$71:$BA$71,">1") -> 13
A49: HOW THE MODEL WORKS
A50: 1. Control & Parameters holds every assumption. Column C is the live value selected by the scenario dropdown above; columns E–G hold the Base, Optimistic and Stress inputs. All other sheets read column C through named ranges — nothing is hardcoded downstream.
A51: 2. Macro & Indexation builds independent CPI, rent-inflation and HPI index series. Row 15 is a free time-series override for HPI: type a rate into any year to model a crash or boom for that year alone.
A52: 4. Asset Register tracks every annual acquisition cohort separately (rows 10–59 for value, 66–115 for gross rent), so each vintage carries its own purchase price, HPI revaluation and rent-inflation path. The CapEx sinking fund sits at rows 130–135 and can earn an investment return.
A53: 4. Asset Register tracks every annual acquisition cohort separately (rows 10–59 for value, 66–115 for gross rent), so each vintage carries its own purchase price, HPI revaluation and rent-inflation path. The CapEx sinking fund sits at rows 131–134.
A54: 5. Capital & Debt runs the three capital sources. The Tontine is a closed-end lifetime annuity mutual: SLC draws capital only during the investment phase and only up to the maximum raise, subject to the LTV limit. The principal is indexed to CPI each year and the coupon — derived from the target investor annuity rate plus the fund's operating cost margin and regulatory capital charge — is charged on the indexed balance. There is no principal repayment: from the release phase start year the fund progressively releases property charges, and the reduction is credited straight to reserves.
A55: 6. Financial Statements carries the 50-year P&L, balance sheet and cash flow. The CPI uplift on the Tontine principal is a non-cash finance charge (row 22) and the progressive release is a non-cash credit to reserves (row 42), so neither touches the cash flow. Row 46 is the balance-sheet integrity check and must read nil in every year.
A56: 8. Monthly Cash Flow phases Years 1–5 into 60 months using the timing parameters on Control. Row 36 reconciles each year's twelve months back to the annual cash flow and must read nil. Row 34 flags any month where free cash falls below the minimum operating cash buffer.
A57: 9. Gift Aid is claimed only on cash gifts from living donors. Bequests from estates are excluded, as they fall under inheritance tax rules rather than Gift Aid. The two are separate parameters on Control.
A65: CHART DATA (grouped — expand to inspect)
A67: Year | B67: 1 | C67: 2 | D67: 3 | E67: 4 | F67: 5 | G67: 6 | H67: 7 | I67: 8 | J67: 9 | K67: 10 | L67: 11 | M67: 12 | N67: 13 | O67: 14 | P67: 15 | Q67: 16 | R67: 17 | S67: 18 | T67: 19 | U67: 20 | V67: 21 | W67: 22 | X67: 23 | Y67: 24 | Z67: 25 | AA67: 26 | AB67: 27 | AC67: 28 | AD67: 29 | AE67: 30 | AF67: 31 | AG67: 32 | AH67: 33 | AI67: 34 | AJ67: 35 | AK67: 36 | AL67: 37 | AM67: 38 | AN67: 39 | AO67: 40 | AP67: 41 | AQ67: 42 | AR67: 43 | AS67: 44 | AT67: 45 | AU67: 46 | AV67: 47 | AW67: 48 | AX67: 49 | AY67: 50
A68: Portfolio value | B68: ='Asset Register'!D61 -> 280000 | C68: ='Asset Register'!E61 -> 869400 | D68: ='Asset Register'!F61 -> 1799658 | E68: ='Asset Register'!G61 -> 2793969 | F68: ='Asset Register'!H61 -> 3855677.3 | G68: ='Asset Register'!I61 -> 4988282.5 | H68: ='Asset Register'!J61 -> 6195446.8 | I68: ='Asset Register'!K61 -> 7481002.1 | ... AY68: ='Asset Register'!BA61 -> 74034006
A69: Total debt outstanding | B69: ='Capital & Debt'!D56 -> 53300 | C69: ='Capital & Debt'!E56 -> 465436.71 | D69: ='Capital & Debt'!F56 -> 1165357 | E69: ='Capital & Debt'!G56 -> 1860651.5 | F69: ='Capital & Debt'!H56 -> 2631621.6 | G69: ='Capital & Debt'!I56 -> 3451190.3 | H69: ='Capital & Debt'!J56 -> 4336812.8 | I69: ='Capital & Debt'!K56 -> 5236701.4 | ... AY69: ='Capital & Debt'!BA56 -> 3875803.9
A71: Year | B71: 1 | C71: 2 | D71: 3 | E71: 4 | F71: 5 | G71: 6 | H71: 7 | I71: 8 | J71: 9 | K71: 10 | L71: 11 | M71: 12 | N71: 13 | O71: 14 | P71: 15 | Q71: 16 | R71: 17 | S71: 18 | T71: 19 | U71: 20 | V71: 21 | W71: 22 | X71: 23 | Y71: 24 | Z71: 25 | AA71: 26 | AB71: 27 | AC71: 28 | AD71: 29 | AE71: 30 | AF71: 31 | AG71: 32 | AH71: 33 | AI71: 34 | AJ71: 35 | AK71: 36 | AL71: 37 | AM71: 38 | AN71: 39 | AO71: 40 | AP71: 41 | AQ71: 42 | AR71: 43 | AS71: 44 | AT71: 45 | AU71: 46 | AV71: 47 | AW71: 48 | AX71: 49 | AY71: 50
A72: Net rental income | B72: ='Financial Statements'!D10 -> 10640 | C72: ='Financial Statements'!E10 -> 32930.8 | D72: ='Financial Statements'!F10 -> 67947.572 | E72: ='Financial Statements'!G10 -> 105036.54 | F72: ='Financial Statements'!H10 -> 144291.38 | G72: ='Financial Statements'!I10 -> 185809.61 | H72: ='Financial Statements'!J10 -> 229692.69 | I72: ='Financial Statements'!K10 -> 276046.16 | ... AY72: ='Financial Statements'!BA10 -> 2144928.1
A73: Total debt service | B73: ='Capital & Debt'!D55 -> 1665.625 | C73: ='Capital & Debt'!E55 -> 16252.163 | D73: ='Capital & Debt'!F55 -> 51325.925 | E73: ='Capital & Debt'!G55 -> 95473.199 | F73: ='Capital & Debt'!H55 -> 141837.17 | G73: ='Capital & Debt'!I55 -> 192143.83 | H73: ='Capital & Debt'!J55 -> 246071.34 | I73: ='Capital & Debt'!K55 -> 302560.45 | ... AY73: ='Capital & Debt'!BA55 -> 257699.73
A74: Free cash / reserves | B74: ='Financial Statements'!D65 -> 26824.375 | C74: ='Financial Statements'!E65 -> 26129.262 | D74: ='Financial Statements'!F65 -> 10605.976 | E74: ='Financial Statements'!G65 -> -14514.878 | F74: ='Financial Statements'!H65 -> -23275.537 | G74: ='Financial Statements'!I65 -> -27162.479 | H74: ='Financial Statements'!J65 -> -23343.824 | I74: ='Financial Statements'!K65 -> -62488.728 | ... AY74: ='Financial Statements'!BA65 -> 2677875.3

Sheet Monthly Cash Flow
A1: STROUD LAND COMMONS — MONTHLY CASH FLOW, YEARS 1–5
A2: Phasing of the annual cash flow. Rent, gifts, admin, maintenance, issuance costs and share flows accrue evenly each month. Debt service is paid at the frequency set on Control. Acquisitions, the related purchase price and the matching Tontine drawdown all fall in the acquisition month. Dividends and tax are paid in the month set on Control. Row 33 reconciles each year's twelve months back to the annual cash flow statement and must read nil.
A6: Month | B6: month | D6: =1 -> 1 | E6: =2 -> 2 | F6: =3 -> 3 | G6: =4 -> 4 | H6: =5 -> 5 | I6: =6 -> 6 | J6: =7 -> 7 | K6: =8 -> 8 | L6: =9 -> 9 | M6: =10 -> 10 | N6: =11 -> 11 | O6: =12 -> 12 | P6: =13 -> 13 | Q6: =14 -> 14 | R6: =15 -> 15 | S6: =16 -> 16 | T6: =17 -> 17 | U6: =18 -> 18 | V6: =19 -> 19 | W6: =20 -> 20 | X6: =21 -> 21 | Y6: =22 -> 22 | Z6: =23 -> 23 | AA6: =24 -> 24 | AB6: =25 -> 25 | AC6: =26 -> 26 | AD6: =27 -> 27 | AE6: =28 -> 28 | AF6: =29 -> 29 | AG6: =30 -> 30 | AH6: =31 -> 31 | AI6: =32 -> 32 | AJ6: =33 -> 33 | AK6: =34 -> 34 | AL6: =35 -> 35 | AM6: =36 -> 36 | AN6: =37 -> 37 | AO6: =38 -> 38 | AP6: =39 -> 39 | AQ6: =40 -> 40 | AR6: =41 -> 41 | AS6: =42 -> 42 | AT6: =43 -> 43 | AU6: =44 -> 44 | AV6: =45 -> 45 | AW6: =46 -> 46 | AX6: =47 -> 47 | AY6: =48 -> 48 | AZ6: =49 -> 49 | BA6: =50 -> 50 | BB6: =51 -> 51 | BC6: =52 -> 52 | BD6: =53 -> 53 | BE6: =54 -> 54 | BF6: =55 -> 55 | BG6: =56 -> 56 | BH6: =57 -> 57 | BI6: =58 -> 58 | BJ6: =59 -> 59 | BK6: =60 -> 60
A7: Model year | B7: year | D7: =INT((D$6-1)/12)+1 -> 1 | E7: =INT((E$6-1)/12)+1 -> 1 | F7: =INT((F$6-1)/12)+1 -> 1 | G7: =INT((G$6-1)/12)+1 -> 1 | H7: =INT((H$6-1)/12)+1 -> 1 | I7: =INT((I$6-1)/12)+1 -> 1 | J7: =INT((J$6-1)/12)+1 -> 1 | K7: =INT((K$6-1)/12)+1 -> 1 | ... BK7: =INT((BK$6-1)/12)+1 -> 5
A8: Month in year | B8: month | D8: =D$6-12*(D$7-1) -> 1 | E8: =E$6-12*(E$7-1) -> 2 | F8: =F$6-12*(F$7-1) -> 3 | G8: =G$6-12*(G$7-1) -> 4 | H8: =H$6-12*(H$7-1) -> 5 | I8: =I$6-12*(I$7-1) -> 6 | J8: =J$6-12*(J$7-1) -> 7 | K8: =K$6-12*(K$7-1) -> 8 | ... BK8: =BK$6-12*(BK$7-1) -> 12
A10: RECEIPTS
A11: Rental income received | B11: £ | D11: {=INDEX('Financial Statements'!$D$10:$BA$10,D$7)/12} -> 886.66667 | E11: {=INDEX('Financial Statements'!$D$10:$BA$10,E$7)/12} -> 886.66667 | F11: {=INDEX('Financial Statements'!$D$10:$BA$10,F$7)/12} -> 886.66667 | G11: {=INDEX('Financial Statements'!$D$10:$BA$10,G$7)/12} -> 886.66667 | H11: {=INDEX('Financial Statements'!$D$10:$BA$10,H$7)/12} -> 886.66667 | I11: {=INDEX('Financial Statements'!$D$10:$BA$10,I$7)/12} -> 886.66667 | J11: {=INDEX('Financial Statements'!$D$10:$BA$10,J$7)/12} -> 886.66667 | K11: {=INDEX('Financial Statements'!$D$10:$BA$10,K$7)/12} -> 886.66667 | ... BK11: {=INDEX('Financial Statements'!$D$10:$BA$10,BK$7)/12} -> 12024.282
A12: Cash gifts, bequests & Gift Aid | B12: £ | D12: {=(INDEX('Capital & Debt'!$D$10:$BA$10,D$7)+INDEX('Capital & Debt'!$D$11:$BA$11,D$7)+INDEX('Capital & Debt'!$D$13:$BA$13,D$7))/12} -> 9166.6667 | E12: {=(INDEX('Capital & Debt'!$D$10:$BA$10,E$7)+INDEX('Capital & Debt'!$D$11:$BA$11,E$7)+INDEX('Capital & Debt'!$D$13:$BA$13,E$7))/12} -> 9166.6667 | F12: {=(INDEX('Capital & Debt'!$D$10:$BA$10,F$7)+INDEX('Capital & Debt'!$D$11:$BA$11,F$7)+INDEX('Capital & Debt'!$D$13:$BA$13,F$7))/12} -> 9166.6667 | G12: {=(INDEX('Capital & Debt'!$D$10:$BA$10,G$7)+INDEX('Capital & Debt'!$D$11:$BA$11,G$7)+INDEX('Capital & Debt'!$D$13:$BA$13,G$7))/12} -> 9166.6667 | H12: {=(INDEX('Capital & Debt'!$D$10:$BA$10,H$7)+INDEX('Capital & Debt'!$D$11:$BA$11,H$7)+INDEX('Capital & Debt'!$D$13:$BA$13,H$7))/12} -> 9166.6667 | I12: {=(INDEX('Capital & Debt'!$D$10:$BA$10,I$7)+INDEX('Capital & Debt'!$D$11:$BA$11,I$7)+INDEX('Capital & Debt'!$D$13:$BA$13,I$7))/12} -> 9166.6667 | J12: {=(INDEX('Capital & Debt'!$D$10:$BA$10,J$7)+INDEX('Capital & Debt'!$D$11:$BA$11,J$7)+INDEX('Capital & Debt'!$D$13:$BA$13,J$7))/12} -> 9166.6667 | K12: {=(INDEX('Capital & Debt'!$D$10:$BA$10,K$7)+INDEX('Capital & Debt'!$D$11:$BA$11,K$7)+INDEX('Capital & Debt'!$D$13:$BA$13,K$7))/12} -> 9166.6667 | ... BK12: {=(INDEX('Capital & Debt'!$D$10:$BA$10,BK$7)+INDEX('Capital & Debt'!$D$11:$BA$11,BK$7)+INDEX('Capital & Debt'!$D$13:$BA$13,BK$7))/12} -> 10118.285
A13: Founding capital injection | B13: £ | D13: =IF(AND(D$7=1,D$8=1),founding_capital,0) -> 150000 | E13: =IF(AND(E$7=1,E$8=1),founding_capital,0) -> 0 | F13: =IF(AND(F$7=1,F$8=1),founding_capital,0) -> 0 | G13: =IF(AND(G$7=1,G$8=1),founding_capital,0) -> 0 | H13: =IF(AND(H$7=1,H$8=1),founding_capital,0) -> 0 | I13: =IF(AND(I$7=1,I$8=1),founding_capital,0) -> 0 | J13: =IF(AND(J$7=1,J$8=1),founding_capital,0) -> 0 | K13: =IF(AND(K$7=1,K$8=1),founding_capital,0) -> 0 | ... BK13: =IF(AND(BK$7=1,BK$8=1),founding_capital,0) -> 0
A14: Tontine capital drawn | B14: £ | D14: {=IF(D$8=acq_month,INDEX('Financial Statements'!$D$56:$BA$56,D$7),0)} -> 0 | E14: {=IF(E$8=acq_month,INDEX('Financial Statements'!$D$56:$BA$56,E$7),0)} -> 0 | F14: {=IF(F$8=acq_month,INDEX('Financial Statements'!$D$56:$BA$56,F$7),0)} -> 0 | G14: {=IF(G$8=acq_month,INDEX('Financial Statements'!$D$56:$BA$56,G$7),0)} -> 0 | H14: {=IF(H$8=acq_month,INDEX('Financial Statements'!$D$56:$BA$56,H$7),0)} -> 0 | I14: {=IF(I$8=acq_month,INDEX('Financial Statements'!$D$56:$BA$56,I$7),0)} -> 0 | J14: {=IF(J$8=acq_month,INDEX('Financial Statements'!$D$56:$BA$56,J$7),0)} -> 0 | K14: {=IF(K$8=acq_month,INDEX('Financial Statements'!$D$56:$BA$56,K$7),0)} -> 0 | ... BK14: {=IF(BK$8=acq_month,INDEX('Financial Statements'!$D$56:$BA$56,BK$7),0)} -> 724453.84
A15: Community shares issued | B15: £ | D15: {=INDEX('Financial Statements'!$D$57:$BA$57,D$7)/12} -> 0 | E15: {=INDEX('Financial Statements'!$D$57:$BA$57,E$7)/12} -> 0 | F15: {=INDEX('Financial Statements'!$D$57:$BA$57,F$7)/12} -> 0 | G15: {=INDEX('Financial Statements'!$D$57:$BA$57,G$7)/12} -> 0 | H15: {=INDEX('Financial Statements'!$D$57:$BA$57,H$7)/12} -> 0 | I15: {=INDEX('Financial Statements'!$D$57:$BA$57,I$7)/12} -> 0 | J15: {=INDEX('Financial Statements'!$D$57:$BA$57,J$7)/12} -> 0 | K15: {=INDEX('Financial Statements'!$D$57:$BA$57,K$7)/12} -> 0 | ... BK15: {=INDEX('Financial Statements'!$D$57:$BA$57,BK$7)/12} -> 16232.095
A17: PAYMENTS
A18: Admin costs | B18: £ | D18: {=INDEX('Financial Statements'!$D$14:$BA$14,D$7)/12} -> -470.83333 | E18: {=INDEX('Financial Statements'!$D$14:$BA$14,E$7)/12} -> -470.83333 | F18: {=INDEX('Financial Statements'!$D$14:$BA$14,F$7)/12} -> -470.83333 | G18: {=INDEX('Financial Statements'!$D$14:$BA$14,G$7)/12} -> -470.83333 | H18: {=INDEX('Financial Statements'!$D$14:$BA$14,H$7)/12} -> -470.83333 | I18: {=INDEX('Financial Statements'!$D$14:$BA$14,I$7)/12} -> -470.83333 | J18: {=INDEX('Financial Statements'!$D$14:$BA$14,J$7)/12} -> -470.83333 | K18: {=INDEX('Financial Statements'!$D$14:$BA$14,K$7)/12} -> -470.83333 | ... BK18: {=INDEX('Financial Statements'!$D$14:$BA$14,BK$7)/12} -> -2465.1821
A19: Structural maintenance | B19: £ | D19: {=INDEX('Financial Statements'!$D$16:$BA$16,D$7)/12} -> -58.333333 | E19: {=INDEX('Financial Statements'!$D$16:$BA$16,E$7)/12} -> -58.333333 | F19: {=INDEX('Financial Statements'!$D$16:$BA$16,F$7)/12} -> -58.333333 | G19: {=INDEX('Financial Statements'!$D$16:$BA$16,G$7)/12} -> -58.333333 | H19: {=INDEX('Financial Statements'!$D$16:$BA$16,H$7)/12} -> -58.333333 | I19: {=INDEX('Financial Statements'!$D$16:$BA$16,I$7)/12} -> -58.333333 | J19: {=INDEX('Financial Statements'!$D$16:$BA$16,J$7)/12} -> -58.333333 | K19: {=INDEX('Financial Statements'!$D$16:$BA$16,K$7)/12} -> -58.333333 | ... BK19: {=INDEX('Financial Statements'!$D$16:$BA$16,BK$7)/12} -> -772.66902
A20: Acquisition transaction costs | B20: £ | D20: {=IF(D$8=acq_month,INDEX('Financial Statements'!$D$15:$BA$15,D$7),0)} -> 0 | E20: {=IF(E$8=acq_month,INDEX('Financial Statements'!$D$15:$BA$15,E$7),0)} -> 0 | F20: {=IF(F$8=acq_month,INDEX('Financial Statements'!$D$15:$BA$15,F$7),0)} -> 0 | G20: {=IF(G$8=acq_month,INDEX('Financial Statements'!$D$15:$BA$15,G$7),0)} -> 0 | H20: {=IF(H$8=acq_month,INDEX('Financial Statements'!$D$15:$BA$15,H$7),0)} -> 0 | I20: {=IF(I$8=acq_month,INDEX('Financial Statements'!$D$15:$BA$15,I$7),0)} -> 0 | J20: {=IF(J$8=acq_month,INDEX('Financial Statements'!$D$15:$BA$15,J$7),0)} -> 0 | K20: {=IF(K$8=acq_month,INDEX('Financial Statements'!$D$15:$BA$15,K$7),0)} -> 0 | ... BK20: {=IF(BK$8=acq_month,INDEX('Financial Statements'!$D$15:$BA$15,BK$7),0)} -> -27484.941
A21: Share issuance / marketing costs | B21: £ | D21: {=INDEX('Financial Statements'!$D$17:$BA$17,D$7)/12} -> 0 | E21: {=INDEX('Financial Statements'!$D$17:$BA$17,E$7)/12} -> 0 | F21: {=INDEX('Financial Statements'!$D$17:$BA$17,F$7)/12} -> 0 | G21: {=INDEX('Financial Statements'!$D$17:$BA$17,G$7)/12} -> 0 | H21: {=INDEX('Financial Statements'!$D$17:$BA$17,H$7)/12} -> 0 | I21: {=INDEX('Financial Statements'!$D$17:$BA$17,I$7)/12} -> 0 | J21: {=INDEX('Financial Statements'!$D$17:$BA$17,J$7)/12} -> 0 | K21: {=INDEX('Financial Statements'!$D$17:$BA$17,K$7)/12} -> 0 | ... BK21: {=INDEX('Financial Statements'!$D$17:$BA$17,BK$7)/12} -> -811.60474
A22: Property purchases | B22: £ | D22: {=IF(D$8=acq_month,INDEX('Financial Statements'!$D$54:$BA$54,D$7),0)} -> 0 | E22: {=IF(E$8=acq_month,INDEX('Financial Statements'!$D$54:$BA$54,E$7),0)} -> 0 | F22: {=IF(F$8=acq_month,INDEX('Financial Statements'!$D$54:$BA$54,F$7),0)} -> 0 | G22: {=IF(G$8=acq_month,INDEX('Financial Statements'!$D$54:$BA$54,G$7),0)} -> 0 | H22: {=IF(H$8=acq_month,INDEX('Financial Statements'!$D$54:$BA$54,H$7),0)} -> 0 | I22: {=IF(I$8=acq_month,INDEX('Financial Statements'!$D$54:$BA$54,I$7),0)} -> 0 | J22: {=IF(J$8=acq_month,INDEX('Financial Statements'!$D$54:$BA$54,J$7),0)} -> 0 | K22: {=IF(K$8=acq_month,INDEX('Financial Statements'!$D$54:$BA$54,K$7),0)} -> 0 | ... BK22: {=IF(BK$8=acq_month,INDEX('Financial Statements'!$D$54:$BA$54,BK$7),0)} -> -963919.32
A23: Interest paid | B23: £ | D23: {=IF(MOD(D$8,12/debt_pay_freq)=0,INDEX('Financial Statements'!$D$50:$BA$50,D$7)/debt_pay_freq,0)} -> 0 | E23: {=IF(MOD(E$8,12/debt_pay_freq)=0,INDEX('Financial Statements'!$D$50:$BA$50,E$7)/debt_pay_freq,0)} -> 0 | F23: {=IF(MOD(F$8,12/debt_pay_freq)=0,INDEX('Financial Statements'!$D$50:$BA$50,F$7)/debt_pay_freq,0)} -> -416.40625 | G23: {=IF(MOD(G$8,12/debt_pay_freq)=0,INDEX('Financial Statements'!$D$50:$BA$50,G$7)/debt_pay_freq,0)} -> 0 | H23: {=IF(MOD(H$8,12/debt_pay_freq)=0,INDEX('Financial Statements'!$D$50:$BA$50,H$7)/debt_pay_freq,0)} -> 0 | I23: {=IF(MOD(I$8,12/debt_pay_freq)=0,INDEX('Financial Statements'!$D$50:$BA$50,I$7)/debt_pay_freq,0)} -> -416.40625 | J23: {=IF(MOD(J$8,12/debt_pay_freq)=0,INDEX('Financial Statements'!$D$50:$BA$50,J$7)/debt_pay_freq,0)} -> 0 | K23: {=IF(MOD(K$8,12/debt_pay_freq)=0,INDEX('Financial Statements'!$D$50:$BA$50,K$7)/debt_pay_freq,0)} -> 0 | ... BK23: {=IF(MOD(BK$8,12/debt_pay_freq)=0,INDEX('Financial Statements'!$D$50:$BA$50,BK$7)/debt_pay_freq,0)} -> -35459.292
A24: Commercial mortgage principal repaid | B24: £ | D24: {=IF(MOD(D$8,12/debt_pay_freq)=0,INDEX('Financial Statements'!$D$59:$BA$59,D$7)/debt_pay_freq,0)} -> 0 | E24: {=IF(MOD(E$8,12/debt_pay_freq)=0,INDEX('Financial Statements'!$D$59:$BA$59,E$7)/debt_pay_freq,0)} -> 0 | F24: {=IF(MOD(F$8,12/debt_pay_freq)=0,INDEX('Financial Statements'!$D$59:$BA$59,F$7)/debt_pay_freq,0)} -> 0 | G24: {=IF(MOD(G$8,12/debt_pay_freq)=0,INDEX('Financial Statements'!$D$59:$BA$59,G$7)/debt_pay_freq,0)} -> 0 | H24: {=IF(MOD(H$8,12/debt_pay_freq)=0,INDEX('Financial Statements'!$D$59:$BA$59,H$7)/debt_pay_freq,0)} -> 0 | I24: {=IF(MOD(I$8,12/debt_pay_freq)=0,INDEX('Financial Statements'!$D$59:$BA$59,I$7)/debt_pay_freq,0)} -> 0 | J24: {=IF(MOD(J$8,12/debt_pay_freq)=0,INDEX('Financial Statements'!$D$59:$BA$59,J$7)/debt_pay_freq,0)} -> 0 | K24: {=IF(MOD(K$8,12/debt_pay_freq)=0,INDEX('Financial Statements'!$D$59:$BA$59,K$7)/debt_pay_freq,0)} -> 0 | ... BK24: {=IF(MOD(BK$8,12/debt_pay_freq)=0,INDEX('Financial Statements'!$D$59:$BA$59,BK$7)/debt_pay_freq,0)} -> 0
A25: Community share dividends | B25: £ | D25: {=IF(D$8=div_month,INDEX('Financial Statements'!$D$51:$BA$51,D$7),0)} -> 0 | E25: {=IF(E$8=div_month,INDEX('Financial Statements'!$D$51:$BA$51,E$7),0)} -> 0 | F25: {=IF(F$8=div_month,INDEX('Financial Statements'!$D$51:$BA$51,F$7),0)} -> 0 | G25: {=IF(G$8=div_month,INDEX('Financial Statements'!$D$51:$BA$51,G$7),0)} -> 0 | H25: {=IF(H$8=div_month,INDEX('Financial Statements'!$D$51:$BA$51,H$7),0)} -> 0 | I25: {=IF(I$8=div_month,INDEX('Financial Statements'!$D$51:$BA$51,I$7),0)} -> 0 | J25: {=IF(J$8=div_month,INDEX('Financial Statements'!$D$51:$BA$51,J$7),0)} -> 0 | K25: {=IF(K$8=div_month,INDEX('Financial Statements'!$D$51:$BA$51,K$7),0)} -> 0 | ... BK25: {=IF(BK$8=div_month,INDEX('Financial Statements'!$D$51:$BA$51,BK$7),0)} -> -1278.9368
A26: Corporation tax | B26: £ | D26: {=IF(D$8=12,INDEX('Financial Statements'!$D$52:$BA$52,D$7),0)} -> 0 | E26: {=IF(E$8=12,INDEX('Financial Statements'!$D$52:$BA$52,E$7),0)} -> 0 | F26: {=IF(F$8=12,INDEX('Financial Statements'!$D$52:$BA$52,F$7),0)} -> 0 | G26: {=IF(G$8=12,INDEX('Financial Statements'!$D$52:$BA$52,G$7),0)} -> 0 | H26: {=IF(H$8=12,INDEX('Financial Statements'!$D$52:$BA$52,H$7),0)} -> 0 | I26: {=IF(I$8=12,INDEX('Financial Statements'!$D$52:$BA$52,I$7),0)} -> 0 | J26: {=IF(J$8=12,INDEX('Financial Statements'!$D$52:$BA$52,J$7),0)} -> 0 | K26: {=IF(K$8=12,INDEX('Financial Statements'!$D$52:$BA$52,K$7),0)} -> 0 | ... BK26: {=IF(BK$8=12,INDEX('Financial Statements'!$D$52:$BA$52,BK$7),0)} -> 0
A27: Community shares withdrawn | B27: £ | D27: {=INDEX('Financial Statements'!$D$58:$BA$58,D$7)/12} -> 0 | E27: {=INDEX('Financial Statements'!$D$58:$BA$58,E$7)/12} -> 0 | F27: {=INDEX('Financial Statements'!$D$58:$BA$58,F$7)/12} -> 0 | G27: {=INDEX('Financial Statements'!$D$58:$BA$58,G$7)/12} -> 0 | H27: {=INDEX('Financial Statements'!$D$58:$BA$58,H$7)/12} -> 0 | I27: {=INDEX('Financial Statements'!$D$58:$BA$58,I$7)/12} -> 0 | J27: {=INDEX('Financial Statements'!$D$58:$BA$58,J$7)/12} -> 0 | K27: {=INDEX('Financial Statements'!$D$58:$BA$58,K$7)/12} -> 0 | ... BK27: {=INDEX('Financial Statements'!$D$58:$BA$58,BK$7)/12} -> 0
A29: Net movement in cash | B29: £ | D29: =SUM(D11:D15)+SUM(D18:D27) -> 159524.17 | E29: =SUM(E11:E15)+SUM(E18:E27) -> 9524.1667 | F29: =SUM(F11:F15)+SUM(F18:F27) -> 9107.7604 | G29: =SUM(G11:G15)+SUM(G18:G27) -> 9524.1667 | H29: =SUM(H11:H15)+SUM(H18:H27) -> 9524.1667 | I29: =SUM(I11:I15)+SUM(I18:I27) -> 9107.7604 | J29: =SUM(J11:J15)+SUM(J18:J27) -> 9524.1667 | K29: =SUM(K11:K15)+SUM(K18:K27) -> 9524.1667 | ... BK29: =SUM(BK11:BK15)+SUM(BK18:BK27) -> -269363.44
A30: Cash — opening | B30: £ | D30: =0 -> 0 | E30: =D31 -> 159524.17 | F30: =E31 -> 169048.33 | G30: =F31 -> 178156.09 | H30: =G31 -> 187680.26 | I30: =H31 -> 197204.43 | J30: =I31 -> 206312.19 | K30: =J31 -> 215836.35 | L30: =K31 -> 225360.52 | ... BK30: =BJ31 -> 272741.12
A31: Cash — closing (total) | B31: £ | D31: =D30+D29 -> 159524.17 | E31: =E30+E29 -> 169048.33 | F31: =F30+F29 -> 178156.09 | G31: =G30+G29 -> 187680.26 | H31: =H30+H29 -> 197204.43 | I31: =I30+I29 -> 206312.19 | J31: =J30+J29 -> 215836.35 | K31: =K30+K29 -> 225360.52 | ... BK31: =BK30+BK29 -> 3377.6788
A32: Less: CapEx sinking fund earmarked (pro-rated) | B32: £ | D32: {=-INDEX('Asset Register'!$D$135:$BA$135,D$7)*D$8/12} -> -66.666667 | E32: {=-INDEX('Asset Register'!$D$135:$BA$135,E$7)*E$8/12} -> -133.33333 | F32: {=-INDEX('Asset Register'!$D$135:$BA$135,F$7)*F$8/12} -> -200 | G32: {=-INDEX('Asset Register'!$D$135:$BA$135,G$7)*G$8/12} -> -266.66667 | H32: {=-INDEX('Asset Register'!$D$135:$BA$135,H$7)*H$8/12} -> -333.33333 | I32: {=-INDEX('Asset Register'!$D$135:$BA$135,I$7)*I$8/12} -> -400 | J32: {=-INDEX('Asset Register'!$D$135:$BA$135,J$7)*J$8/12} -> -466.66667 | K32: {=-INDEX('Asset Register'!$D$135:$BA$135,K$7)*K$8/12} -> -533.33333 | ... BK32: {=-INDEX('Asset Register'!$D$135:$BA$135,BK$7)*BK$8/12} -> -26653.216
A33: Free cash — closing | B33: £ | D33: =D31+D32 -> 159457.5 | E33: =E31+E32 -> 168915 | F33: =F31+F32 -> 177956.09 | G33: =G31+G32 -> 187413.59 | H33: =H31+H32 -> 196871.09 | I33: =I31+I32 -> 205912.19 | J33: =J31+J32 -> 215369.69 | K33: =K31+K32 -> 224827.19 | ... BK33: =BK31+BK32 -> -23275.537
A34: Below minimum operating cash buffer? | D34: =IF(D33<min_cash_buffer,"BREACH","OK") -> OK | E34: =IF(E33<min_cash_buffer,"BREACH","OK") -> OK | F34: =IF(F33<min_cash_buffer,"BREACH","OK") -> OK | G34: =IF(G33<min_cash_buffer,"BREACH","OK") -> OK | H34: =IF(H33<min_cash_buffer,"BREACH","OK") -> OK | I34: =IF(I33<min_cash_buffer,"BREACH","OK") -> OK | J34: =IF(J33<min_cash_buffer,"BREACH","OK") -> OK | K34: =IF(K33<min_cash_buffer,"BREACH","OK") -> OK | ... BK34: =IF(BK33<min_cash_buffer,"BREACH","OK") -> BREACH
A36: CHECK: 12 months vs annual cash flow (nil expected) | B36: £ | D36: {=IF(D$8=12,ROUND(SUMIF($D$7:$BK$7,D$7,$D$29:$BK$29)-INDEX('Financial Statements'!$D$61:$BA$61,D$7),2),"")} | E36: {=IF(E$8=12,ROUND(SUMIF($D$7:$BK$7,E$7,$D$29:$BK$29)-INDEX('Financial Statements'!$D$61:$BA$61,E$7),2),"")} | F36: {=IF(F$8=12,ROUND(SUMIF($D$7:$BK$7,F$7,$D$29:$BK$29)-INDEX('Financial Statements'!$D$61:$BA$61,F$7),2),"")} | G36: {=IF(G$8=12,ROUND(SUMIF($D$7:$BK$7,G$7,$D$29:$BK$29)-INDEX('Financial Statements'!$D$61:$BA$61,G$7),2),"")} | H36: {=IF(H$8=12,ROUND(SUMIF($D$7:$BK$7,H$7,$D$29:$BK$29)-INDEX('Financial Statements'!$D$61:$BA$61,H$7),2),"")} | I36: {=IF(I$8=12,ROUND(SUMIF($D$7:$BK$7,I$7,$D$29:$BK$29)-INDEX('Financial Statements'!$D$61:$BA$61,I$7),2),"")} | J36: {=IF(J$8=12,ROUND(SUMIF($D$7:$BK$7,J$7,$D$29:$BK$29)-INDEX('Financial Statements'!$D$61:$BA$61,J$7),2),"")} | K36: {=IF(K$8=12,ROUND(SUMIF($D$7:$BK$7,K$7,$D$29:$BK$29)-INDEX('Financial Statements'!$D$61:$BA$61,K$7),2),"")} | ... BK36: {=IF(BK$8=12,ROUND(SUMIF($D$7:$BK$7,BK$7,$D$29:$BK$29)-INDEX('Financial Statements'!$D$61:$BA$61,BK$7),2),"")} -> 0
